Workbook
Name UPDATE: 'Data Sheet'!$E$1

Sheet Profit & Loss
A1: ='Data Sheet'!B1 -> OIL & NATURAL GAS CORPN LTD | H1: =UPDATE | M1: SCREENER.IN
A3: Narration | B3: ='Data Sheet'!B16 -> 42094 | C3: ='Data Sheet'!C16 -> 42460 | D3: ='Data Sheet'!D16 -> 42825 | E3: ='Data Sheet'!E16 -> 43190 | F3: ='Data Sheet'!F16 -> 43555 | G3: ='Data Sheet'!G16 -> 43921 | H3: ='Data Sheet'!H16 -> 44286 | I3: ='Data Sheet'!I16 -> 44651 | ... K3: ='Data Sheet'!K16 -> 45382 | L3: Trailing | M3: Best Case | N3: Worst Case
A4: Sales | B4: ='Data Sheet'!B17 -> 160922.64 | C4: ='Data Sheet'!C17 -> 124035.71 | D4: ='Data Sheet'!D17 -> 282506.11 | E4: ='Data Sheet'!E17 -> 322705.76 | F4: ='Data Sheet'!F17 -> 421623.93 | G4: ='Data Sheet'!G17 -> 396727.91 | H4: ='Data Sheet'!H17 -> 303848.91 | I4: ='Data Sheet'!I17 -> 491246.24 | ... K4: ='Data Sheet'!K17 -> 591396.26 | L4: =SUM(Quarters!H4:K4) -> 659221.21 | M4: =$K4+M23*K4 -> 738389.54 | N4: =$K4+N23*L4 -> 637552.93
A5: Expenses | B5: =SUM('Data Sheet'!B18,'Data Sheet'!B20:B24, -1*'Data Sheet'!B19) -> 118610.32 | C5: =SUM('Data Sheet'!C18,'Data Sheet'!C20:C24, -1*'Data Sheet'!C19) -> 84901.08 | D5: =SUM('Data Sheet'!D18,'Data Sheet'!D20:D24, -1*'Data Sheet'!D19) -> 229702.44 | E5: =SUM('Data Sheet'!E18,'Data Sheet'!E20:E24, -1*'Data Sheet'!E19) -> 265816.7 | F5: =SUM('Data Sheet'!F18,'Data Sheet'!F20:F24, -1*'Data Sheet'!F19) -> 346804.94 | G5: =SUM('Data Sheet'!G18,'Data Sheet'!G20:G24, -1*'Data Sheet'!G19) -> 344622.93 | H5: =SUM('Data Sheet'!H18,'Data Sheet'!H20:H24, -1*'Data Sheet'!H19) -> 254375.47 | I5: =SUM('Data Sheet'!I18,'Data Sheet'!I20:I24, -1*'Data Sheet'!I19) -> 411372.65 | ... K5: =SUM('Data Sheet'!K18,'Data Sheet'!K20:K24, -1*'Data Sheet'!K19) -> 488560.82 | L5: =SUM(Quarters!H5:K5) -> 569596.7 | M5: =M4-M6 -> 627202.28 | N5: =N4-N6 -> 550874.33
A6: Operating Profit | B6: =B4-B5 -> 42312.32 | C6: =C4-C5 -> 39134.63 | D6: =D4-D5 -> 52803.67 | E6: =E4-E5 -> 56889.06 | F6: =F4-F5 -> 74818.99 | G6: =G4-G5 -> 52104.98 | H6: =H4-H5 -> 49473.44 | I6: =I4-I5 -> 79873.59 | ... K6: =K4-K5 -> 102835.44 | L6: =SUM(Quarters!H6:K6) -> 89624.51 | M6: =M4*M24 -> 111187.26 | N6: =N4*N24 -> 86678.596
A7: Other Income | B7: ='Data Sheet'!B25 -> 5954.76 | C7: ='Data Sheet'!C25 -> 1067.26 | D7: ='Data Sheet'!D25 -> 12724.18 | E7: ='Data Sheet'!E25 -> 10429.39 | F7: ='Data Sheet'!F25 -> 9567.1 | G7: ='Data Sheet'!G25 -> 981.69 | H7: ='Data Sheet'!H25 -> 11270.51 | I7: ='Data Sheet'!I25 -> 6796.72 | ... K7: ='Data Sheet'!K25 -> 12981.54 | L7: =SUM(Quarters!H7:K7) -> 12738.76 | M7: 0 | N7: 0
A8: Depreciation | B8: ='Data Sheet'!B26 -> 18032.97 | C8: ='Data Sheet'!C26 -> 16384.06 | D8: ='Data Sheet'!D26 -> 20219.2 | E8: ='Data Sheet'!E26 -> 23111.91 | F8: ='Data Sheet'!F26 -> 23703.7 | G8: ='Data Sheet'!G26 -> 26634.88 | H8: ='Data Sheet'!H26 -> 25538.47 | I8: ='Data Sheet'!I26 -> 26883.16 | ... K8: ='Data Sheet'!K26 -> 28762.75 | L8: =SUM(Quarters!H8:K8) -> 34025.55 | M8: =+$L8 -> 34025.55 | N8: =+$L8 -> 34025.55
A9: Interest | B9: ='Data Sheet'!B27 -> 2863.75 | C9: ='Data Sheet'!C27 -> 3765.58 | D9: ='Data Sheet'!D27 -> 3591.11 | E9: ='Data Sheet'!E27 -> 4999.04 | F9: ='Data Sheet'!F27 -> 5836.73 | G9: ='Data Sheet'!G27 -> 7489.34 | H9: ='Data Sheet'!H27 -> 5079.03 | I9: ='Data Sheet'!I27 -> 5696.04 | ... K9: ='Data Sheet'!K27 -> 10194.17 | L9: =SUM(Quarters!H9:K9) -> 13717.4 | M9: =+$L9 -> 13717.4 | N9: =+$L9 -> 13717.4
A10: Profit before tax | B10: ='Data Sheet'!B28 -> 27370.36 | C10: ='Data Sheet'!C28 -> 20052.25 | D10: ='Data Sheet'!D28 -> 41717.54 | E10: ='Data Sheet'!E28 -> 39207.5 | F10: ='Data Sheet'!F28 -> 54845.66 | G10: ='Data Sheet'!G28 -> 18962.45 | H10: ='Data Sheet'!H28 -> 30126.45 | I10: ='Data Sheet'!I28 -> 54091.11 | ... K10: ='Data Sheet'!K28 -> 76860.06 | L10: =SUM(Quarters!H10:K10) -> 54620.32 | M10: =M6+M7-SUM(M8:M9) -> 63444.31 | N10: =N6+N7-SUM(N8:N9) -> 38935.646
A11: Tax | B11: ='Data Sheet'!B29 -> 9697.41 | C11: ='Data Sheet'!C29 -> 6950.7 | D11: ='Data Sheet'!D29 -> 12548.42 | E11: ='Data Sheet'!E29 -> 13139.52 | F11: ='Data Sheet'!F29 -> 20907.65 | G11: ='Data Sheet'!G29 -> 7506.19 | H11: ='Data Sheet'!H29 -> 8766.2 | I11: ='Data Sheet'!I29 -> 4797.04 | ... K11: ='Data Sheet'!K29 -> 19759.23 | L11: =SUM(Quarters!H11:K11) -> 13621.53 | M11: =IF($L10>0,$L11/$L10,0) -> 0.24938576 | N11: =IF($L10>0,$L11/$L10,0) -> 0.24938576
A12: Net profit | B12: ='Data Sheet'!B30 -> 18333.52 | C12: ='Data Sheet'!C30 -> 12875.21 | D12: ='Data Sheet'!D30 -> 24419.25 | E12: ='Data Sheet'!E30 -> 22105.93 | F12: ='Data Sheet'!F30 -> 30546.04 | G12: ='Data Sheet'!G30 -> 10803.6 | H12: ='Data Sheet'!H30 -> 16304.4 | I12: ='Data Sheet'!I30 -> 45522.11 | ... K12: ='Data Sheet'!K30 -> 49221.38 | L12: =SUM(Quarters!H12:K12) -> 39010.15 | M12: =M10-M11*M10 -> 47622.202 | N12: =N10-N11*N10 -> 29225.65
A13: EPS | B13: =IF('Data Sheet'!B93>0,B12/'Data Sheet'!B93,0) -> 14.286008 | C13: =IF('Data Sheet'!C93>0,C12/'Data Sheet'!C93,0) -> 10.032735 | D13: =IF('Data Sheet'!D93>0,D12/'Data Sheet'!D93,0) -> 19.028185 | E13: =IF('Data Sheet'!E93>0,E12/'Data Sheet'!E93,0) -> 17.225579 | F13: =IF('Data Sheet'!F93>0,F12/'Data Sheet'!F93,0) -> 24.280852 | G13: =IF('Data Sheet'!G93>0,G12/'Data Sheet'!G93,0) -> 8.5877125 | H13: =IF('Data Sheet'!H93>0,H12/'Data Sheet'!H93,0) -> 12.960263 | I13: =IF('Data Sheet'!I93>0,I12/'Data Sheet'!I93,0) -> 36.185234 | ... K13: =IF('Data Sheet'!K93>0,K12/'Data Sheet'!K93,0) -> 39.12576 | L13: =IF('Data Sheet'!$B6>0,'Profit & Loss'!L12/'Data Sheet'!$B6,0) -> 31.008954 | M13: =IF('Data Sheet'!$B6>0,'Profit & Loss'!M12/'Data Sheet'!$B6,0) -> 37.854627 | N13: =IF('Data Sheet'!$B6>0,'Profit & Loss'!N12/'Data Sheet'!$B6,0) -> 23.231309
A14: Price to earning | B14: =IF(B15>0,B15/B13,"") -> 14.295806 | C14: =IF(C15>0,C15/C13,"") -> 14.226429 | D14: =IF(D15>0,D15/D13,"") -> 9.7224198 | E14: =IF(E15>0,E15/E13,"") -> 10.321859 | F14: =IF(F15>0,F15/F13,"") -> 6.5792585 | G14: =IF(G15>0,G15/G13,"") -> 7.9532238 | H14: =IF(H15>0,H15/H13,"") -> 7.8817843 | I14: =IF(I15>0,I15/I13,"") -> 4.5294719 | ... K14: =IF(K15>0,K15/K13,"") -> 6.8509851 | L14: =IF(L13>0,L15/L13,0) -> 7.9767284 | M14: =M25 -> 7.9767284 | N14: =N25 -> 6.179751
A15: Price | B15: ='Data Sheet'!B90 -> 204.23 | C15: ='Data Sheet'!C90 -> 142.73 | D15: ='Data Sheet'!D90 -> 185 | E15: ='Data Sheet'!E90 -> 177.8 | F15: ='Data Sheet'!F90 -> 159.75 | G15: ='Data Sheet'!G90 -> 68.3 | H15: ='Data Sheet'!H90 -> 102.15 | I15: ='Data Sheet'!I90 -> 163.9 | ... K15: ='Data Sheet'!K90 -> 268.05 | L15: ='Data Sheet'!B8 -> 247.35 | M15: =M13*M14 -> 301.95607 | N15: =N13*N14 -> 143.5637
A17: RATIOS:
A18: Dividend Payout | B18: =IF('Data Sheet'!B30>0, 'Data Sheet'!B31/'Data Sheet'!B30, 0) -> 0.44332676 | C18: =IF('Data Sheet'!C30>0, 'Data Sheet'!C31/'Data Sheet'!C30, 0) -> 0.56482108 | D18: =IF('Data Sheet'!D30>0, 'Data Sheet'!D31/'Data Sheet'!D30, 0) -> 0.39678164 | E18: =IF('Data Sheet'!E30>0, 'Data Sheet'!E31/'Data Sheet'!E30, 0) -> 0.38315285 | F18: =IF('Data Sheet'!F30>0, 'Data Sheet'!F31/'Data Sheet'!F30, 0) -> 0.28829302 | G18: =IF('Data Sheet'!G30>0, 'Data Sheet'!G31/'Data Sheet'!G30, 0) -> 0.58222722 | H18: =IF('Data Sheet'!H30>0, 'Data Sheet'!H31/'Data Sheet'!H30, 0) -> 0.27777164 | I18: =IF('Data Sheet'!I30>0, 'Data Sheet'!I31/'Data Sheet'!I30, 0) -> 0.29017306 | ... K18: =IF('Data Sheet'!K30>0, 'Data Sheet'!K31/'Data Sheet'!K30, 0) -> 0.3130924
A19: OPM | B19: =IF(B6>0,B6/B4,0) -> 0.26293578 | C19: =IF(C6>0,C6/C4,0) -> 0.31551099 | D19: =IF(D6>0,D6/D4,0) -> 0.1869116 | E19: =IF(E6>0,E6/E4,0) -> 0.17628771 | F19: =IF(F6>0,F6/F4,0) -> 0.17745433 | G19: =IF(G6>0,G6/G4,0) -> 0.13133681 | H19: =IF(H6>0,H6/H4,0) -> 0.1628225 | I19: =IF(I6>0,I6/I4,0) -> 0.16259379 | ... L19: =IF(L6>0,L6/L4,0) -> 0.13595514
G22: TRENDS: | H22: 10 YEARS | I22: 7 YEARS | J22: 5 YEARS | K22: 3 YEARS | L22: RECENT | M22: BEST | N22: WORST
G23: Sales Growth | H23: =IF(B4=0,"",POWER($K4/B4,1/9)-1) -> 0.15559812 | I23: =IF(D4=0,"",POWER($K4/D4,1/7)-1) -> 0.11131153 | J23: =IF(F4=0,"",POWER($K4/F4,1/5)-1) -> 0.070016967 | K23: =IF(H4=0,"",POWER($K4/H4, 1/3)-1) -> 0.24855295 | L23: =IF(ISERROR(MAX(IF(J4=0,"",(K4-J4)/J4),IF(K4=0,"",(L4-K4)/K4))),"",MAX(IF(J4=0,"",(K4-J4)/J4),IF(K4=0,"",(L4-K4)/K4))) -> 0.11468613 | M23: =MAX(K23:L23) -> 0.24855295 | N23: =MIN(H23:L23) -> 0.070016967
G24: OPM | H24: =IF(SUM(B4:$K$4)=0,"",SUMPRODUCT(B19:$K$19,B4:$K$4)/SUM(B4:$K$4)) -> 0.16788891 | I24: =IF(SUM(E4:$K$4)=0,"",SUMPRODUCT(E19:$K$19,E4:$K$4)/SUM(E4:$K$4)) -> 0.15555296 | J24: =IF(SUM(G4:$K$4)=0,"",SUMPRODUCT(G19:$K$19,G4:$K$4)/SUM(G4:$K$4)) -> 0.14896 | K24: =IF(SUM(I4:$K$4)=0, "", SUMPRODUCT(I19:$K$19,I4:$K$4)/SUM(I4:$K$4)) -> 0.15058076 | L24: =L19 -> 0.13595514 | M24: =MAX(K24:L24) -> 0.15058076 | N24: =MIN(H24:L24) -> 0.13595514
G25: Price to Earning | H25: =IF(ISERROR(AVERAGEIF(B14:$L14,">0")),"",AVERAGEIF(B14:$L14,">0")) -> 8.6999804 | I25: =IF(ISERROR(AVERAGEIF(E14:$L14,">0")),"",AVERAGEIF(E14:$L14,">0")) -> 7.1818912 | J25: =IF(ISERROR(AVERAGEIF(G14:$L14,">0")),"",AVERAGEIF(G14:$L14,">0")) -> 6.7590021 | K25: =IF(ISERROR(AVERAGEIF(I14:$L14,">0")),"",AVERAGEIF(I14:$L14,">0")) -> 6.179751 | L25: =L14 -> 7.9767284 | M25: =MAX(K25:L25) -> 7.9767284 | N25: =MIN(H25:L25) -> 6.179751

Sheet Quarters
A1: ='Profit & Loss'!A1 -> OIL & NATURAL GAS CORPN LTD | E1: =UPDATE | J1: SCREENER.IN
A3: Narration | B3: ='Data Sheet'!B41 -> 44834 | C3: ='Data Sheet'!C41 -> 44926 | D3: ='Data Sheet'!D41 -> 45016 | E3: ='Data Sheet'!E41 -> 45107 | F3: ='Data Sheet'!F41 -> 45199 | G3: ='Data Sheet'!G41 -> 45291 | H3: ='Data Sheet'!H41 -> 45382 | I3: ='Data Sheet'!I41 -> 45473 | ... K3: ='Data Sheet'!K41 -> 45657
A4: Sales | B4: ='Data Sheet'!B42 -> 168656.12 | C4: ='Data Sheet'!C42 -> 169212.63 | D4: ='Data Sheet'!D42 -> 164066.72 | E4: ='Data Sheet'!E42 -> 163823.59 | F4: ='Data Sheet'!F42 -> 147613.68 | G4: ='Data Sheet'!G42 -> 167356.63 | H4: ='Data Sheet'!H42 -> 166770.63 | I4: ='Data Sheet'!I42 -> 168024.8 | ... K4: ='Data Sheet'!K42 -> 166096.68
A5: Expenses | B5: ='Data Sheet'!B43 -> 155310.59 | C5: ='Data Sheet'!C43 -> 147345.52 | D5: ='Data Sheet'!D43 -> 143527.29 | E5: ='Data Sheet'!E43 -> 133028.63 | F5: ='Data Sheet'!F43 -> 119533.64 | G5: ='Data Sheet'!G43 -> 146996.46 | H5: ='Data Sheet'!H43 -> 143545.42 | I5: ='Data Sheet'!I43 -> 146398.25 | ... K5: ='Data Sheet'!K43 -> 141818.62
A6: Operating Profit | B6: ='Data Sheet'!B50 -> 13345.53 | C6: ='Data Sheet'!C50 -> 21867.11 | D6: ='Data Sheet'!D50 -> 20539.43 | E6: ='Data Sheet'!E50 -> 30794.96 | F6: ='Data Sheet'!F50 -> 28080.04 | G6: ='Data Sheet'!G50 -> 20360.17 | H6: ='Data Sheet'!H50 -> 23225.21 | I6: ='Data Sheet'!I50 -> 21626.55 | ... K6: ='Data Sheet'!K50 -> 24278.06
A7: Other Income | B7: ='Data Sheet'!B44 -> 2314.59 | C7: ='Data Sheet'!C44 -> 2807.3 | D7: ='Data Sheet'!D44 -> -4786.26 | E7: ='Data Sheet'!E44 -> 3069.28 | F7: ='Data Sheet'!F44 -> 3672.87 | G7: ='Data Sheet'!G44 -> 4299.03 | H7: ='Data Sheet'!H44 -> 2548.87 | I7: ='Data Sheet'!I44 -> 3615.38 | ... K7: ='Data Sheet'!K44 -> 2411.09
A8: Depreciation | B8: ='Data Sheet'!B45 -> 4442.76 | C8: ='Data Sheet'!C45 -> 6784.01 | D8: ='Data Sheet'!D45 -> 6743.59 | E8: ='Data Sheet'!E45 -> 7078.28 | F8: ='Data Sheet'!F45 -> 7078.57 | G8: ='Data Sheet'!G45 -> 7494.27 | H8: ='Data Sheet'!H45 -> 7862.89 | I8: ='Data Sheet'!I45 -> 8456.43 | ... K8: ='Data Sheet'!K45 -> 9497.22
A9: Interest | B9: ='Data Sheet'!B46 -> 1992.94 | C9: ='Data Sheet'!C46 -> 2188.43 | D9: ='Data Sheet'!D46 -> 2068.11 | E9: ='Data Sheet'!E46 -> 2363.94 | F9: ='Data Sheet'!F46 -> 3243.32 | G9: ='Data Sheet'!G46 -> 3203.18 | H9: ='Data Sheet'!H46 -> 2682.77 | I9: ='Data Sheet'!I46 -> 3615.9 | ... K9: ='Data Sheet'!K46 -> 3669.74
A10: Profit before tax | B10: ='Data Sheet'!B47 -> 9224.42 | C10: ='Data Sheet'!C47 -> 15701.97 | D10: ='Data Sheet'!D47 -> 6941.47 | E10: ='Data Sheet'!E47 -> 24422.02 | F10: ='Data Sheet'!F47 -> 21431.02 | G10: ='Data Sheet'!G47 -> 13961.75 | H10: ='Data Sheet'!H47 -> 15228.42 | I10: ='Data Sheet'!I47 -> 13169.6 | ... K10: ='Data Sheet'!K47 -> 13522.19
A11: Tax | B11: ='Data Sheet'!B48 -> 2394.26 | C11: ='Data Sheet'!C48 -> 4036.73 | D11: ='Data Sheet'!D48 -> 463.24 | E11: ='Data Sheet'!E48 -> 6528.54 | F11: ='Data Sheet'!F48 -> 5259.72 | G11: ='Data Sheet'!G48 -> 3450.52 | H11: ='Data Sheet'!H48 -> 3701.89 | I11: ='Data Sheet'!I48 -> 3359.42 | ... K11: ='Data Sheet'!K48 -> 3738.55
A12: Net profit | B12: ='Data Sheet'!B49 -> 8299.37 | C12: ='Data Sheet'!C49 -> 11488.99 | D12: ='Data Sheet'!D49 -> 4492.25 | E12: ='Data Sheet'!E49 -> 14644.43 | F12: ='Data Sheet'!F49 -> 13703.38 | G12: ='Data Sheet'!G49 -> 10703.17 | H12: ='Data Sheet'!H49 -> 10107.36 | I12: ='Data Sheet'!I49 -> 10008.6 | ... K12: ='Data Sheet'!K49 -> 8621.69
A14: OPM | B14: =IF(B4>0,B6/B4,"") -> 0.079128644 | C14: =IF(C4>0,C6/C4,"") -> 0.12922859 | D14: =IF(D4>0,D6/D4,"") -> 0.1251895 | E14: =IF(E4>0,E6/E4,"") -> 0.18797635 | F14: =IF(F4>0,F6/F4,"") -> 0.19022654 | G14: =IF(G4>0,G6/G4,"") -> 0.12165739 | H14: =IF(H4>0,H6/H4,"") -> 0.13926439 | I14: =IF(I4>0,I6/I4,"") -> 0.12871046 | ... K14: =IF(K4>0,K6/K4,"") -> 0.14616824

Sheet Balance Sheet
A1: ='Profit & Loss'!A1 -> OIL & NATURAL GAS CORPN LTD | E1: =UPDATE | J1: SCREENER.IN
A3: Narration | B3: ='Data Sheet'!B56 -> 42094 | C3: ='Data Sheet'!C56 -> 42460 | D3: ='Data Sheet'!D56 -> 42825 | E3: ='Data Sheet'!E56 -> 43190 | F3: ='Data Sheet'!F56 -> 43555 | G3: ='Data Sheet'!G56 -> 43921 | H3: ='Data Sheet'!H56 -> 44286 | I3: ='Data Sheet'!I56 -> 44651 | ... K3: ='Data Sheet'!K56 -> 45382
A4: Equity Share Capital | B4: ='Data Sheet'!B57 -> 4277.76 | C4: ='Data Sheet'!C57 -> 4277.76 | D4: ='Data Sheet'!D57 -> 6416.63 | E4: ='Data Sheet'!E57 -> 6416.63 | F4: ='Data Sheet'!F57 -> 6290.15 | G4: ='Data Sheet'!G57 -> 6290.15 | H4: ='Data Sheet'!H57 -> 6290.14 | I4: ='Data Sheet'!I57 -> 6290.14 | ... K4: ='Data Sheet'!K57 -> 6290.14
A5: Reserves | B5: ='Data Sheet'!B58 -> 176176.64 | C5: ='Data Sheet'!C58 -> 193535.88 | D5: ='Data Sheet'!D58 -> 187968.59 | E5: ='Data Sheet'!E58 -> 197602.3 | F5: ='Data Sheet'!F58 -> 210644.5 | G5: ='Data Sheet'!G58 -> 198814.45 | H5: ='Data Sheet'!H58 -> 214690.85 | I5: ='Data Sheet'!I58 -> 253212.77 | ... K5: ='Data Sheet'!K58 -> 330780.09
A6: Borrowings | B6: ='Data Sheet'!B59 -> 53944.47 | C6: ='Data Sheet'!C59 -> 45500.17 | D6: ='Data Sheet'!D59 -> 80029.27 | E6: ='Data Sheet'!E59 -> 106549.94 | F6: ='Data Sheet'!F59 -> 107741.69 | G6: ='Data Sheet'!G59 -> 129472.52 | H6: ='Data Sheet'!H59 -> 133186.92 | I6: ='Data Sheet'!I59 -> 121985.86 | ... K6: ='Data Sheet'!K59 -> 153180.53
A7: Other Liabilities | B7: ='Data Sheet'!B60 -> 103447.69 | C7: ='Data Sheet'!C60 -> 98458.57 | D7: ='Data Sheet'!D60 -> 170110.83 | E7: ='Data Sheet'!E60 -> 148663.53 | F7: ='Data Sheet'!F60 -> 167666.95 | G7: ='Data Sheet'!G60 -> 173786.92 | H7: ='Data Sheet'!H60 -> 187579.74 | I7: ='Data Sheet'!I60 -> 201770.75 | ... K7: ='Data Sheet'!K60 -> 219523.17
A8: Total | B8: ='Data Sheet'!B61 -> 337846.56 | C8: ='Data Sheet'!C61 -> 341772.38 | D8: ='Data Sheet'!D61 -> 444525.32 | E8: ='Data Sheet'!E61 -> 459232.4 | F8: ='Data Sheet'!F61 -> 492343.29 | G8: ='Data Sheet'!G61 -> 508364.04 | H8: ='Data Sheet'!H61 -> 541747.65 | I8: ='Data Sheet'!I61 -> 583259.52 | ... K8: ='Data Sheet'!K61 -> 709773.93
A10: Net Block | B10: ='Data Sheet'!B62 -> 179932.96 | C10: ='Data Sheet'!C62 -> 166276.73 | D10: ='Data Sheet'!D62 -> 211125.43 | E10: ='Data Sheet'!E62 -> 226057.68 | F10: ='Data Sheet'!F62 -> 230390.7 | G10: ='Data Sheet'!G62 -> 243891.96 | H10: ='Data Sheet'!H62 -> 243746.36 | I10: ='Data Sheet'!I62 -> 254402.17 | ... K10: ='Data Sheet'!K62 -> 298454.36
A11: Capital Work in Progress | B11: ='Data Sheet'!B63 -> 63393.37 | C11: ='Data Sheet'!C63 -> 57668.48 | D11: ='Data Sheet'!D63 -> 59042.48 | E11: ='Data Sheet'!E63 -> 61511.87 | F11: ='Data Sheet'!F63 -> 69056.44 | G11: ='Data Sheet'!G63 -> 83832.4 | H11: ='Data Sheet'!H63 -> 100308.82 | I11: ='Data Sheet'!I63 -> 106719.23 | ... K11: ='Data Sheet'!K63 -> 116021.68
A12: Investments | B12: ='Data Sheet'!B64 -> 4749.14 | C12: ='Data Sheet'!C64 -> 33386.85 | D12: ='Data Sheet'!D64 -> 70745.67 | E12: ='Data Sheet'!E64 -> 67334.61 | F12: ='Data Sheet'!F64 -> 66908.92 | G12: ='Data Sheet'!G64 -> 56755.18 | H12: ='Data Sheet'!H64 -> 60320.36 | I12: ='Data Sheet'!I64 -> 66642.14 | ... K12: ='Data Sheet'!K64 -> 102207.2
A13: Other Assets | B13: ='Data Sheet'!B65 -> 89771.09 | C13: ='Data Sheet'!C65 -> 84440.32 | D13: ='Data Sheet'!D65 -> 103611.74 | E13: ='Data Sheet'!E65 -> 104328.24 | F13: ='Data Sheet'!F65 -> 125987.23 | G13: ='Data Sheet'!G65 -> 123884.5 | H13: ='Data Sheet'!H65 -> 137372.11 | I13: ='Data Sheet'!I65 -> 155495.98 | ... K13: ='Data Sheet'!K65 -> 193090.69
A14: Total | B14: ='Data Sheet'!B66 -> 337846.56 | C14: ='Data Sheet'!C66 -> 341772.38 | D14: ='Data Sheet'!D66 -> 444525.32 | E14: ='Data Sheet'!E66 -> 459232.4 | F14: ='Data Sheet'!F66 -> 492343.29 | G14: ='Data Sheet'!G66 -> 508364.04 | H14: ='Data Sheet'!H66 -> 541747.65 | I14: ='Data Sheet'!I66 -> 583259.52 | ... K14: ='Data Sheet'!K66 -> 709773.93
A16: Working Capital | B16: =B13-B7 -> -13676.6 | C16: =C13-C7 -> -14018.25 | D16: =D13-D7 -> -66499.09 | E16: =E13-E7 -> -44335.29 | F16: =F13-F7 -> -41679.72 | G16: =G13-G7 -> -49902.42 | H16: =H13-H7 -> -50207.63 | I16: =I13-I7 -> -46274.77 | ... K16: =K13-K7 -> -26432.48
A17: Debtors | B17: ='Data Sheet'!B67 -> 18815.82 | C17: ='Data Sheet'!C67 -> 8331.71 | D17: ='Data Sheet'!D67 -> 12547.12 | E17: ='Data Sheet'!E67 -> 13899.17 | F17: ='Data Sheet'!F67 -> 15396.46 | G17: ='Data Sheet'!G67 -> 9173.41 | H17: ='Data Sheet'!H67 -> 16015.83 | I17: ='Data Sheet'!I67 -> 19187.28 | ... K17: ='Data Sheet'!K67 -> 19762.95
A18: Inventory | B18: ='Data Sheet'!B68 -> 11354.86 | C18: ='Data Sheet'!C68 -> 10761.97 | D18: ='Data Sheet'!D68 -> 30555.38 | E18: ='Data Sheet'!E68 -> 31253.57 | F18: ='Data Sheet'!F68 -> 35949.41 | G18: ='Data Sheet'!G68 -> 34065.12 | H18: ='Data Sheet'!H68 -> 45735.85 | I18: ='Data Sheet'!I68 -> 55360.27 | ... K18: ='Data Sheet'!K68 -> 53255.24
A20: Debtor Days | B20: =IF('Profit & Loss'!B4>0,'Balance Sheet'!B17/('Profit & Loss'!B4/365),0) -> 42.67749 | C20: =IF('Profit & Loss'!C4>0,'Balance Sheet'!C17/('Profit & Loss'!C4/365),0) -> 24.517731 | D20: =IF('Profit & Loss'!D4>0,'Balance Sheet'!D17/('Profit & Loss'!D4/365),0) -> 16.210973 | E20: =IF('Profit & Loss'!E4>0,'Balance Sheet'!E17/('Profit & Loss'!E4/365),0) -> 15.720813 | F20: =IF('Profit & Loss'!F4>0,'Balance Sheet'!F17/('Profit & Loss'!F4/365),0) -> 13.328721 | G20: =IF('Profit & Loss'!G4>0,'Balance Sheet'!G17/('Profit & Loss'!G4/365),0) -> 8.4397759 | H20: =IF('Profit & Loss'!H4>0,'Balance Sheet'!H17/('Profit & Loss'!H4/365),0) -> 19.239095 | I20: =IF('Profit & Loss'!I4>0,'Balance Sheet'!I17/('Profit & Loss'!I4/365),0) -> 14.256307 | ... K20: =IF('Profit & Loss'!K4>0,'Balance Sheet'!K17/('Profit & Loss'!K4/365),0) -> 12.197366
A21: Inventory Turnover | B21: =IF('Balance Sheet'!B18>0,'Profit & Loss'!B4/'Balance Sheet'!B18,0) -> 14.172138 | C21: =IF('Balance Sheet'!C18>0,'Profit & Loss'!C4/'Balance Sheet'!C18,0) -> 11.525372 | D21: =IF('Balance Sheet'!D18>0,'Profit & Loss'!D4/'Balance Sheet'!D18,0) -> 9.2457076 | E21: =IF('Balance Sheet'!E18>0,'Profit & Loss'!E4/'Balance Sheet'!E18,0) -> 10.325405 | F21: =IF('Balance Sheet'!F18>0,'Profit & Loss'!F4/'Balance Sheet'!F18,0) -> 11.728257 | G21: =IF('Balance Sheet'!G18>0,'Profit & Loss'!G4/'Balance Sheet'!G18,0) -> 11.646162 | H21: =IF('Balance Sheet'!H18>0,'Profit & Loss'!H4/'Balance Sheet'!H18,0) -> 6.643561 | I21: =IF('Balance Sheet'!I18>0,'Profit & Loss'!I4/'Balance Sheet'!I18,0) -> 8.8736244 | ... K21: =IF('Balance Sheet'!K18>0,'Profit & Loss'!K4/'Balance Sheet'!K18,0) -> 11.10494
A23: Return on Equity | B23: =IF(SUM('Balance Sheet'!B4:B5)>0,'Profit & Loss'!B12/SUM('Balance Sheet'!B4:B5),"") -> 0.10159641 | C23: =IF(SUM('Balance Sheet'!C4:C5)>0,'Profit & Loss'!C12/SUM('Balance Sheet'!C4:C5),"") -> 0.065087574 | D23: =IF(SUM('Balance Sheet'!D4:D5)>0,'Profit & Loss'!D12/SUM('Balance Sheet'!D4:D5),"") -> 0.12562298 | E23: =IF(SUM('Balance Sheet'!E4:E5)>0,'Profit & Loss'!E12/SUM('Balance Sheet'!E4:E5),"") -> 0.10835235 | F23: =IF(SUM('Balance Sheet'!F4:F5)>0,'Profit & Loss'!F12/SUM('Balance Sheet'!F4:F5),"") -> 0.14080757 | G23: =IF(SUM('Balance Sheet'!G4:G5)>0,'Profit & Loss'!G12/SUM('Balance Sheet'!G4:G5),"") -> 0.052673611 | H23: =IF(SUM('Balance Sheet'!H4:H5)>0,'Profit & Loss'!H12/SUM('Balance Sheet'!H4:H5),"") -> 0.073781912 | I23: =IF(SUM('Balance Sheet'!I4:I5)>0,'Profit & Loss'!I12/SUM('Balance Sheet'!I4:I5),"") -> 0.17542042 | ... K23: =IF(SUM('Balance Sheet'!K4:K5)>0,'Profit & Loss'!K12/SUM('Balance Sheet'!K4:K5),"") -> 0.14602708
A24: Return on Capital Emp | C24: =IF((B4+B5+B6+C4+C5+C6)>0,('Profit & Loss'!C10+'Profit & Loss'!C9)*2/(B4+B5+B6+C4+C5+C6),"") -> 0.099716131 | D24: =IF((C4+C5+C6+D4+D5+D6)>0,('Profit & Loss'!D10+'Profit & Loss'!D9)*2/(C4+C5+C6+D4+D5+D6),"") -> 0.17502868 | E24: =IF((D4+D5+D6+E4+E5+E6)>0,('Profit & Loss'!E10+'Profit & Loss'!E9)*2/(D4+D5+D6+E4+E5+E6),"") -> 0.15113777 | F24: =IF((E4+E5+E6+F4+F5+F6)>0,('Profit & Loss'!F10+'Profit & Loss'!F9)*2/(E4+E5+E6+F4+F5+F6),"") -> 0.19105186 | G24: =IF((F4+F5+F6+G4+G5+G6)>0,('Profit & Loss'!G10+'Profit & Loss'!G9)*2/(F4+F5+F6+G4+G5+G6),"") -> 0.080247709 | H24: =IF((G4+G5+G6+H4+H5+H6)>0,('Profit & Loss'!H10+'Profit & Loss'!H9)*2/(G4+G5+G6+H4+H5+H6),"") -> 0.10223081 | I24: =IF((H4+H5+H6+I4+I5+I6)>0,('Profit & Loss'!I10+'Profit & Loss'!I9)*2/(H4+H5+H6+I4+I5+I6),"") -> 0.1625409 | J24: =IF((I4+I5+I6+J4+J5+J6)>0,('Profit & Loss'!J10+'Profit & Loss'!J9)*2/(I4+I5+I6+J4+J5+J6),"") -> 0.12665512 | K24: =IF((J4+J5+J6+K4+K5+K6)>0,('Profit & Loss'!K10+'Profit & Loss'!K9)*2/(J4+J5+J6+K4+K5+K6),"") -> 0.19066737

Sheet Cash Flow
A1: ='Balance Sheet'!A1 -> OIL & NATURAL GAS CORPN LTD | E1: =UPDATE | J1: SCREENER.IN
A3: Narration | B3: ='Data Sheet'!B81 -> 42094 | C3: ='Data Sheet'!C81 -> 42460 | D3: ='Data Sheet'!D81 -> 42825 | E3: ='Data Sheet'!E81 -> 43190 | F3: ='Data Sheet'!F81 -> 43555 | G3: ='Data Sheet'!G81 -> 43921 | H3: ='Data Sheet'!H81 -> 44286 | I3: ='Data Sheet'!I81 -> 44651 | ... K3: ='Data Sheet'!K81 -> 45382
A4: Cash from Operating Activity | B4: ='Data Sheet'!B82 -> 33950.42 | C4: ='Data Sheet'!C82 -> 46292.49 | D4: ='Data Sheet'!D82 -> 45780.48 | E4: ='Data Sheet'!E82 -> 56792.1 | F4: ='Data Sheet'!F82 -> 61457.6 | G4: ='Data Sheet'!G82 -> 70592.98 | H4: ='Data Sheet'!H82 -> 47185.19 | I4: ='Data Sheet'!I82 -> 78248.25 | ... K4: ='Data Sheet'!K82 -> 99262.69
A5: Cash from Investing Activity | B5: ='Data Sheet'!B83 -> -30058.33 | C5: ='Data Sheet'!C83 -> -38255.87 | D5: ='Data Sheet'!D83 -> -43814.55 | E5: ='Data Sheet'!E83 -> -66798.14 | F5: ='Data Sheet'!F83 -> -37131.63 | G5: ='Data Sheet'!G83 -> -53159.05 | H5: ='Data Sheet'!H83 -> -39141.15 | I5: ='Data Sheet'!I83 -> -41197.15 | ... K5: ='Data Sheet'!K83 -> -57203.42
A6: Cash from Financing Activity | B6: ='Data Sheet'!B84 -> -10640.78 | C6: ='Data Sheet'!C84 -> -8972 | D6: ='Data Sheet'!D84 -> -1867.05 | E6: ='Data Sheet'!E84 -> 9909.36 | F6: ='Data Sheet'!F84 -> -23324.5 | G6: ='Data Sheet'!G84 -> -16726.36 | H6: ='Data Sheet'!H84 -> -8239.48 | I6: ='Data Sheet'!I84 -> -35790.02 | ... K6: ='Data Sheet'!K84 -> -45650.29
A7: Net Cash Flow | B7: ='Data Sheet'!B85 -> -6748.68 | C7: ='Data Sheet'!C85 -> -935.38 | D7: ='Data Sheet'!D85 -> 98.87 | E7: ='Data Sheet'!E85 -> -96.69 | F7: ='Data Sheet'!F85 -> 1001.47 | G7: ='Data Sheet'!G85 -> 707.57 | H7: ='Data Sheet'!H85 -> -195.44 | I7: ='Data Sheet'!I85 -> 1261.09 | ... K7: ='Data Sheet'!K85 -> -3591.02

Sheet Customization
A1: How to use it?
A3: You can customize this workbook as you want.
B4: You can add custom formating, add conditional formating, add your own formulas… do ANYTHING.
B5: Please don't edit the "Data Sheet" only.
A7: After customization, you can upload this back on Screener.
B8: Upload on: | C8: https://www.screener.in/excel/
A10: Download your customized workbooks now onwards.
B11: Now whenever you will "Export to excel" from Screener, it will export your customized file.
A14: TESTING:
B15: This is a testing feature currently.
B16: You can report any formula errors on the worksheet at: support@screener.in

Sheet Historical FS
B2: ="Historical Financial Statement - "&'Profit & Loss'!A1 -> Historical Financial Statement - OIL & NATURAL GAS CORPN LTD
B3: Years | C3: =Annual[[#This Row],[Column2]] -> 42094 | D3: =Annual[[#This Row],[Column3]] -> 42460 | E3: =Annual[[#This Row],[Column4]] -> 42825 | F3: =Annual[[#This Row],[Column5]] -> 43190 | G3: =Annual[[#This Row],[Column6]] -> 43555 | H3: =Annual[[#This Row],[Column7]] -> 43921 | I3: =Annual[[#This Row],[Column8]] -> 44286 | J3: =Annual[[#This Row],[Column9]] -> 44651 | K3: =Annual[[#This Row],[Column10]] -> 45016 | L3: =Annual[[#This Row],[Column11]] -> 45382 | M3: LTM
A5: # | B5: Income Statement
B7: Sales | C7: =IFERROR('Profit & Loss'!B4,0) -> 160922.64 | D7: =IFERROR('Profit & Loss'!C4,0) -> 124035.71 | E7: =IFERROR('Profit & Loss'!D4,0) -> 282506.11 | F7: =IFERROR('Profit & Loss'!E4,0) -> 322705.76 | G7: =IFERROR('Profit & Loss'!F4,0) -> 421623.93 | H7: =IFERROR('Profit & Loss'!G4,0) -> 396727.91 | I7: =IFERROR('Profit & Loss'!H4,0) -> 303848.91 | J7: =IFERROR('Profit & Loss'!I4,0) -> 491246.24 | ... L7: =IFERROR('Profit & Loss'!K4,0) -> 591396.26 | M7: =IFERROR(SUM(Quarters!H4:K4),0) -> 659221.21
B8: Sales Growth(y-o-y) | C8: - | D8: =D7/C7 -1 -> -0.22922151 | E8: =E7/D7 -1 -> 1.2776192 | F8: =F7/E7 -1 -> 0.14229657 | G8: =G7/F7 -1 -> 0.30652744 | H8: =H7/G7 -1 -> -0.059047929 | I8: =I7/H7 -1 -> -0.23411259 | J8: =J7/I7 -1 -> 0.61674511 | K8: =K7/J7 -1 -> 0.28711658 | ... M8: =M7/L7 -1 -> 0.11468613
B10: COGS | C10: =IFERROR(SUM('Data Sheet'!B18,'Data Sheet'!B20:B22)-1*'Data Sheet'!B19,0) -> 82045.1 | D10: =IFERROR(SUM('Data Sheet'!C18,'Data Sheet'!C20:C22)-1*'Data Sheet'!C19,0) -> 56921.45 | E10: =IFERROR(SUM('Data Sheet'!D18,'Data Sheet'!D20:D22)-1*'Data Sheet'!D19,0) -> 203938.19 | F10: =IFERROR(SUM('Data Sheet'!E18,'Data Sheet'!E20:E22)-1*'Data Sheet'!E19,0) -> 237810.82 | G10: =IFERROR(SUM('Data Sheet'!F18,'Data Sheet'!F20:F22)-1*'Data Sheet'!F19,0) -> 309596.56 | H10: =IFERROR(SUM('Data Sheet'!G18,'Data Sheet'!G20:G22)-1*'Data Sheet'!G19,0) -> 309680.76 | I10: =IFERROR(SUM('Data Sheet'!H18,'Data Sheet'!H20:H22)-1*'Data Sheet'!H19,0) -> 231708.14 | J10: =IFERROR(SUM('Data Sheet'!I18,'Data Sheet'!I20:I22)-1*'Data Sheet'!I19,0) -> 377208.46 | ... L10: =IFERROR(SUM('Data Sheet'!K18,'Data Sheet'!K20:K22)-1*'Data Sheet'!K19,0) -> 453414.86 | M10: =IFERROR(SUM('Data Sheet'!H43:K43),0) -> 569596.7
B11: COGS % of sales | C11: =C10/C7 -> 0.50984187 | D11: =D10/D7 -> 0.45891179 | E11: =E10/E7 -> 0.72188948 | F11: =F10/F7 -> 0.73692772 | G11: =G10/G7 -> 0.73429551 | H11: =H10/H7 -> 0.78058728 | I11: =I10/I7 -> 0.76257683 | J11: =J10/J7 -> 0.76786025 | ... M11: =M10/M7 -> 0.86404486
B13: Gross Profit | C13: =C7-C10 -> 78877.54 | D13: =D7-D10 -> 67114.26 | E13: =E7-E10 -> 78567.92 | F13: =F7-F10 -> 84894.94 | G13: =G7-G10 -> 112027.37 | H13: =H7-H10 -> 87047.15 | I13: =I7-I10 -> 72140.77 | J13: =J7-J10 -> 114037.78 | ... M13: =M7-M10 -> 89624.51
B14: Gross Profit Margin % of sales | C14: =C13/C7 -> 0.49015813 | D14: =D13/D7 -> 0.54108821 | E14: =E13/E7 -> 0.27811052 | F14: =F13/F7 -> 0.26307228 | G14: =G13/G7 -> 0.26570449 | H14: =H13/H7 -> 0.21941272 | I14: =I13/I7 -> 0.23742317 | J14: =J13/J7 -> 0.23213975 | ... M14: =M13/M7 -> 0.13595514
B16: Selling and General Expenses | C16: =IFERROR(SUM('Data Sheet'!B23:B24),0) -> 36565.22 | D16: =IFERROR(SUM('Data Sheet'!C23:C24),0) -> 27979.63 | E16: =IFERROR(SUM('Data Sheet'!D23:D24),0) -> 25764.25 | F16: =IFERROR(SUM('Data Sheet'!E23:E24),0) -> 28005.88 | G16: =IFERROR(SUM('Data Sheet'!F23:F24),0) -> 37208.38 | H16: =IFERROR(SUM('Data Sheet'!G23:G24),0) -> 34942.17 | I16: =IFERROR(SUM('Data Sheet'!H23:H24),0) -> 22667.33 | J16: =IFERROR(SUM('Data Sheet'!I23:I24),0) -> 34164.19 | ... M16: =IFERROR(SUM('Data Sheet'!L23:L24),0) -> 0
B17: S&G Expenses % of sales | C17: =C16/C7 -> 0.22722235 | D17: =D16/D7 -> 0.22557721 | E17: =E16/E7 -> 0.091198912 | F17: =F16/F7 -> 0.086784568 | G17: =G16/G7 -> 0.088250162 | H17: =H16/H7 -> 0.088075906 | I17: =I16/I7 -> 0.074600663 | J17: =J16/J7 -> 0.069545957 | ... M17: =M16/M7 -> 0
B19: EBITDA | C19: =C13-C16 -> 42312.32 | D19: =D13-D16 -> 39134.63 | E19: =E13-E16 -> 52803.67 | F19: =F13-F16 -> 56889.06 | G19: =G13-G16 -> 74818.99 | H19: =H13-H16 -> 52104.98 | I19: =I13-I16 -> 49473.44 | J19: =J13-J16 -> 79873.59 | ... M19: =M13-M16 -> 89624.51
B20: EBITDA % of sales | C20: =C19/C7 -> 0.26293578 | D20: =D19/D7 -> 0.31551099 | E20: =E19/E7 -> 0.1869116 | F20: =F19/F7 -> 0.17628771 | G20: =G19/G7 -> 0.17745433 | H20: =H19/H7 -> 0.13133681 | I20: =I19/I7 -> 0.1628225 | J20: =J19/J7 -> 0.16259379 | ... M20: =M19/M7 -> 0.13595514
B22: Interest | C22: =IFERROR('Data Sheet'!B27,0) -> 2863.75 | D22: =IFERROR('Data Sheet'!C27,0) -> 3765.58 | E22: =IFERROR('Data Sheet'!D27,0) -> 3591.11 | F22: =IFERROR('Data Sheet'!E27,0) -> 4999.04 | G22: =IFERROR('Data Sheet'!F27,0) -> 5836.73 | H22: =IFERROR('Data Sheet'!G27,0) -> 7489.34 | I22: =IFERROR('Data Sheet'!H27,0) -> 5079.03 | J22: =IFERROR('Data Sheet'!I27,0) -> 5696.04 | ... L22: =IFERROR('Data Sheet'!K27,0) -> 10194.17 | M22: =IFERROR(SUM('Data Sheet'!H46:K46),0) -> 13717.4
B23: Interest % of sales | C23: =C22/C7 -> 0.017795818 | D23: =D22/D7 -> 0.030358838 | E23: =E22/E7 -> 0.012711619 | F23: =F22/F7 -> 0.015491016 | G23: =G22/G7 -> 0.01384345 | H23: =H22/H7 -> 0.018877774 | I23: =I22/I7 -> 0.016715643 | J23: =J22/J7 -> 0.011595081 | ... M23: =M22/M7 -> 0.020808493
B25: Depreciation | C25: =IFERROR('Data Sheet'!B26,0) -> 18032.97 | D25: =IFERROR('Data Sheet'!C26,0) -> 16384.06 | E25: =IFERROR('Data Sheet'!D26,0) -> 20219.2 | F25: =IFERROR('Data Sheet'!E26,0) -> 23111.91 | G25: =IFERROR('Data Sheet'!F26,0) -> 23703.7 | H25: =IFERROR('Data Sheet'!G26,0) -> 26634.88 | I25: =IFERROR('Data Sheet'!H26,0) -> 25538.47 | J25: =IFERROR('Data Sheet'!I26,0) -> 26883.16 | ... L25: =IFERROR('Data Sheet'!K26,0) -> 28762.75 | M25: =IFERROR(SUM('Data Sheet'!H45:K45),0) -> 34025.55
B26: Depreciation % of sales | C26: =C25/C7 -> 0.11205987 | D26: =D25/D7 -> 0.13209148 | E26: =E25/E7 -> 0.071570841 | F26: =F25/F7 -> 0.071619143 | G26: =G25/G7 -> 0.056220006 | H26: =H25/H7 -> 0.067136391 | I26: =I25/I7 -> 0.084049898 | J26: =J25/J7 -> 0.054724409 | ... M26: =M25/M7 -> 0.051614768
B28: EBT | C28: =IFERROR(C19-SUM(C25+C22),0) -> 21415.6 | D28: =IFERROR(D19-SUM(D25+D22),0) -> 18984.99 | E28: =IFERROR(E19-SUM(E25+E22),0) -> 28993.36 | F28: =IFERROR(F19-SUM(F25+F22),0) -> 28778.11 | G28: =IFERROR(G19-SUM(G25+G22),0) -> 45278.56 | H28: =IFERROR(H19-SUM(H25+H22),0) -> 17980.76 | I28: =IFERROR(I19-SUM(I25+I22),0) -> 18855.94 | J28: =IFERROR(J19-SUM(J25+J22),0) -> 47294.39 | ... L28: =IFERROR(L19-SUM(L25+L22),0) -> 63878.52 | M28: =IFERROR(SUM('Data Sheet'!H47:K47),0) -> 54620.32
B29: EBT % of sales | C29: =C28/C7 -> 0.13308009 | D29: =D28/D7 -> 0.15306068 | E29: =E28/E7 -> 0.10262914 | F29: =F28/F7 -> 0.089177553 | G29: =G28/G7 -> 0.10739087 | H29: =H28/H7 -> 0.045322649 | I29: =I28/I7 -> 0.062056961 | J29: =J28/J7 -> 0.096274304 | ... M29: =M28/M7 -> 0.082855829
B31: Tax | C31: =IFERROR('Data Sheet'!B29,0) -> 9697.41 | D31: =IFERROR('Data Sheet'!C29,0) -> 6950.7 | E31: =IFERROR('Data Sheet'!D29,0) -> 12548.42 | F31: =IFERROR('Data Sheet'!E29,0) -> 13139.52 | G31: =IFERROR('Data Sheet'!F29,0) -> 20907.65 | H31: =IFERROR('Data Sheet'!G29,0) -> 7506.19 | I31: =IFERROR('Data Sheet'!H29,0) -> 8766.2 | J31: =IFERROR('Data Sheet'!I29,0) -> 4797.04 | ... L31: =IFERROR('Data Sheet'!K29,0) -> 19759.23 | M31: =IFERROR(SUM('Data Sheet'!H29:K29),0) -> 43595.62
B32: Effective Tax Rate | C32: =C31/C28 -> 0.45281991 | D32: =D31/D28 -> 0.36611555 | E32: =E31/E28 -> 0.43280323 | F32: =F31/F28 -> 0.45658037 | G32: =G31/G28 -> 0.46175607 | H32: =H31/H28 -> 0.41745677 | I32: =I31/I28 -> 0.4649039 | J32: =J31/J28 -> 0.10142937 | ... M32: =M31/M28 -> 0.79815754
B34: Net Profit | C34: =C28-C31 -> 11718.19 | D34: =D28-D31 -> 12034.29 | E34: =E28-E31 -> 16444.94 | F34: =F28-F31 -> 15638.59 | G34: =G28-G31 -> 24370.91 | H34: =H28-H31 -> 10474.57 | I34: =I28-I31 -> 10089.74 | J34: =J28-J31 -> 42497.35 | ... M34: =M28-M31 -> 11024.7
B35: Net Margins | C35: =C34/C7 -> 0.072818778 | D35: =D34/D7 -> 0.097022785 | E35: =E34/E7 -> 0.058210918 | F35: =F34/F7 -> 0.048460833 | G35: =G34/G7 -> 0.057802483 | H35: =H34/H7 -> 0.026402403 | I35: =I34/I7 -> 0.033206438 | J35: =J34/J7 -> 0.086509263 | ... M35: =M34/M7 -> 0.016723825
B37: No of Equity Shares | C37: =IFERROR('Data Sheet'!B93,0) -> 1283.32 | D37: =IFERROR('Data Sheet'!C93,0) -> 1283.32 | E37: =IFERROR('Data Sheet'!D93,0) -> 1283.32 | F37: =IFERROR('Data Sheet'!E93,0) -> 1283.32 | G37: =IFERROR('Data Sheet'!F93,0) -> 1258.03 | H37: =IFERROR('Data Sheet'!G93,0) -> 1258.03 | I37: =IFERROR('Data Sheet'!H93,0) -> 1258.03 | J37: =IFERROR('Data Sheet'!I93,0) -> 1258.03 | ... M37: =IFERROR('Data Sheet'!L93,0) -> 0
B39: EPS | C39: =IFERROR(C34/C37,0) -> 9.131152 | D39: =IFERROR(D34/D37,0) -> 9.3774663 | E39: =IFERROR(E34/E37,0) -> 12.814372 | F39: =IFERROR(F34/F37,0) -> 12.186041 | G39: =IFERROR(G34/G37,0) -> 19.37228 | H39: =IFERROR(H34/H37,0) -> 8.3261687 | I39: =IFERROR(I34/I37,0) -> 8.0202698 | J39: =IFERROR(J34/J37,0) -> 33.780872 | ... M39: =IFERROR(M34/M37,0) -> 0
B40: EPS Growth Rate | D40: =D39/C39 -1 -> 0.026975156 | E40: =E39/D39 -1 -> 0.36650687 | F40: =F39/E39 -1 -> -0.04903332 | G40: =G39/F39 -1 -> 0.58971077 | H40: =H39/G39 -1 -> -0.57020193 | I40: =I39/H39 -1 -> -0.036739456 | J40: =J39/I39 -1 -> 3.2119371 | K40: =K39/J39 -1 -> -0.22801257 | ... M40: =M39/L39 -1 -> -1
B42: Dividend per Share | C42: =IFERROR('Data Sheet'!B31/C37,0) -> 6.3333697 | D42: =IFERROR('Data Sheet'!C31/D37,0) -> 5.6667004 | E42: =IFERROR('Data Sheet'!D31/E37,0) -> 7.5500343 | F42: =IFERROR('Data Sheet'!E31/F37,0) -> 6.6000296 | G42: =IFERROR('Data Sheet'!F31/G37,0) -> 7 | H42: =IFERROR('Data Sheet'!G31/H37,0) -> 5 | I42: =IFERROR('Data Sheet'!H31/I37,0) -> 3.5999936 | J42: =IFERROR('Data Sheet'!I31/J37,0) -> 10.49998 | ... M42: =IFERROR('Data Sheet'!L31/M37,0) -> 0
B43: Dividend payout ratio | C43: =C42/C39 -> 0.69360029 | D43: =D42/D39 -> 0.60428908 | E43: =E42/E39 -> 0.58918488 | F43: =F42/F39 -> 0.54160573 | G43: =G42/G39 -> 0.36134104 | H43: =H42/H39 -> 0.6005163 | I43: =I42/I39 -> 0.44886191 | J43: =J42/J39 -> 0.3108262 | ... M43: =M42/M39 -> #DIV/0!
B45: Retained Earnings | C45: =C39-C42 -> 2.7977823 | D45: =D39-D42 -> 3.7107658 | E45: =E39-E42 -> 5.2643378 | F45: =F39-F42 -> 5.5860113 | G45: =G39-G42 -> 12.37228 | H45: =H39-H42 -> 3.3261687 | I45: =I39-I42 -> 4.4202761 | J45: =J39-J42 -> 23.280892 | ... M45: =M39-M42 -> 0
C46: =C45/C39 -> 0.30639971 | D46: =D45/D39 -> 0.39571092 | E46: =E45/E39 -> 0.41081512 | F46: =F45/F39 -> 0.45839427 | G46: =G45/G39 -> 0.63865896 | H46: =H45/H39 -> 0.3994837 | I46: =I45/I39 -> 0.55113809 | J46: =J45/J39 -> 0.6891738 | ... M46: =M45/M39 -> #DIV/0!
A49: # | B49: Balance Sheet
B51: Equity Share Capital | C51: =IFERROR('Data Sheet'!B57,0) -> 4277.76 | D51: =IFERROR('Data Sheet'!C57,0) -> 4277.76 | E51: =IFERROR('Data Sheet'!D57,0) -> 6416.63 | F51: =IFERROR('Data Sheet'!E57,0) -> 6416.63 | G51: =IFERROR('Data Sheet'!F57,0) -> 6290.15 | H51: =IFERROR('Data Sheet'!G57,0) -> 6290.15 | I51: =IFERROR('Data Sheet'!H57,0) -> 6290.14 | J51: =IFERROR('Data Sheet'!I57,0) -> 6290.14 | ... L51: =IFERROR('Data Sheet'!K57,0) -> 6290.14
B52: Reserves | C52: =IFERROR('Data Sheet'!B58,0) -> 176176.64 | D52: =IFERROR('Data Sheet'!C58,0) -> 193535.88 | E52: =IFERROR('Data Sheet'!D58,0) -> 187968.59 | F52: =IFERROR('Data Sheet'!E58,0) -> 197602.3 | G52: =IFERROR('Data Sheet'!F58,0) -> 210644.5 | H52: =IFERROR('Data Sheet'!G58,0) -> 198814.45 | I52: =IFERROR('Data Sheet'!H58,0) -> 214690.85 | J52: =IFERROR('Data Sheet'!I58,0) -> 253212.77 | ... L52: =IFERROR('Data Sheet'!K58,0) -> 330780.09
B53: Borrowings | C53: =IFERROR('Data Sheet'!B59,0) -> 53944.47 | D53: =IFERROR('Data Sheet'!C59,0) -> 45500.17 | E53: =IFERROR('Data Sheet'!D59,0) -> 80029.27 | F53: =IFERROR('Data Sheet'!E59,0) -> 106549.94 | G53: =IFERROR('Data Sheet'!F59,0) -> 107741.69 | H53: =IFERROR('Data Sheet'!G59,0) -> 129472.52 | I53: =IFERROR('Data Sheet'!H59,0) -> 133186.92 | J53: =IFERROR('Data Sheet'!I59,0) -> 121985.86 | ... L53: =IFERROR('Data Sheet'!K59,0) -> 153180.53
B54: Other Liabilities | C54: =IFERROR('Data Sheet'!B60,0) -> 103447.69 | D54: =IFERROR('Data Sheet'!C60,0) -> 98458.57 | E54: =IFERROR('Data Sheet'!D60,0) -> 170110.83 | F54: =IFERROR('Data Sheet'!E60,0) -> 148663.53 | G54: =IFERROR('Data Sheet'!F60,0) -> 167666.95 | H54: =IFERROR('Data Sheet'!G60,0) -> 173786.92 | I54: =IFERROR('Data Sheet'!H60,0) -> 187579.74 | J54: =IFERROR('Data Sheet'!I60,0) -> 201770.75 | ... L54: =IFERROR('Data Sheet'!K60,0) -> 219523.17
B55: Total lIabilities | C55: =IFERROR('Data Sheet'!B61,0) -> 337846.56 | D55: =IFERROR('Data Sheet'!C61,0) -> 341772.38 | E55: =IFERROR('Data Sheet'!D61,0) -> 444525.32 | F55: =IFERROR('Data Sheet'!E61,0) -> 459232.4 | G55: =IFERROR('Data Sheet'!F61,0) -> 492343.29 | H55: =IFERROR('Data Sheet'!G61,0) -> 508364.04 | I55: =IFERROR('Data Sheet'!H61,0) -> 541747.65 | J55: =IFERROR('Data Sheet'!I61,0) -> 583259.52 | ... L55: =IFERROR('Data Sheet'!K61,0) -> 709773.93
B57: Fixed Assets Net Block | C57: =IFERROR('Data Sheet'!B62,0) -> 179932.96 | D57: =IFERROR('Data Sheet'!C62,0) -> 166276.73 | E57: =IFERROR('Data Sheet'!D62,0) -> 211125.43 | F57: =IFERROR('Data Sheet'!E62,0) -> 226057.68 | G57: =IFERROR('Data Sheet'!F62,0) -> 230390.7 | H57: =IFERROR('Data Sheet'!G62,0) -> 243891.96 | I57: =IFERROR('Data Sheet'!H62,0) -> 243746.36 | J57: =IFERROR('Data Sheet'!I62,0) -> 254402.17 | ... L57: =IFERROR('Data Sheet'!K62,0) -> 298454.36
B58: Capital Work in Progress | C58: =IFERROR('Data Sheet'!B63,0) -> 63393.37 | D58: =IFERROR('Data Sheet'!C63,0) -> 57668.48 | E58: =IFERROR('Data Sheet'!D63,0) -> 59042.48 | F58: =IFERROR('Data Sheet'!E63,0) -> 61511.87 | G58: =IFERROR('Data Sheet'!F63,0) -> 69056.44 | H58: =IFERROR('Data Sheet'!G63,0) -> 83832.4 | I58: =IFERROR('Data Sheet'!H63,0) -> 100308.82 | J58: =IFERROR('Data Sheet'!I63,0) -> 106719.23 | ... L58: =IFERROR('Data Sheet'!K63,0) -> 116021.68
B59: Investments | C59: =IFERROR('Data Sheet'!B64,0) -> 4749.14 | D59: =IFERROR('Data Sheet'!C64,0) -> 33386.85 | E59: =IFERROR('Data Sheet'!D64,0) -> 70745.67 | F59: =IFERROR('Data Sheet'!E64,0) -> 67334.61 | G59: =IFERROR('Data Sheet'!F64,0) -> 66908.92 | H59: =IFERROR('Data Sheet'!G64,0) -> 56755.18 | I59: =IFERROR('Data Sheet'!H64,0) -> 60320.36 | J59: =IFERROR('Data Sheet'!I64,0) -> 66642.14 | ... L59: =IFERROR('Data Sheet'!K64,0) -> 102207.2
B60: Other Assets | C60: =IFERROR('Data Sheet'!B65-SUM('Data Sheet'!B67:B69),0) -> 43503.49 | D60: =IFERROR('Data Sheet'!C65-SUM('Data Sheet'!C67:C69),0) -> 40657.6 | E60: =IFERROR('Data Sheet'!D65-SUM('Data Sheet'!D67:D69),0) -> 47296.6 | F60: =IFERROR('Data Sheet'!E65-SUM('Data Sheet'!E67:E69),0) -> 54112.66 | G60: =IFERROR('Data Sheet'!F65-SUM('Data Sheet'!F67:F69),0) -> 69821.7 | H60: =IFERROR('Data Sheet'!G65-SUM('Data Sheet'!G67:G69),0) -> 71005.73 | I60: =IFERROR('Data Sheet'!H65-SUM('Data Sheet'!H67:H69),0) -> 68428.17 | J60: =IFERROR('Data Sheet'!I65-SUM('Data Sheet'!I67:I69),0) -> 74107.49 | ... L60: =IFERROR('Data Sheet'!K65-SUM('Data Sheet'!K67:K69),0) -> 83382.86
B61: Total Non Current Assets | C61: =SUM(C57:C60) -> 291578.96 | D61: =SUM(D57:D60) -> 297989.66 | E61: =SUM(E57:E60) -> 388210.18 | F61: =SUM(F57:F60) -> 409016.82 | G61: =SUM(G57:G60) -> 436177.76 | H61: =SUM(H57:H60) -> 455485.27 | I61: =SUM(I57:I60) -> 472803.71 | J61: =SUM(J57:J60) -> 501871.03 | ... L61: =SUM(L57:L60) -> 600066.1
B63: Receivables | C63: =IFERROR('Data Sheet'!B67,0) -> 18815.82 | D63: =IFERROR('Data Sheet'!C67,0) -> 8331.71 | E63: =IFERROR('Data Sheet'!D67,0) -> 12547.12 | F63: =IFERROR('Data Sheet'!E67,0) -> 13899.17 | G63: =IFERROR('Data Sheet'!F67,0) -> 15396.46 | H63: =IFERROR('Data Sheet'!G67,0) -> 9173.41 | I63: =IFERROR('Data Sheet'!H67,0) -> 16015.83 | J63: =IFERROR('Data Sheet'!I67,0) -> 19187.28 | ... L63: =IFERROR('Data Sheet'!K67,0) -> 19762.95
B64: Inventory | C64: =IFERROR('Data Sheet'!B68,0) -> 11354.86 | D64: =IFERROR('Data Sheet'!C68,0) -> 10761.97 | E64: =IFERROR('Data Sheet'!D68,0) -> 30555.38 | F64: =IFERROR('Data Sheet'!E68,0) -> 31253.57 | G64: =IFERROR('Data Sheet'!F68,0) -> 35949.41 | H64: =IFERROR('Data Sheet'!G68,0) -> 34065.12 | I64: =IFERROR('Data Sheet'!H68,0) -> 45735.85 | J64: =IFERROR('Data Sheet'!I68,0) -> 55360.27 | ... L64: =IFERROR('Data Sheet'!K68,0) -> 53255.24
B65: Cash & Bank | C65: =IFERROR('Data Sheet'!B69,0) -> 16096.92 | D65: =IFERROR('Data Sheet'!C69,0) -> 24689.04 | E65: =IFERROR('Data Sheet'!D69,0) -> 13212.64 | F65: =IFERROR('Data Sheet'!E69,0) -> 5062.84 | G65: =IFERROR('Data Sheet'!F69,0) -> 4819.66 | H65: =IFERROR('Data Sheet'!G69,0) -> 9640.24 | I65: =IFERROR('Data Sheet'!H69,0) -> 7192.26 | J65: =IFERROR('Data Sheet'!I69,0) -> 6840.94 | ... L65: =IFERROR('Data Sheet'!K69,0) -> 36689.64
B66: Total Current Assets | C66: =SUM(C63:C65) -> 46267.6 | D66: =SUM(D63:D65) -> 43782.72 | E66: =SUM(E63:E65) -> 56315.14 | F66: =SUM(F63:F65) -> 50215.58 | G66: =SUM(G63:G65) -> 56165.53 | H66: =SUM(H63:H65) -> 52878.77 | I66: =SUM(I63:I65) -> 68943.94 | J66: =SUM(J63:J65) -> 81388.49 | ... L66: =SUM(L63:L65) -> 109707.83
B68: Total Assets | C68: =IFERROR(C66+C61,0) -> 337846.56 | D68: =IFERROR(D66+D61,0) -> 341772.38 | E68: =IFERROR(E66+E61,0) -> 444525.32 | F68: =IFERROR(F66+F61,0) -> 459232.4 | G68: =IFERROR(G66+G61,0) -> 492343.29 | H68: =IFERROR(H66+H61,0) -> 508364.04 | I68: =IFERROR(I66+I61,0) -> 541747.65 | J68: =IFERROR(J66+J61,0) -> 583259.52 | ... L68: =IFERROR(L66+L61,0) -> 709773.93
B70: Check | C70: =C68=C55 -> TRUE | D70: =D68=D55 -> TRUE | E70: =E68=E55 -> TRUE | F70: =F68=F55 -> TRUE | G70: =G68=G55 -> TRUE | H70: =H68=H55 -> TRUE | I70: =I68=I55 -> TRUE | J70: =J68=J55 -> TRUE | ... L70: =L68=L55 -> TRUE
A72: # | B72: Cash Flow Statements
B74: Operating Activities
B75: Profit from operations | C75: =IFERROR('Cash Flow Data'!E4,0) -> 54535 | D75: =IFERROR('Cash Flow Data'!F4,0) -> 46768 | E75: =IFERROR('Cash Flow Data'!G4,0) -> 58077 | F75: =IFERROR('Cash Flow Data'!H4,0) -> 67335 | G75: =IFERROR('Cash Flow Data'!I4,0) -> 86600 | H75: =IFERROR('Cash Flow Data'!J4,0) -> 67907 | I75: =IFERROR('Cash Flow Data'!K4,0) -> 58661 | J75: =IFERROR('Cash Flow Data'!L4,0) -> 88028 | ... L75: =IFERROR('Cash Flow Data'!N4,0) -> 113693
B76: Receivables | C76: =IFERROR('Cash Flow Data'!E5,0) -> -6040 | D76: =IFERROR('Cash Flow Data'!F5,0) -> 7835 | E76: =IFERROR('Cash Flow Data'!G5,0) -> -2128 | F76: =IFERROR('Cash Flow Data'!H5,0) -> -1744 | G76: =IFERROR('Cash Flow Data'!I5,0) -> -2252 | H76: =IFERROR('Cash Flow Data'!J5,0) -> 6145 | I76: =IFERROR('Cash Flow Data'!K5,0) -> -6666 | J76: =IFERROR('Cash Flow Data'!L5,0) -> -3067 | ... L76: =IFERROR('Cash Flow Data'!N5,0) -> -1085
B77: Inventory | C77: =IFERROR('Cash Flow Data'!E6,0) -> 4462 | D77: =IFERROR('Cash Flow Data'!F6,0) -> 491 | E77: =IFERROR('Cash Flow Data'!G6,0) -> -6594 | F77: =IFERROR('Cash Flow Data'!H6,0) -> -751 | G77: =IFERROR('Cash Flow Data'!I6,0) -> -4682 | H77: =IFERROR('Cash Flow Data'!J6,0) -> 957 | I77: =IFERROR('Cash Flow Data'!K6,0) -> -11681 | J77: =IFERROR('Cash Flow Data'!L6,0) -> -9672 | ... L77: =IFERROR('Cash Flow Data'!N6,0) -> -8135
B78: Payables | C78: =IFERROR('Cash Flow Data'!E7,0) -> -3972 | D78: =IFERROR('Cash Flow Data'!F7,0) -> 579 | E78: =IFERROR('Cash Flow Data'!G7,0) -> -6214 | F78: =IFERROR('Cash Flow Data'!H7,0) -> 5875 | G78: =IFERROR('Cash Flow Data'!I7,0) -> 9441 | H78: =IFERROR('Cash Flow Data'!J7,0) -> 6161 | I78: =IFERROR('Cash Flow Data'!K7,0) -> 13406 | J78: =IFERROR('Cash Flow Data'!L7,0) -> 18358 | ... L78: =IFERROR('Cash Flow Data'!N7,0) -> 9639
B79: Loans Advances | C79: =IFERROR('Cash Flow Data'!E8,0) -> -3007 | D79: =IFERROR('Cash Flow Data'!F8,0) -> 145 | E79: =IFERROR('Cash Flow Data'!G8,0) -> 123 | F79: =IFERROR('Cash Flow Data'!H8,0) -> -1866 | G79: =IFERROR('Cash Flow Data'!I8,0) -> -6374 | H79: =IFERROR('Cash Flow Data'!J8,0) -> 2622 | I79: =IFERROR('Cash Flow Data'!K8,0) -> 5236 | J79: =IFERROR('Cash Flow Data'!L8,0) -> -451 | ... L79: =IFERROR('Cash Flow Data'!N8,0) -> -1186
B80: Other WC items | C80: =IFERROR('Cash Flow Data'!E9,0) -> -3078 | D80: =IFERROR('Cash Flow Data'!F9,0) -> -1863 | E80: =IFERROR('Cash Flow Data'!G9,0) -> 12140 | F80: =IFERROR('Cash Flow Data'!H9,0) -> -1261 | G80: =IFERROR('Cash Flow Data'!I9,0) -> -5951 | H80: =IFERROR('Cash Flow Data'!J9,0) -> -3182 | I80: =IFERROR('Cash Flow Data'!K9,0) -> -4235 | J80: =IFERROR('Cash Flow Data'!L9,0) -> -1452 | ... L80: =IFERROR('Cash Flow Data'!N9,0) -> 902
B81: Working capital changes | C81: =IFERROR('Cash Flow Data'!E10,0) -> -11635 | D81: =IFERROR('Cash Flow Data'!F10,0) -> 7186 | E81: =IFERROR('Cash Flow Data'!G10,0) -> -2673 | F81: =IFERROR('Cash Flow Data'!H10,0) -> 254 | G81: =IFERROR('Cash Flow Data'!I10,0) -> -9817 | H81: =IFERROR('Cash Flow Data'!J10,0) -> 12702 | I81: =IFERROR('Cash Flow Data'!K10,0) -> -3940 | J81: =IFERROR('Cash Flow Data'!L10,0) -> 3716 | ... L81: =IFERROR('Cash Flow Data'!N10,0) -> 136
B82: Direct taxes | C82: =IFERROR('Cash Flow Data'!E11,0) -> -9029 | D82: =IFERROR('Cash Flow Data'!F11,0) -> -7662 | E82: =IFERROR('Cash Flow Data'!G11,0) -> -9624 | F82: =IFERROR('Cash Flow Data'!H11,0) -> -10798 | G82: =IFERROR('Cash Flow Data'!I11,0) -> -15326 | H82: =IFERROR('Cash Flow Data'!J11,0) -> -10017 | I82: =IFERROR('Cash Flow Data'!K11,0) -> -7537 | J82: =IFERROR('Cash Flow Data'!L11,0) -> -13496 | ... L82: =IFERROR('Cash Flow Data'!N11,0) -> -14566
B83: Other operating items | C83: =IFERROR('Cash Flow Data'!E12,0) -> 80 | D83: =IFERROR('Cash Flow Data'!F12,0) -> 0 | E83: =IFERROR('Cash Flow Data'!G12,0) -> 0 | F83: =IFERROR('Cash Flow Data'!H12,0) -> 0 | G83: =IFERROR('Cash Flow Data'!I12,0) -> 0 | H83: =IFERROR('Cash Flow Data'!J12,0) -> 0 | I83: =IFERROR('Cash Flow Data'!K12,0) -> 0 | J83: =IFERROR('Cash Flow Data'!L12,0) -> 0 | ... L83: =IFERROR('Cash Flow Data'!N12,0) -> 0
B84: Cash from Operating Activities | C84: =SUM(C75:C83) -> 22316 | D84: =SUM(D75:D83) -> 53479 | E84: =SUM(E75:E83) -> 43107 | F84: =SUM(F75:F83) -> 57044 | G84: =SUM(G75:G83) -> 51639 | H84: =SUM(H75:H83) -> 83295 | I84: =SUM(I75:I83) -> 43244 | J84: =SUM(J75:J83) -> 81964 | ... L84: =SUM(L75:L83) -> 99398
B86: Investing Activities
B87: Fixed assets purchased | C87: =IFERROR('Cash Flow Data'!E14,0) -> -16906 | D87: =IFERROR('Cash Flow Data'!F14,0) -> -15120 | E87: =IFERROR('Cash Flow Data'!G14,0) -> -20524 | F87: =IFERROR('Cash Flow Data'!H14,0) -> -27815 | G87: =IFERROR('Cash Flow Data'!I14,0) -> -25963 | H87: =IFERROR('Cash Flow Data'!J14,0) -> -42258 | I87: =IFERROR('Cash Flow Data'!K14,0) -> -32319 | J87: =IFERROR('Cash Flow Data'!L14,0) -> -33457 | ... L87: =IFERROR('Cash Flow Data'!N14,0) -> -37916
B88: Fixed assets sold | C88: =IFERROR('Cash Flow Data'!E15,0) -> 9 | D88: =IFERROR('Cash Flow Data'!F15,0) -> 26 | E88: =IFERROR('Cash Flow Data'!G15,0) -> 189 | F88: =IFERROR('Cash Flow Data'!H15,0) -> 83 | G88: =IFERROR('Cash Flow Data'!I15,0) -> 203 | H88: =IFERROR('Cash Flow Data'!J15,0) -> 401 | I88: =IFERROR('Cash Flow Data'!K15,0) -> 281 | J88: =IFERROR('Cash Flow Data'!L15,0) -> 367 | ... L88: =IFERROR('Cash Flow Data'!N15,0) -> 251
B89: Investments purchased | C89: =IFERROR('Cash Flow Data'!E16,0) -> 0 | D89: =IFERROR('Cash Flow Data'!F16,0) -> -3003 | E89: =IFERROR('Cash Flow Data'!G16,0) -> -631 | F89: =IFERROR('Cash Flow Data'!H16,0) -> -240 | G89: =IFERROR('Cash Flow Data'!I16,0) -> -236 | H89: =IFERROR('Cash Flow Data'!J16,0) -> -235 | I89: =IFERROR('Cash Flow Data'!K16,0) -> -327 | J89: =IFERROR('Cash Flow Data'!L16,0) -> -836 | ... L89: =IFERROR('Cash Flow Data'!N16,0) -> -8
B90: Investments sold | C90: =IFERROR('Cash Flow Data'!E17,0) -> 33 | D90: =IFERROR('Cash Flow Data'!F17,0) -> 0 | E90: =IFERROR('Cash Flow Data'!G17,0) -> 140 | F90: =IFERROR('Cash Flow Data'!H17,0) -> 5010 | G90: =IFERROR('Cash Flow Data'!I17,0) -> 0 | H90: =IFERROR('Cash Flow Data'!J17,0) -> 0 | I90: =IFERROR('Cash Flow Data'!K17,0) -> 0 | J90: =IFERROR('Cash Flow Data'!L17,0) -> 0 | ... L90: =IFERROR('Cash Flow Data'!N17,0) -> 32
B91: Subsidy received | C91: =IFERROR('Cash Flow Data'!E18,0) -> 0 | D91: =IFERROR('Cash Flow Data'!F18,0) -> 0 | E91: =IFERROR('Cash Flow Data'!G18,0) -> 0 | F91: =IFERROR('Cash Flow Data'!H18,0) -> 0 | G91: =IFERROR('Cash Flow Data'!I18,0) -> 0 | H91: =IFERROR('Cash Flow Data'!J18,0) -> 0 | I91: =IFERROR('Cash Flow Data'!K18,0) -> 0 | J91: =IFERROR('Cash Flow Data'!L18,0) -> 0 | ... L91: =IFERROR('Cash Flow Data'!N18,0) -> 5
B92: Interest received | C92: =IFERROR('Cash Flow Data'!E19,0) -> 2993 | D92: =IFERROR('Cash Flow Data'!F19,0) -> 2892 | E92: =IFERROR('Cash Flow Data'!G19,0) -> 2807 | F92: =IFERROR('Cash Flow Data'!H19,0) -> 2465 | G92: =IFERROR('Cash Flow Data'!I19,0) -> 1932 | H92: =IFERROR('Cash Flow Data'!J19,0) -> 1797 | I92: =IFERROR('Cash Flow Data'!K19,0) -> 1606 | J92: =IFERROR('Cash Flow Data'!L19,0) -> 1509 | ... L92: =IFERROR('Cash Flow Data'!N19,0) -> 4416
B93: Dividends received | C93: =IFERROR('Cash Flow Data'!E20,0) -> 468 | D93: =IFERROR('Cash Flow Data'!F20,0) -> 1025 | E93: =IFERROR('Cash Flow Data'!G20,0) -> 1864 | F93: =IFERROR('Cash Flow Data'!H20,0) -> 4599 | G93: =IFERROR('Cash Flow Data'!I20,0) -> 6486 | H93: =IFERROR('Cash Flow Data'!J20,0) -> 5032 | I93: =IFERROR('Cash Flow Data'!K20,0) -> 4310 | J93: =IFERROR('Cash Flow Data'!L20,0) -> 4388 | ... L93: =IFERROR('Cash Flow Data'!N20,0) -> 3657
B94: Investment in group cos | C94: =IFERROR('Cash Flow Data'!E21,0) -> 0 | D94: =IFERROR('Cash Flow Data'!F21,0) -> -708 | E94: =IFERROR('Cash Flow Data'!G21,0) -> -12482 | F94: =IFERROR('Cash Flow Data'!H21,0) -> -3368 | G94: =IFERROR('Cash Flow Data'!I21,0) -> -1468 | H94: =IFERROR('Cash Flow Data'!J21,0) -> -838 | I94: =IFERROR('Cash Flow Data'!K21,0) -> -2526 | J94: =IFERROR('Cash Flow Data'!L21,0) -> -2447 | ... L94: =IFERROR('Cash Flow Data'!N21,0) -> -3530
B95: Other investing items | C95: =IFERROR('Cash Flow Data'!E22,0) -> -16655 | D95: =IFERROR('Cash Flow Data'!F22,0) -> -23368 | E95: =IFERROR('Cash Flow Data'!G22,0) -> -15177 | F95: =IFERROR('Cash Flow Data'!H22,0) -> -47532 | G95: =IFERROR('Cash Flow Data'!I22,0) -> -18085 | H95: =IFERROR('Cash Flow Data'!J22,0) -> -17058 | I95: =IFERROR('Cash Flow Data'!K22,0) -> -10165 | J95: =IFERROR('Cash Flow Data'!L22,0) -> -10721 | ... L95: =IFERROR('Cash Flow Data'!N22,0) -> -24112
B96: Cash from Investing Activities | C96: =SUM(C87:C95) -> -30058 | D96: =SUM(D87:D95) -> -38256 | E96: =SUM(E87:E95) -> -43814 | F96: =SUM(F87:F95) -> -66798 | G96: =SUM(G87:G95) -> -37131 | H96: =SUM(H87:H95) -> -53159 | I96: =SUM(I87:I95) -> -39140 | J96: =SUM(J87:J95) -> -41197 | ... L96: =SUM(L87:L95) -> -57205
B98: Financing Activities
B99: Proceeds from shares | C99: =IFERROR('Cash Flow Data'!E24,0) -> 0 | D99: =IFERROR('Cash Flow Data'!F24,0) -> 0 | E99: =IFERROR('Cash Flow Data'!G24,0) -> 0 | F99: =IFERROR('Cash Flow Data'!H24,0) -> 0 | G99: =IFERROR('Cash Flow Data'!I24,0) -> 0 | H99: =IFERROR('Cash Flow Data'!J24,0) -> 0 | I99: =IFERROR('Cash Flow Data'!K24,0) -> 0 | J99: =IFERROR('Cash Flow Data'!L24,0) -> 0 | ... L99: =IFERROR('Cash Flow Data'!N24,0) -> 0
B100: Proceeds from borrowings | C100: =IFERROR('Cash Flow Data'!E25,0) -> 0 | D100: =IFERROR('Cash Flow Data'!F25,0) -> 4138 | E100: =IFERROR('Cash Flow Data'!G25,0) -> 15991 | F100: =IFERROR('Cash Flow Data'!H25,0) -> 33376 | G100: =IFERROR('Cash Flow Data'!I25,0) -> 8230 | H100: =IFERROR('Cash Flow Data'!J25,0) -> 27871 | I100: =IFERROR('Cash Flow Data'!K25,0) -> 18834 | J100: =IFERROR('Cash Flow Data'!L25,0) -> 17685 | ... L100: =IFERROR('Cash Flow Data'!N25,0) -> 22459
B101: Repayment of borrowings | C101: =IFERROR('Cash Flow Data'!E26,0) -> 0 | D101: =IFERROR('Cash Flow Data'!F26,0) -> -4332 | E101: =IFERROR('Cash Flow Data'!G26,0) -> 0 | F101: =IFERROR('Cash Flow Data'!H26,0) -> -9316 | G101: =IFERROR('Cash Flow Data'!I26,0) -> -11362 | H101: =IFERROR('Cash Flow Data'!J26,0) -> -25460 | I101: =IFERROR('Cash Flow Data'!K26,0) -> -13534 | J101: =IFERROR('Cash Flow Data'!L26,0) -> -30679 | ... L101: =IFERROR('Cash Flow Data'!N26,0) -> -37880
B102: Interest paid fin | C102: =IFERROR('Cash Flow Data'!E27,0) -> -3003 | D102: =IFERROR('Cash Flow Data'!F27,0) -> -2399 | E102: =IFERROR('Cash Flow Data'!G27,0) -> -2126 | F102: =IFERROR('Cash Flow Data'!H27,0) -> -2924 | G102: =IFERROR('Cash Flow Data'!I27,0) -> -4056 | H102: =IFERROR('Cash Flow Data'!J27,0) -> -4241 | I102: =IFERROR('Cash Flow Data'!K27,0) -> -3834 | J102: =IFERROR('Cash Flow Data'!L27,0) -> -4343 | ... L102: =IFERROR('Cash Flow Data'!N27,0) -> -9364
B103: Dividends paid | C103: =IFERROR('Cash Flow Data'!E28,0) -> -7920 | D103: =IFERROR('Cash Flow Data'!F28,0) -> -4917 | E103: =IFERROR('Cash Flow Data'!G28,0) -> -15350 | F103: =IFERROR('Cash Flow Data'!H28,0) -> -9496 | G103: =IFERROR('Cash Flow Data'!I28,0) -> -10086 | H103: =IFERROR('Cash Flow Data'!J28,0) -> -8297 | I103: =IFERROR('Cash Flow Data'!K28,0) -> -3096 | J103: =IFERROR('Cash Flow Data'!L28,0) -> -12924 | ... L103: =IFERROR('Cash Flow Data'!N28,0) -> -12895
B104: Financial liabilities | C104: =IFERROR('Cash Flow Data'!E29,0) -> 0 | D104: =IFERROR('Cash Flow Data'!F29,0) -> 0 | E104: =IFERROR('Cash Flow Data'!G29,0) -> 0 | F104: =IFERROR('Cash Flow Data'!H29,0) -> 0 | G104: =IFERROR('Cash Flow Data'!I29,0) -> 0 | H104: =IFERROR('Cash Flow Data'!J29,0) -> -5038 | I104: =IFERROR('Cash Flow Data'!K29,0) -> -5688 | J104: =IFERROR('Cash Flow Data'!L29,0) -> -5250 | ... L104: =IFERROR('Cash Flow Data'!N29,0) -> -7362
B105: Share application money | C105: =IFERROR('Cash Flow Data'!E30,0) -> 0 | D105: =IFERROR('Cash Flow Data'!F30,0) -> 0 | E105: =IFERROR('Cash Flow Data'!G30,0) -> 0 | F105: =IFERROR('Cash Flow Data'!H30,0) -> 0 | G105: =IFERROR('Cash Flow Data'!I30,0) -> 0 | H105: =IFERROR('Cash Flow Data'!J30,0) -> 0 | I105: =IFERROR('Cash Flow Data'!K30,0) -> 0 | J105: =IFERROR('Cash Flow Data'!L30,0) -> 0 | ... L105: =IFERROR('Cash Flow Data'!N30,0) -> 0
B106: Other financing items | C106: =IFERROR('Cash Flow Data'!E31,0) -> 283 | D106: =IFERROR('Cash Flow Data'!F31,0) -> -1462 | E106: =IFERROR('Cash Flow Data'!G31,0) -> -382 | F106: =IFERROR('Cash Flow Data'!H31,0) -> -1731 | G106: =IFERROR('Cash Flow Data'!I31,0) -> -6051 | H106: =IFERROR('Cash Flow Data'!J31,0) -> -1561 | I106: =IFERROR('Cash Flow Data'!K31,0) -> -921 | J106: =IFERROR('Cash Flow Data'!L31,0) -> -278 | ... L106: =IFERROR('Cash Flow Data'!N31,0) -> -609
B107: Cash from Financing Activities | C107: =SUM(C98:C106) -> -10640 | D107: =SUM(D98:D106) -> -8972 | E107: =SUM(E98:E106) -> -1867 | F107: =SUM(F98:F106) -> 9909 | G107: =SUM(G98:G106) -> -23325 | H107: =SUM(H98:H106) -> -16726 | I107: =SUM(I98:I106) -> -8239 | J107: =SUM(J98:J106) -> -35789 | ... L107: =SUM(L98:L106) -> -45651
B109: Net Cash Flow | C109: =C107+C96+C84 -> -18382 | D109: =D107+D96+D84 -> 6251 | E109: =E107+E96+E84 -> -2574 | F109: =F107+F96+F84 -> 155 | G109: =G107+G96+G84 -> -8817 | H109: =H107+H96+H84 -> 13410 | I109: =I107+I96+I84 -> -4135 | J109: =J107+J96+J84 -> 4978 | ... L109: =L107+L96+L84 -> -3458

Sheet Ratio Analysis
B2: ="Ratio Analysis - "&'Profit & Loss'!A1 -> Ratio Analysis - OIL & NATURAL GAS CORPN LTD
B3: Years | C3: =Annual[[#This Row],[Column2]] -> 42094 | D3: =Annual[[#This Row],[Column3]] -> 42460 | E3: =Annual[[#This Row],[Column4]] -> 42825 | F3: =Annual[[#This Row],[Column5]] -> 43190 | G3: =Annual[[#This Row],[Column6]] -> 43555 | H3: =Annual[[#This Row],[Column7]] -> 43921 | I3: =Annual[[#This Row],[Column8]] -> 44286 | J3: =Annual[[#This Row],[Column9]] -> 44651 | K3: =Annual[[#This Row],[Column10]] -> 45016 | L3: =Annual[[#This Row],[Column11]] -> 45382 | M3: Mean | N3: Median | O3: Trend
B5: Sales Growth | D5: =IFERROR('Historical FS'!D8,0) -> -0.22922151 | E5: =IFERROR('Historical FS'!E8,0) -> 1.2776192 | F5: =IFERROR('Historical FS'!F8,0) -> 0.14229657 | G5: =IFERROR('Historical FS'!G8,0) -> 0.30652744 | H5: =IFERROR('Historical FS'!H8,0) -> -0.059047929 | I5: =IFERROR('Historical FS'!I8,0) -> -0.23411259 | J5: =IFERROR('Historical FS'!J8,0) -> 0.61674511 | K5: =IFERROR('Historical FS'!K8,0) -> 0.28711658 | L5: =IFERROR('Historical FS'!L8,0) -> -0.064677353 | M5: =AVERAGE(C5:L5) -> 0.22702728 | N5: =MEDIAN(D5:L5) -> 0.14229657
B6: EBITDA Growth | D6: =IFERROR('Historical FS'!D19/'Historical FS'!C19-1,0) -> -0.075100822 | E6: =IFERROR('Historical FS'!E19/'Historical FS'!D19-1,0) -> 0.34928246 | F6: =IFERROR('Historical FS'!F19/'Historical FS'!E19-1,0) -> 0.077369433 | G6: =IFERROR('Historical FS'!G19/'Historical FS'!F19-1,0) -> 0.3151736 | H6: =IFERROR('Historical FS'!H19/'Historical FS'!G19-1,0) -> -0.30358616 | I6: =IFERROR('Historical FS'!I19/'Historical FS'!H19-1,0) -> -0.050504577 | J6: =IFERROR('Historical FS'!J19/'Historical FS'!I19-1,0) -> 0.61447415 | K6: =IFERROR('Historical FS'!K19/'Historical FS'!J19-1,0) -> -0.054418488 | L6: =IFERROR('Historical FS'!L19/'Historical FS'!K19-1,0) -> 0.36157207 | M6: =AVERAGE(C6:L6) -> 0.13714019 | N6: =MEDIAN(D6:L6) -> 0.077369433
B7: EBIT Growth | D7: =IFERROR('Historical FS'!D28/'Historical FS'!C28-1,0) -> -0.11349717 | E7: =IFERROR('Historical FS'!E28/'Historical FS'!D28-1,0) -> 0.52717278 | F7: =IFERROR('Historical FS'!F28/'Historical FS'!E28-1,0) -> -0.0074241137 | G7: =IFERROR('Historical FS'!G28/'Historical FS'!F28-1,0) -> 0.57336809 | H7: =IFERROR('Historical FS'!H28/'Historical FS'!G28-1,0) -> -0.60288578 | I7: =IFERROR('Historical FS'!I28/'Historical FS'!H28-1,0) -> 0.048673137 | J7: =IFERROR('Historical FS'!J28/'Historical FS'!I28-1,0) -> 1.5081958 | K7: =IFERROR('Historical FS'!K28/'Historical FS'!J28-1,0) -> -0.089097671 | L7: =IFERROR('Historical FS'!L28/'Historical FS'!K28-1,0) -> 0.48276868 | M7: =AVERAGE(C7:L7) -> 0.25858598 | N7: =MEDIAN(D7:L7) -> 0.048673137
B8: Net Profit Growth | D8: =IFERROR('Historical FS'!D34/'Historical FS'!C34-1,0) -> 0.026975156 | E8: =IFERROR('Historical FS'!E34/'Historical FS'!D34-1,0) -> 0.36650687 | F8: =IFERROR('Historical FS'!F34/'Historical FS'!E34-1,0) -> -0.04903332 | G8: =IFERROR('Historical FS'!G34/'Historical FS'!F34-1,0) -> 0.55838282 | H8: =IFERROR('Historical FS'!H34/'Historical FS'!G34-1,0) -> -0.57020193 | I8: =IFERROR('Historical FS'!I34/'Historical FS'!H34-1,0) -> -0.036739456 | J8: =IFERROR('Historical FS'!J34/'Historical FS'!I34-1,0) -> 3.2119371 | K8: =IFERROR('Historical FS'!K34/'Historical FS'!J34-1,0) -> -0.22801257 | L8: =IFERROR('Historical FS'!L34/'Historical FS'!K34-1,0) -> 0.34479609 | M8: =AVERAGE(C8:L8) -> 0.40273453 | N8: =MEDIAN(D8:L8) -> 0.026975156
B9: Dividend Growth | D9: =IFERROR('Historical FS'!D42/'Historical FS'!C42-1,0) -> -0.10526296 | E9: =IFERROR('Historical FS'!E42/'Historical FS'!D42-1,0) -> 0.33235105 | F9: =IFERROR('Historical FS'!F42/'Historical FS'!E42-1,0) -> -0.12582786 | G9: =IFERROR('Historical FS'!G42/'Historical FS'!F42-1,0) -> 0.060601302 | H9: =IFERROR('Historical FS'!H42/'Historical FS'!G42-1,0) -> -0.28571429 | I9: =IFERROR('Historical FS'!I42/'Historical FS'!H42-1,0) -> -0.28000127 | J9: =IFERROR('Historical FS'!J42/'Historical FS'!I42-1,0) -> 1.9166663 | K9: =IFERROR('Historical FS'!K42/'Historical FS'!J42-1,0) -> 0.071429274 | L9: =IFERROR('Historical FS'!L42/'Historical FS'!K42-1,0) -> 0.088888292 | M9: =AVERAGE(C9:L9) -> 0.18590332 | N9: =MEDIAN(D9:L9) -> 0.060601302
B11: Gross Margin | C11: =IFERROR('Historical FS'!C14,0) -> 0.49015813 | D11: =IFERROR('Historical FS'!D14,0) -> 0.54108821 | E11: =IFERROR('Historical FS'!E14,0) -> 0.27811052 | F11: =IFERROR('Historical FS'!F14,0) -> 0.26307228 | G11: =IFERROR('Historical FS'!G14,0) -> 0.26570449 | H11: =IFERROR('Historical FS'!H14,0) -> 0.21941272 | I11: =IFERROR('Historical FS'!I14,0) -> 0.23742317 | J11: =IFERROR('Historical FS'!J14,0) -> 0.23213975 | ... L11: =IFERROR('Historical FS'!L14,0) -> 0.23331463 | M11: =AVERAGE(C11:L11) -> 0.29572155 | N11: =MEDIAN(D11:L11) -> 0.23742317
B12: EBITDA Margin | C12: =IFERROR('Historical FS'!C20,0) -> 0.26293578 | D12: =IFERROR('Historical FS'!D20,0) -> 0.31551099 | E12: =IFERROR('Historical FS'!E20,0) -> 0.1869116 | F12: =IFERROR('Historical FS'!F20,0) -> 0.17628771 | G12: =IFERROR('Historical FS'!G20,0) -> 0.17745433 | H12: =IFERROR('Historical FS'!H20,0) -> 0.13133681 | I12: =IFERROR('Historical FS'!I20,0) -> 0.1628225 | J12: =IFERROR('Historical FS'!J20,0) -> 0.16259379 | ... L12: =IFERROR('Historical FS'!L20,0) -> 0.17388585 | M12: =AVERAGE(C12:L12) -> 0.18691891 | N12: =MEDIAN(D12:L12) -> 0.17388585
B13: EBIT Margin | C13: =IFERROR(('Historical FS'!C19-'Historical FS'!C25)/'Historical FS'!C7,0) -> 0.15087591 | D13: =IFERROR(('Historical FS'!D19-'Historical FS'!D25)/'Historical FS'!D7,0) -> 0.18341952 | E13: =IFERROR(('Historical FS'!E19-'Historical FS'!E25)/'Historical FS'!E7,0) -> 0.11534076 | F13: =IFERROR(('Historical FS'!F19-'Historical FS'!F25)/'Historical FS'!F7,0) -> 0.10466857 | G13: =IFERROR(('Historical FS'!G19-'Historical FS'!G25)/'Historical FS'!G7,0) -> 0.12123432 | H13: =IFERROR(('Historical FS'!H19-'Historical FS'!H25)/'Historical FS'!H7,0) -> 0.064200424 | I13: =IFERROR(('Historical FS'!I19-'Historical FS'!I25)/'Historical FS'!I7,0) -> 0.078772604 | J13: =IFERROR(('Historical FS'!J19-'Historical FS'!J25)/'Historical FS'!J7,0) -> 0.10786939 | ... L13: =IFERROR(('Historical FS'!L19-'Historical FS'!L25)/'Historical FS'!L7,0) -> 0.12525052 | M13: =AVERAGE(C13:L13) -> 0.11322435 | N13: =MEDIAN(D13:L13) -> 0.10786939
B14: EBT Margin | C14: =IFERROR('Historical FS'!C29,0) -> 0.13308009 | D14: =IFERROR('Historical FS'!D29,0) -> 0.15306068 | E14: =IFERROR('Historical FS'!E29,0) -> 0.10262914 | F14: =IFERROR('Historical FS'!F29,0) -> 0.089177553 | G14: =IFERROR('Historical FS'!G29,0) -> 0.10739087 | H14: =IFERROR('Historical FS'!H29,0) -> 0.045322649 | I14: =IFERROR('Historical FS'!I29,0) -> 0.062056961 | J14: =IFERROR('Historical FS'!J29,0) -> 0.096274304 | ... L14: =IFERROR('Historical FS'!L29,0) -> 0.10801306 | M14: =AVERAGE(C14:L14) -> 0.096513938 | N14: =MEDIAN(D14:L14) -> 0.096274304
B15: Net Profit Margin | C15: =IFERROR('Historical FS'!C35,0) -> 0.072818778 | D15: =IFERROR('Historical FS'!D35,0) -> 0.097022785 | E15: =IFERROR('Historical FS'!E35,0) -> 0.058210918 | F15: =IFERROR('Historical FS'!F35,0) -> 0.048460833 | G15: =IFERROR('Historical FS'!G35,0) -> 0.057802483 | H15: =IFERROR('Historical FS'!H35,0) -> 0.026402403 | I15: =IFERROR('Historical FS'!I35,0) -> 0.033206438 | J15: =IFERROR('Historical FS'!J35,0) -> 0.086509263 | ... L15: =IFERROR('Historical FS'!L35,0) -> 0.074601909 | M15: =AVERAGE(C15:L15) -> 0.060692238 | N15: =MEDIAN(D15:L15) -> 0.057802483
B17: Sales Expenses % of Sales | C17: =IFERROR('Historical FS'!C17,0) -> 0.22722235 | D17: =IFERROR('Historical FS'!D17,0) -> 0.22557721 | E17: =IFERROR('Historical FS'!E17,0) -> 0.091198912 | F17: =IFERROR('Historical FS'!F17,0) -> 0.086784568 | G17: =IFERROR('Historical FS'!G17,0) -> 0.088250162 | H17: =IFERROR('Historical FS'!H17,0) -> 0.088075906 | I17: =IFERROR('Historical FS'!I17,0) -> 0.074600663 | J17: =IFERROR('Historical FS'!J17,0) -> 0.069545957 | ... L17: =IFERROR('Historical FS'!L17,0) -> 0.059428783 | M17: =AVERAGE(C17:L17) -> 0.10880265 | N17: =MEDIAN(D17:L17) -> 0.086784568
B18: Depreciation % of Sales | C18: =IFERROR('Historical FS'!C26,0) -> 0.11205987 | D18: =IFERROR('Historical FS'!D26,0) -> 0.13209148 | E18: =IFERROR('Historical FS'!E26,0) -> 0.071570841 | F18: =IFERROR('Historical FS'!F26,0) -> 0.071619143 | G18: =IFERROR('Historical FS'!G26,0) -> 0.056220006 | H18: =IFERROR('Historical FS'!H26,0) -> 0.067136391 | I18: =IFERROR('Historical FS'!I26,0) -> 0.084049898 | J18: =IFERROR('Historical FS'!J26,0) -> 0.054724409 | ... L18: =IFERROR('Historical FS'!L26,0) -> 0.048635326 | M18: =AVERAGE(C18:L18) -> 0.073694557 | N18: =MEDIAN(D18:L18) -> 0.067136391
B19: Operating Income % of Sales | C19: =C13 -> 0.15087591 | D19: =D13 -> 0.18341952 | E19: =E13 -> 0.11534076 | F19: =F13 -> 0.10466857 | G19: =G13 -> 0.12123432 | H19: =H13 -> 0.064200424 | I19: =I13 -> 0.078772604 | J19: =J13 -> 0.10786939 | ... L19: =L13 -> 0.12525052 | M19: =AVERAGE(C19:L19) -> 0.11322435 | N19: =MEDIAN(D19:L19) -> 0.10786939
B21: Return on Capital Employed | C21: =IFERROR(('Historical FS'!C19-'Historical FS'!C25)/(SUM('Historical FS'!C51:C53)),0) -> 0.10358134 | D21: =IFERROR(('Historical FS'!D19-'Historical FS'!D25)/(SUM('Historical FS'!D51:D53)),0) -> 0.093502995 | E21: =IFERROR(('Historical FS'!E19-'Historical FS'!E25)/(SUM('Historical FS'!E51:E53)),0) -> 0.1187418 | F21: =IFERROR(('Historical FS'!F19-'Historical FS'!F25)/(SUM('Historical FS'!F51:F53)),0) -> 0.10875897 | G21: =IFERROR(('Historical FS'!G19-'Historical FS'!G25)/(SUM('Historical FS'!G51:G53)),0) -> 0.1574346 | H21: =IFERROR(('Historical FS'!H19-'Historical FS'!H25)/(SUM('Historical FS'!H51:H53)),0) -> 0.076126246 | I21: =IFERROR(('Historical FS'!I19-'Historical FS'!I25)/(SUM('Historical FS'!I51:I53)),0) -> 0.067580855 | J21: =IFERROR(('Historical FS'!J19-'Historical FS'!J25)/(SUM('Historical FS'!J51:J53)),0) -> 0.1389043 | ... L21: =IFERROR(('Historical FS'!L19-'Historical FS'!L25)/(SUM('Historical FS'!L51:L53)),0) -> 0.15109143 | M21: =AVERAGE(C21:L21) -> 0.11362467 | N21: =MEDIAN(D21:L21) -> 0.1187418
B22: Retained Earnings % | C22: =IFERROR('Historical FS'!C46,0) -> 0.30639971 | D22: =IFERROR('Historical FS'!D46,0) -> 0.39571092 | E22: =IFERROR('Historical FS'!E46,0) -> 0.41081512 | F22: =IFERROR('Historical FS'!F46,0) -> 0.45839427 | G22: =IFERROR('Historical FS'!G46,0) -> 0.63865896 | H22: =IFERROR('Historical FS'!H46,0) -> 0.3994837 | I22: =IFERROR('Historical FS'!I46,0) -> 0.55113809 | J22: =IFERROR('Historical FS'!J46,0) -> 0.6891738 | ... L22: =IFERROR('Historical FS'!L46,0) -> 0.65070063 | M22: =AVERAGE(C22:L22) -> 0.50690844 | N22: =MEDIAN(D22:L22) -> 0.55113809
B23: Return on Equity % | C23: =IFERROR('Historical FS'!C34/SUM('Historical FS'!C51:C52),0) -> 0.064937125 | D23: =IFERROR('Historical FS'!D34/SUM('Historical FS'!D51:D52),0) -> 0.060836502 | E23: =IFERROR('Historical FS'!E34/SUM('Historical FS'!E51:E52),0) -> 0.084599745 | F23: =IFERROR('Historical FS'!F34/SUM('Historical FS'!F51:F52),0) -> 0.076652642 | G23: =IFERROR('Historical FS'!G34/SUM('Historical FS'!G51:G52),0) -> 0.11234217 | H23: =IFERROR('Historical FS'!H34/SUM('Historical FS'!H51:H52),0) -> 0.051069406 | I23: =IFERROR('Historical FS'!I34/SUM('Historical FS'!I51:I52),0) -> 0.04565886 | J23: =IFERROR('Historical FS'!J34/SUM('Historical FS'!J51:J52),0) -> 0.16376444 | ... L23: =IFERROR('Historical FS'!L34/SUM('Historical FS'!L51:L52),0) -> 0.1308905 | M23: =AVERAGE(C23:L23) -> 0.090765051 | N23: =MEDIAN(D23:L23) -> 0.084599745
B24: Self Sustained Growth Rate | C24: =IFERROR(C22*C23,0) -> 0.019896716 | D24: =IFERROR(D22*D23,0) -> 0.024073669 | E24: =IFERROR(E22*E23,0) -> 0.034754854 | F24: =IFERROR(F22*F23,0) -> 0.035137132 | G24: =IFERROR(G22*G23,0) -> 0.071748335 | H24: =IFERROR(H22*H23,0) -> 0.020401395 | I24: =IFERROR(I22*I23,0) -> 0.025164337 | J24: =IFERROR(J22*J23,0) -> 0.11286216 | ... L24: =IFERROR(L22*L23,0) -> 0.08517053 | M24: =AVERAGE(C24:L24) -> 0.049567904 | N24: =MEDIAN(D24:L24) -> 0.035137132
B25: Interest Coverage Ratio | C25: =IFERROR(('Historical FS'!C19-'Historical FS'!C25)/'Historical FS'!C22,0) -> 8.4781667 | D25: =IFERROR(('Historical FS'!D19-'Historical FS'!D25)/'Historical FS'!D22,0) -> 6.0417173 | E25: =IFERROR(('Historical FS'!E19-'Historical FS'!E25)/'Historical FS'!E22,0) -> 9.0736485 | F25: =IFERROR(('Historical FS'!F19-'Historical FS'!F25)/'Historical FS'!F22,0) -> 6.7567273 | G25: =IFERROR(('Historical FS'!G19-'Historical FS'!G25)/'Historical FS'!G22,0) -> 8.7575218 | H25: =IFERROR(('Historical FS'!H19-'Historical FS'!H25)/'Historical FS'!H22,0) -> 3.4008471 | I25: =IFERROR(('Historical FS'!I19-'Historical FS'!I25)/'Historical FS'!I22,0) -> 4.7125081 | J25: =IFERROR(('Historical FS'!J19-'Historical FS'!J25)/'Historical FS'!J22,0) -> 9.3030298 | ... L25: =IFERROR(('Historical FS'!L19-'Historical FS'!L25)/'Historical FS'!L22,0) -> 7.2661816 | M25: =AVERAGE(C25:L25) -> 7.0250939 | N25: =MEDIAN(D25:L25) -> 6.7567273
B27: Debtor Turnover Ratio | C27: =IFERROR('Historical FS'!C7/'Historical FS'!C63,0) -> 8.552518 | D27: =IFERROR('Historical FS'!D7/'Historical FS'!D63,0) -> 14.887185 | E27: =IFERROR('Historical FS'!E7/'Historical FS'!E63,0) -> 22.515614 | F27: =IFERROR('Historical FS'!F7/'Historical FS'!F63,0) -> 23.217628 | G27: =IFERROR('Historical FS'!G7/'Historical FS'!G63,0) -> 27.384472 | H27: =IFERROR('Historical FS'!H7/'Historical FS'!H63,0) -> 43.247594 | I27: =IFERROR('Historical FS'!I7/'Historical FS'!I63,0) -> 18.971787 | J27: =IFERROR('Historical FS'!J7/'Historical FS'!J63,0) -> 25.602703 | ... L27: =IFERROR('Historical FS'!L7/'Historical FS'!L63,0) -> 29.924493 | M27: =AVERAGE(C27:L27) -> 24.802335 | N27: =MEDIAN(D27:L27) -> 25.602703
B28: Creditor Turnver Ratio | C28: =IFERROR('Historical FS'!C7/'Historical FS'!C54,0) -> 1.5555943 | D28: =IFERROR('Historical FS'!D7/'Historical FS'!D54,0) -> 1.2597757 | E28: =IFERROR('Historical FS'!E7/'Historical FS'!E54,0) -> 1.660718 | F28: =IFERROR('Historical FS'!F7/'Historical FS'!F54,0) -> 2.1707123 | G28: =IFERROR('Historical FS'!G7/'Historical FS'!G54,0) -> 2.5146514 | H28: =IFERROR('Historical FS'!H7/'Historical FS'!H54,0) -> 2.282841 | I28: =IFERROR('Historical FS'!I7/'Historical FS'!I54,0) -> 1.6198386 | J28: =IFERROR('Historical FS'!J7/'Historical FS'!J54,0) -> 2.4346752 | ... L28: =IFERROR('Historical FS'!L7/'Historical FS'!L54,0) -> 2.6940038 | M28: =AVERAGE(C28:L28) -> 2.1516942 | N28: =MEDIAN(D28:L28) -> 2.282841
B29: Inventory Turnover | C29: =IFERROR('Historical FS'!C7/'Historical FS'!C64,0) -> 14.172138 | D29: =IFERROR('Historical FS'!D7/'Historical FS'!D64,0) -> 11.525372 | E29: =IFERROR('Historical FS'!E7/'Historical FS'!E64,0) -> 9.2457076 | F29: =IFERROR('Historical FS'!F7/'Historical FS'!F64,0) -> 10.325405 | G29: =IFERROR('Historical FS'!G7/'Historical FS'!G64,0) -> 11.728257 | H29: =IFERROR('Historical FS'!H7/'Historical FS'!H64,0) -> 11.646162 | I29: =IFERROR('Historical FS'!I7/'Historical FS'!I64,0) -> 6.643561 | J29: =IFERROR('Historical FS'!J7/'Historical FS'!J64,0) -> 8.8736244 | ... L29: =IFERROR('Historical FS'!L7/'Historical FS'!L64,0) -> 11.10494 | M29: =AVERAGE(C29:L29) -> 10.924202 | N29: =MEDIAN(D29:L29) -> 11.10494
B30: Fixed Asset Turnover | C30: =IFERROR('Historical FS'!C7/'Historical FS'!C57,0) -> 0.89434776 | D30: =IFERROR('Historical FS'!D7/'Historical FS'!D57,0) -> 0.74595952 | E30: =IFERROR('Historical FS'!E7/'Historical FS'!E57,0) -> 1.3380961 | F30: =IFERROR('Historical FS'!F7/'Historical FS'!F57,0) -> 1.4275373 | G30: =IFERROR('Historical FS'!G7/'Historical FS'!G57,0) -> 1.8300388 | H30: =IFERROR('Historical FS'!H7/'Historical FS'!H57,0) -> 1.6266543 | I30: =IFERROR('Historical FS'!I7/'Historical FS'!I57,0) -> 1.2465782 | J30: =IFERROR('Historical FS'!J7/'Historical FS'!J57,0) -> 1.9309829 | ... L30: =IFERROR('Historical FS'!L7/'Historical FS'!L57,0) -> 1.98153 | M30: =AVERAGE(C30:L30) -> 1.5542627 | N30: =MEDIAN(D30:L30) -> 1.6266543
B31: Capital Turnover Ratio | C31: =IFERROR('Historical FS'!C7/SUM('Historical FS'!C51:C52),0) -> 0.89176346 | D31: =IFERROR('Historical FS'!D7/SUM('Historical FS'!D51:D52),0) -> 0.62703315 | E31: =IFERROR('Historical FS'!E7/SUM('Historical FS'!E51:E52),0) -> 1.4533312 | F31: =IFERROR('Historical FS'!F7/SUM('Historical FS'!F51:F52),0) -> 1.5817442 | G31: =IFERROR('Historical FS'!G7/SUM('Historical FS'!G51:G52),0) -> 1.9435527 | H31: =IFERROR('Historical FS'!H7/SUM('Historical FS'!H51:H52),0) -> 1.9342711 | I31: =IFERROR('Historical FS'!I7/SUM('Historical FS'!I51:I52),0) -> 1.3750002 | J31: =IFERROR('Historical FS'!J7/SUM('Historical FS'!J51:J52),0) -> 1.8930279 | ... L31: =IFERROR('Historical FS'!L7/SUM('Historical FS'!L51:L52),0) -> 1.7545194 | M31: =AVERAGE(C31:L31) -> 1.5707218 | N31: =MEDIAN(D31:L31) -> 1.7545194
B33: Debtor Days | C33: =IFERROR(365/C27,0) -> 42.67749 | D33: =IFERROR(365/D27,0) -> 24.517731 | E33: =IFERROR(365/E27,0) -> 16.210973 | F33: =IFERROR(365/F27,0) -> 15.720813 | G33: =IFERROR(365/G27,0) -> 13.328721 | H33: =IFERROR(365/H27,0) -> 8.4397759 | I33: =IFERROR(365/I27,0) -> 19.239095 | J33: =IFERROR(365/J27,0) -> 14.256307 | ... L33: =IFERROR(365/L27,0) -> 12.197366 | M33: =AVERAGE(C33:L33) -> 17.741292 | N33: =MEDIAN(D33:L33) -> 14.256307
B34: Payable Days | C34: =IFERROR(365/C28,0) -> 234.63701 | D34: =IFERROR(365/D28,0) -> 289.73413 | E34: =IFERROR(365/E28,0) -> 219.78446 | F34: =IFERROR(365/F28,0) -> 168.14757 | G34: =IFERROR(365/G28,0) -> 145.14934 | H34: =IFERROR(365/H28,0) -> 159.88849 | I34: =IFERROR(365/I28,0) -> 225.33109 | J34: =IFERROR(365/J28,0) -> 149.91733 | ... L34: =IFERROR(365/L28,0) -> 135.48607 | M34: =AVERAGE(C34:L34) -> 183.78786 | N34: =MEDIAN(D34:L34) -> 159.88849
B35: Inventory Days | C35: =IFERROR(365/C29,0) -> 25.75476 | D35: =IFERROR(365/D29,0) -> 31.669259 | E35: =IFERROR(365/E29,0) -> 39.477779 | F35: =IFERROR(365/F29,0) -> 35.349704 | G35: =IFERROR(365/G29,0) -> 31.121418 | H35: =IFERROR(365/H29,0) -> 31.340797 | I35: =IFERROR(365/I29,0) -> 54.940415 | J35: =IFERROR(365/J29,0) -> 41.133136 | ... L35: =IFERROR(365/L29,0) -> 32.868254 | M35: =AVERAGE(C35:L35) -> 34.977013 | N35: =MEDIAN(D35:L35) -> 32.868254
B36: Cash Conversion Cycle (in days) | C36: =IFERROR(SUM(C33+C35)-C34,0) -> -166.20476 | D36: =IFERROR(SUM(D33+D35)-D34,0) -> -233.54714 | E36: =IFERROR(SUM(E33+E35)-E34,0) -> -164.09571 | F36: =IFERROR(SUM(F33+F35)-F34,0) -> -117.07705 | G36: =IFERROR(SUM(G33+G35)-G34,0) -> -100.6992 | H36: =IFERROR(SUM(H33+H35)-H34,0) -> -120.10792 | I36: =IFERROR(SUM(I33+I35)-I34,0) -> -151.15158 | J36: =IFERROR(SUM(J33+J35)-J34,0) -> -94.527885 | ... N36: =IFERROR(SUM(N33+N35)-N34,0) -> -112.76393
B38: CFO/Sales | C38: =IFERROR('Historical FS'!C84/'Historical FS'!C7,0) -> 0.13867533 | D38: =IFERROR('Historical FS'!D84/'Historical FS'!D7,0) -> 0.43115809 | E38: =IFERROR('Historical FS'!E84/'Historical FS'!E7,0) -> 0.15258785 | F38: =IFERROR('Historical FS'!F84/'Historical FS'!F7,0) -> 0.17676784 | G38: =IFERROR('Historical FS'!G84/'Historical FS'!G7,0) -> 0.12247644 | H38: =IFERROR('Historical FS'!H84/'Historical FS'!H7,0) -> 0.20995498 | I38: =IFERROR('Historical FS'!I84/'Historical FS'!I7,0) -> 0.14232073 | J38: =IFERROR('Historical FS'!J84/'Historical FS'!J7,0) -> 0.16684911 | ... L38: =IFERROR('Historical FS'!L84/'Historical FS'!L7,0) -> 0.16807343 | M38: =AVERAGE(C38:L38) -> 0.18587473 | N38: =MEDIAN(D38:L38) -> 0.16684911
B39: CFO/Total Assets | C39: =IFERROR('Historical FS'!C84/'Historical FS'!C68,0) -> 0.066053655 | D39: =IFERROR('Historical FS'!D84/'Historical FS'!D68,0) -> 0.15647549 | E39: =IFERROR('Historical FS'!E84/'Historical FS'!E68,0) -> 0.096973104 | F39: =IFERROR('Historical FS'!F84/'Historical FS'!F68,0) -> 0.12421597 | G39: =IFERROR('Historical FS'!G84/'Historical FS'!G68,0) -> 0.10488413 | H39: =IFERROR('Historical FS'!H84/'Historical FS'!H68,0) -> 0.16384912 | I39: =IFERROR('Historical FS'!I84/'Historical FS'!I68,0) -> 0.079823143 | J39: =IFERROR('Historical FS'!J84/'Historical FS'!J68,0) -> 0.1405275 | ... L39: =IFERROR('Historical FS'!L84/'Historical FS'!L68,0) -> 0.14004177 | M39: =AVERAGE(C39:L39) -> 0.12274153 | N39: =MEDIAN(D39:L39) -> 0.14004177
B40: CFO/Total Debt | C40: =IFERROR('Historical FS'!C84/'Historical FS'!C53,0) -> 0.41368466 | D40: =IFERROR('Historical FS'!D84/'Historical FS'!D53,0) -> 1.1753582 | E40: =IFERROR('Historical FS'!E84/'Historical FS'!E53,0) -> 0.53864042 | F40: =IFERROR('Historical FS'!F84/'Historical FS'!F53,0) -> 0.53537337 | G40: =IFERROR('Historical FS'!G84/'Historical FS'!G53,0) -> 0.47928522 | H40: =IFERROR('Historical FS'!H84/'Historical FS'!H53,0) -> 0.64334115 | I40: =IFERROR('Historical FS'!I84/'Historical FS'!I53,0) -> 0.32468654 | J40: =IFERROR('Historical FS'!J84/'Historical FS'!J53,0) -> 0.67191394 | ... L40: =IFERROR('Historical FS'!L84/'Historical FS'!L53,0) -> 0.64889448 | M40: =AVERAGE(C40:L40) -> 0.60973769 | N40: =MEDIAN(D40:L40) -> 0.64334115

Sheet Common Size Statement
B2: Common Size Statement
B4: ="Common Size Income Statement" &" "&" - "&'Data Sheet'!B1 -> Common Size Income Statement - OIL & NATURAL GAS CORPN LTD
B6: Particulars | C6: ='Data Sheet'!$B$16 -> 42094 | D6: ='Data Sheet'!C16 -> 42460 | E6: ='Data Sheet'!D16 -> 42825 | F6: ='Data Sheet'!E16 -> 43190 | G6: ='Data Sheet'!F16 -> 43555 | H6: ='Data Sheet'!G16 -> 43921 | I6: ='Data Sheet'!H16 -> 44286 | J6: ='Data Sheet'!I16 -> 44651 | K6: ='Data Sheet'!J16 -> 45016 | L6: ='Data Sheet'!K16 -> 45382
B8: ='Data Sheet'!A17 -> Sales | C8: ='Data Sheet'!B17/'Data Sheet'!B$17 -> 1 | D8: ='Data Sheet'!C17/'Data Sheet'!C$17 -> 1 | E8: ='Data Sheet'!D17/'Data Sheet'!D$17 -> 1 | F8: ='Data Sheet'!E17/'Data Sheet'!E$17 -> 1 | G8: ='Data Sheet'!F17/'Data Sheet'!F$17 -> 1 | H8: ='Data Sheet'!G17/'Data Sheet'!G$17 -> 1 | I8: ='Data Sheet'!H17/'Data Sheet'!H$17 -> 1 | J8: ='Data Sheet'!I17/'Data Sheet'!I$17 -> 1 | ... L8: ='Data Sheet'!K17/'Data Sheet'!K$17 -> 1
B9: ='Data Sheet'!A18 -> Raw Material Cost | C9: ='Data Sheet'!B18/'Data Sheet'!B$17 -> 0.38473542 | D9: ='Data Sheet'!C18/'Data Sheet'!C$17 -> 0.29561592 | E9: ='Data Sheet'!D18/'Data Sheet'!D$17 -> 0.62078916 | F9: ='Data Sheet'!E18/'Data Sheet'!E$17 -> 0.62688224 | G9: ='Data Sheet'!F18/'Data Sheet'!F$17 -> 0.65348191 | H9: ='Data Sheet'!G18/'Data Sheet'!G$17 -> 0.68050511 | I9: ='Data Sheet'!H18/'Data Sheet'!H$17 -> 0.6776826 | J9: ='Data Sheet'!I18/'Data Sheet'!I$17 -> 0.45927462 | ... L9: ='Data Sheet'!K18/'Data Sheet'!K$17 -> 0.38970407
B10: ='Data Sheet'!A19 -> Change in Inventory | C10: ='Data Sheet'!B19/'Data Sheet'!B$17 -> -0.010706511 | D10: ='Data Sheet'!C19/'Data Sheet'!C$17 -> -0.0060951802 | E10: ='Data Sheet'!D19/'Data Sheet'!D$17 -> 0.016936589 | F10: ='Data Sheet'!E19/'Data Sheet'!E$17 -> 2.5317181e-05 | G10: ='Data Sheet'!F19/'Data Sheet'!F$17 -> 0.0073421354 | H10: ='Data Sheet'!G19/'Data Sheet'!G$17 -> -0.0028875206 | I10: ='Data Sheet'!H19/'Data Sheet'!H$17 -> 0.033066072 | J10: ='Data Sheet'!I19/'Data Sheet'!I$17 -> 0.0046882191 | ... L10: ='Data Sheet'!K19/'Data Sheet'!K$17 -> 0.0074973927
B11: ='Data Sheet'!A20 -> Power and Fuel | C11: ='Data Sheet'!B20/'Data Sheet'!B$17 -> 0.0054454737 | D11: ='Data Sheet'!C20/'Data Sheet'!C$17 -> 0.0095325774 | E11: ='Data Sheet'!D20/'Data Sheet'!D$17 -> 0.0069305758 | F11: ='Data Sheet'!E20/'Data Sheet'!E$17 -> 0.0067476329 | G11: ='Data Sheet'!F20/'Data Sheet'!F$17 -> 0.0050749729 | H11: ='Data Sheet'!G20/'Data Sheet'!G$17 -> 0.0052401657 | I11: ='Data Sheet'!H20/'Data Sheet'!H$17 -> 0.0065178447 | J11: ='Data Sheet'!I20/'Data Sheet'!I$17 -> 0.0045581214 | ... L11: ='Data Sheet'!K20/'Data Sheet'!K$17 -> 0.0051037184
B12: ='Data Sheet'!A21 -> Other Mfr. Exp | C12: ='Data Sheet'!B21/'Data Sheet'!B$17 -> 0.050781543 | D12: ='Data Sheet'!C21/'Data Sheet'!C$17 -> 0.073252695 | E12: ='Data Sheet'!D21/'Data Sheet'!D$17 -> 0.05755649 | F12: ='Data Sheet'!E21/'Data Sheet'!E$17 -> 0.056931925 | G12: ='Data Sheet'!F21/'Data Sheet'!F$17 -> 0.045486839 | H12: ='Data Sheet'!G21/'Data Sheet'!G$17 -> 0.052806091 | I12: ='Data Sheet'!H21/'Data Sheet'!H$17 -> 0.064922234 | J12: ='Data Sheet'!I21/'Data Sheet'!I$17 -> 0.27770126 | ... L12: ='Data Sheet'!K21/'Data Sheet'!K$17 -> 0.35353602
B13: ='Data Sheet'!A22 -> Employee Cost | C13: ='Data Sheet'!B22/'Data Sheet'!B$17 -> 0.058172921 | D13: ='Data Sheet'!C22/'Data Sheet'!C$17 -> 0.074415424 | E13: ='Data Sheet'!D22/'Data Sheet'!D$17 -> 0.053549851 | F13: ='Data Sheet'!E22/'Data Sheet'!E$17 -> 0.046391239 | G13: ='Data Sheet'!F22/'Data Sheet'!F$17 -> 0.037593929 | H13: ='Data Sheet'!G22/'Data Sheet'!G$17 -> 0.039148393 | I13: ='Data Sheet'!H22/'Data Sheet'!H$17 -> 0.046520226 | J13: ='Data Sheet'!I22/'Data Sheet'!I$17 -> 0.031014466 | ... L13: ='Data Sheet'!K22/'Data Sheet'!K$17 -> 0.025838953
B14: ='Data Sheet'!A23 -> Selling and admin | C14: ='Data Sheet'!B23/'Data Sheet'!B$17 -> 0.2565296 | D14: ='Data Sheet'!C23/'Data Sheet'!C$17 -> 0.28810501 | E14: ='Data Sheet'!D23/'Data Sheet'!D$17 -> 0.12877208 | F14: ='Data Sheet'!E23/'Data Sheet'!E$17 -> 0.10638664 | G14: ='Data Sheet'!F23/'Data Sheet'!F$17 -> 0.093973414 | H14: ='Data Sheet'!G23/'Data Sheet'!G$17 -> 0.073999482 | I14: ='Data Sheet'!H23/'Data Sheet'!H$17 -> 0.075708944 | J14: ='Data Sheet'!I23/'Data Sheet'!I$17 -> 0.073990612 | ... L14: ='Data Sheet'!K23/'Data Sheet'!K$17 -> 0.064500763
B15: ='Data Sheet'!A24 -> Other Expenses | C15: ='Data Sheet'!B24/'Data Sheet'!B$17 -> -0.02930725 | D15: ='Data Sheet'!C24/'Data Sheet'!C$17 -> -0.062527799 | E15: ='Data Sheet'!D24/'Data Sheet'!D$17 -> -0.03757317 | F15: ='Data Sheet'!E24/'Data Sheet'!E$17 -> -0.019602067 | G15: ='Data Sheet'!F24/'Data Sheet'!F$17 -> -0.005723252 | H15: ='Data Sheet'!G24/'Data Sheet'!G$17 -> 0.014076423 | I15: ='Data Sheet'!H24/'Data Sheet'!H$17 -> -0.0011082811 | J15: ='Data Sheet'!I24/'Data Sheet'!I$17 -> -0.0044446549 | ... L15: ='Data Sheet'!K24/'Data Sheet'!K$17 -> -0.00507198
B16: ='Data Sheet'!A25 -> Other Income | C16: ='Data Sheet'!B25/'Data Sheet'!B$17 -> 0.037003867 | D16: ='Data Sheet'!C25/'Data Sheet'!C$17 -> 0.0086044575 | E16: ='Data Sheet'!D25/'Data Sheet'!D$17 -> 0.045040371 | F16: ='Data Sheet'!E25/'Data Sheet'!E$17 -> 0.032318574 | G16: ='Data Sheet'!F25/'Data Sheet'!F$17 -> 0.022691074 | H16: ='Data Sheet'!G25/'Data Sheet'!G$17 -> 0.0024744667 | I16: ='Data Sheet'!H25/'Data Sheet'!H$17 -> 0.037092481 | J16: ='Data Sheet'!I25/'Data Sheet'!I$17 -> 0.013835668 | ... L16: ='Data Sheet'!K25/'Data Sheet'!K$17 -> 0.021950663
B17: ='Data Sheet'!A26 -> Depreciation | C17: ='Data Sheet'!B26/'Data Sheet'!B$17 -> 0.11205987 | D17: ='Data Sheet'!C26/'Data Sheet'!C$17 -> 0.13209148 | E17: ='Data Sheet'!D26/'Data Sheet'!D$17 -> 0.071570841 | F17: ='Data Sheet'!E26/'Data Sheet'!E$17 -> 0.071619143 | G17: ='Data Sheet'!F26/'Data Sheet'!F$17 -> 0.056220006 | H17: ='Data Sheet'!G26/'Data Sheet'!G$17 -> 0.067136391 | I17: ='Data Sheet'!H26/'Data Sheet'!H$17 -> 0.084049898 | J17: ='Data Sheet'!I26/'Data Sheet'!I$17 -> 0.054724409 | ... L17: ='Data Sheet'!K26/'Data Sheet'!K$17 -> 0.048635326
B18: ='Data Sheet'!A27 -> Interest | C18: ='Data Sheet'!B27/'Data Sheet'!B$17 -> 0.017795818 | D18: ='Data Sheet'!C27/'Data Sheet'!C$17 -> 0.030358838 | E18: ='Data Sheet'!D27/'Data Sheet'!D$17 -> 0.012711619 | F18: ='Data Sheet'!E27/'Data Sheet'!E$17 -> 0.015491016 | G18: ='Data Sheet'!F27/'Data Sheet'!F$17 -> 0.01384345 | H18: ='Data Sheet'!G27/'Data Sheet'!G$17 -> 0.018877774 | I18: ='Data Sheet'!H27/'Data Sheet'!H$17 -> 0.016715643 | J18: ='Data Sheet'!I27/'Data Sheet'!I$17 -> 0.011595081 | ... L18: ='Data Sheet'!K27/'Data Sheet'!K$17 -> 0.017237461
B19: ='Data Sheet'!A28 -> Profit before tax | C19: ='Data Sheet'!B28/'Data Sheet'!B$17 -> 0.17008396 | D19: ='Data Sheet'!C28/'Data Sheet'!C$17 -> 0.16166514 | E19: ='Data Sheet'!D28/'Data Sheet'!D$17 -> 0.14766951 | F19: ='Data Sheet'!E28/'Data Sheet'!E$17 -> 0.12149613 | G19: ='Data Sheet'!F28/'Data Sheet'!F$17 -> 0.13008194 | H19: ='Data Sheet'!G28/'Data Sheet'!G$17 -> 0.047797116 | I19: ='Data Sheet'!H28/'Data Sheet'!H$17 -> 0.099149442 | J19: ='Data Sheet'!I28/'Data Sheet'!I$17 -> 0.11010997 | ... L19: ='Data Sheet'!K28/'Data Sheet'!K$17 -> 0.12996372
... B23: ='Data Sheet'!A32 -> EBITDA | C23: ='Data Sheet'!B32/'Data Sheet'!B$17 -> 0.30404454 | D23: ='Data Sheet'!C32/'Data Sheet'!C$17 -> 0.32229065 | E23: ='Data Sheet'!D32/'Data Sheet'!D$17 -> 0.21513864 | F23: ='Data Sheet'!E32/'Data Sheet'!E$17 -> 0.19632869 | G23: ='Data Sheet'!F32/'Data Sheet'!F$17 -> 0.19210039 | H23: ='Data Sheet'!G32/'Data Sheet'!G$17 -> 0.13216617 | I23: ='Data Sheet'!H32/'Data Sheet'!H$17 -> 0.18327563 | J23: ='Data Sheet'!I32/'Data Sheet'!I$17 -> 0.16875111 | ... L23: ='Data Sheet'!K32/'Data Sheet'!K$17 -> 0.18251304
B26: ="Common Size Balance Sheet" &" "&" - "&'Data Sheet'!B1 -> Common Size Balance Sheet - OIL & NATURAL GAS CORPN LTD
B28: Particulars | C28: ='Data Sheet'!$B$16 -> 42094 | D28: ='Data Sheet'!C16 -> 42460 | E28: ='Data Sheet'!$B$16 -> 42094 | F28: ='Data Sheet'!E16 -> 43190 | G28: ='Data Sheet'!$B$16 -> 42094 | H28: ='Data Sheet'!G16 -> 43921 | I28: ='Data Sheet'!$B$16 -> 42094 | J28: ='Data Sheet'!I16 -> 44651 | K28: ='Data Sheet'!$B$16 -> 42094 | L28: ='Data Sheet'!K16 -> 45382
B30: Total Liabilities | C30: ='Data Sheet'!B61/'Data Sheet'!B$61 -> 1 | D30: ='Data Sheet'!C61/'Data Sheet'!C$61 -> 1 | E30: ='Data Sheet'!D61/'Data Sheet'!D$61 -> 1 | F30: ='Data Sheet'!E61/'Data Sheet'!E$61 -> 1 | G30: ='Data Sheet'!F61/'Data Sheet'!F$61 -> 1 | H30: ='Data Sheet'!G61/'Data Sheet'!G$61 -> 1 | I30: ='Data Sheet'!H61/'Data Sheet'!H$61 -> 1 | J30: ='Data Sheet'!I61/'Data Sheet'!I$61 -> 1 | ... L30: ='Data Sheet'!K61/'Data Sheet'!K$61 -> 1
B31: ='Data Sheet'!A57 -> Equity Share Capital | C31: ='Data Sheet'!B57/'Data Sheet'!B$61 -> 0.012661843 | D31: ='Data Sheet'!C57/'Data Sheet'!C$61 -> 0.012516401 | E31: ='Data Sheet'!D57/'Data Sheet'!D$61 -> 0.014434791 | F31: ='Data Sheet'!E57/'Data Sheet'!E$61 -> 0.013972512 | G31: ='Data Sheet'!F57/'Data Sheet'!F$61 -> 0.012775943 | H31: ='Data Sheet'!G57/'Data Sheet'!G$61 -> 0.012373318 | I31: ='Data Sheet'!H57/'Data Sheet'!H$61 -> 0.01161083 | J31: ='Data Sheet'!I57/'Data Sheet'!I$61 -> 0.010784462 | ... L31: ='Data Sheet'!K57/'Data Sheet'!K$61 -> 0.0088621739
B32: ='Data Sheet'!A58 -> Reserves | C32: ='Data Sheet'!B58/'Data Sheet'!B$61 -> 0.52146939 | D32: ='Data Sheet'!C58/'Data Sheet'!C$61 -> 0.56627127 | E32: ='Data Sheet'!D58/'Data Sheet'!D$61 -> 0.42285238 | F32: ='Data Sheet'!E58/'Data Sheet'!E$61 -> 0.43028824 | G32: ='Data Sheet'!F58/'Data Sheet'!F$61 -> 0.4278407 | H32: ='Data Sheet'!G58/'Data Sheet'!G$61 -> 0.39108677 | I32: ='Data Sheet'!H58/'Data Sheet'!H$61 -> 0.39629309 | J32: ='Data Sheet'!I58/'Data Sheet'!I$61 -> 0.43413397 | ... L32: ='Data Sheet'!K58/'Data Sheet'!K$61 -> 0.46603584
B33: ='Data Sheet'!A59 -> Borrowings | C33: ='Data Sheet'!B59/'Data Sheet'!B$61 -> 0.15967151 | D33: ='Data Sheet'!C59/'Data Sheet'!C$61 -> 0.13313004 | E33: ='Data Sheet'!D59/'Data Sheet'!D$61 -> 0.1800331 | F33: ='Data Sheet'!E59/'Data Sheet'!E$61 -> 0.23201747 | G33: ='Data Sheet'!F59/'Data Sheet'!F$61 -> 0.21883448 | H33: ='Data Sheet'!G59/'Data Sheet'!G$61 -> 0.25468465 | I33: ='Data Sheet'!H59/'Data Sheet'!H$61 -> 0.24584679 | J33: ='Data Sheet'!I59/'Data Sheet'!I$61 -> 0.20914508 | ... L33: ='Data Sheet'!K59/'Data Sheet'!K$61 -> 0.21581594
B34: ='Data Sheet'!A60 -> Other Liabilities | C34: ='Data Sheet'!B60/'Data Sheet'!B$61 -> 0.30619726 | D34: ='Data Sheet'!C60/'Data Sheet'!C$61 -> 0.28808229 | E34: ='Data Sheet'!D60/'Data Sheet'!D$61 -> 0.38267973 | F34: ='Data Sheet'!E60/'Data Sheet'!E$61 -> 0.32372178 | G34: ='Data Sheet'!F60/'Data Sheet'!F$61 -> 0.34054887 | H34: ='Data Sheet'!G60/'Data Sheet'!G$61 -> 0.34185526 | I34: ='Data Sheet'!H60/'Data Sheet'!H$61 -> 0.34624929 | J34: ='Data Sheet'!I60/'Data Sheet'!I$61 -> 0.34593649 | ... L34: ='Data Sheet'!K60/'Data Sheet'!K$61 -> 0.30928604
B36: Total Assets | C36: ='Data Sheet'!B76/'Data Sheet'!B$76 -> 1 | D36: ='Data Sheet'!C76/'Data Sheet'!C$76 -> 1 | E36: ='Data Sheet'!D76/'Data Sheet'!D$76 -> 1 | F36: ='Data Sheet'!E76/'Data Sheet'!E$76 -> 1 | G36: ='Data Sheet'!F76/'Data Sheet'!F$76 -> 1 | H36: ='Data Sheet'!G76/'Data Sheet'!G$76 -> 1 | I36: ='Data Sheet'!H76/'Data Sheet'!H$76 -> 1 | J36: ='Data Sheet'!I76/'Data Sheet'!I$76 -> 1 | ... L36: ='Data Sheet'!K76/'Data Sheet'!K$76 -> 1
B37: ='Data Sheet'!A62 -> Net Block | C37: ='Data Sheet'!B62/'Data Sheet'!B$76 -> 0.53258781 | D37: ='Data Sheet'!C62/'Data Sheet'!C$76 -> 0.48651307 | E37: ='Data Sheet'!D62/'Data Sheet'!D$76 -> 0.47494579 | F37: ='Data Sheet'!E62/'Data Sheet'!E$76 -> 0.49225116 | G37: ='Data Sheet'!F62/'Data Sheet'!F$76 -> 0.46794727 | H37: ='Data Sheet'!G62/'Data Sheet'!G$76 -> 0.47975848 | I37: ='Data Sheet'!H62/'Data Sheet'!H$76 -> 0.44992601 | J37: ='Data Sheet'!I62/'Data Sheet'!I$76 -> 0.4361732 | ... L37: ='Data Sheet'!K62/'Data Sheet'!K$76 -> 0.42049214
B38: ='Data Sheet'!A63 -> Capital Work in Progress | C38: ='Data Sheet'!B63/'Data Sheet'!B$76 -> 0.18763953 | D38: ='Data Sheet'!C63/'Data Sheet'!C$76 -> 0.16873359 | E38: ='Data Sheet'!D63/'Data Sheet'!D$76 -> 0.13282141 | F38: ='Data Sheet'!E63/'Data Sheet'!E$76 -> 0.13394497 | G38: ='Data Sheet'!F63/'Data Sheet'!F$76 -> 0.14026075 | H38: ='Data Sheet'!G63/'Data Sheet'!G$76 -> 0.16490624 | I38: ='Data Sheet'!H63/'Data Sheet'!H$76 -> 0.18515783 | J38: ='Data Sheet'!I63/'Data Sheet'!I$76 -> 0.1829704 | ... L38: ='Data Sheet'!K63/'Data Sheet'!K$76 -> 0.16346286
B39: ='Data Sheet'!A64 -> Investments | C39: ='Data Sheet'!B64/'Data Sheet'!B$76 -> 0.014057091 | D39: ='Data Sheet'!C64/'Data Sheet'!C$76 -> 0.097687385 | E39: ='Data Sheet'!D64/'Data Sheet'!D$76 -> 0.1591488 | F39: ='Data Sheet'!E64/'Data Sheet'!E$76 -> 0.14662426 | G39: ='Data Sheet'!F64/'Data Sheet'!F$76 -> 0.13589892 | H39: ='Data Sheet'!G64/'Data Sheet'!G$76 -> 0.11164279 | I39: ='Data Sheet'!H64/'Data Sheet'!H$76 -> 0.11134402 | J39: ='Data Sheet'!I64/'Data Sheet'!I$76 -> 0.11425813 | ... L39: ='Data Sheet'!K64/'Data Sheet'!K$76 -> 0.14399965
B40: ='Data Sheet'!A65 -> Other Assets | C40: ='Data Sheet'!B74/'Data Sheet'!B$76 -> 0.12876701 | D40: ='Data Sheet'!C74/'Data Sheet'!C$76 -> 0.11896105 | E40: ='Data Sheet'!D74/'Data Sheet'!D$76 -> 0.10639799 | F40: ='Data Sheet'!E74/'Data Sheet'!E$76 -> 0.11783284 | G40: ='Data Sheet'!F74/'Data Sheet'!F$76 -> 0.14181507 | H40: ='Data Sheet'!G74/'Data Sheet'!G$76 -> 0.13967497 | I40: ='Data Sheet'!H74/'Data Sheet'!H$76 -> 0.12631004 | J40: ='Data Sheet'!I74/'Data Sheet'!I$76 -> 0.12705749 | ... L40: ='Data Sheet'!K74/'Data Sheet'!K$76 -> 0.11747805
B41: ='Data Sheet'!A67 -> Receivables | C41: ='Data Sheet'!B67/'Data Sheet'!B$76 -> 0.055693389 | D41: ='Data Sheet'!C67/'Data Sheet'!C$76 -> 0.02437795 | E41: ='Data Sheet'!D67/'Data Sheet'!D$76 -> 0.028225884 | F41: ='Data Sheet'!E67/'Data Sheet'!E$76 -> 0.030266092 | G41: ='Data Sheet'!F67/'Data Sheet'!F$76 -> 0.031271798 | H41: ='Data Sheet'!G67/'Data Sheet'!G$76 -> 0.018044962 | I41: ='Data Sheet'!H67/'Data Sheet'!H$76 -> 0.029563266 | J41: ='Data Sheet'!I67/'Data Sheet'!I$76 -> 0.032896643 | ... L41: ='Data Sheet'!K67/'Data Sheet'!K$76 -> 0.027844007
B42: ='Data Sheet'!A68 -> Inventory | C42: ='Data Sheet'!B68/'Data Sheet'!B$76 -> 0.033609518 | D42: ='Data Sheet'!C68/'Data Sheet'!C$76 -> 0.031488706 | E42: ='Data Sheet'!D68/'Data Sheet'!D$76 -> 0.068737097 | F42: ='Data Sheet'!E68/'Data Sheet'!E$76 -> 0.068056108 | G42: ='Data Sheet'!F68/'Data Sheet'!F$76 -> 0.073016959 | H42: ='Data Sheet'!G68/'Data Sheet'!G$76 -> 0.067009303 | I42: ='Data Sheet'!H68/'Data Sheet'!H$76 -> 0.084422794 | J42: ='Data Sheet'!I68/'Data Sheet'!I$76 -> 0.09491533 | ... L42: ='Data Sheet'!K68/'Data Sheet'!K$76 -> 0.075031271
B43: ='Data Sheet'!A69 -> Cash & Bank | C43: ='Data Sheet'!B69/'Data Sheet'!B$76 -> 0.047645653 | D43: ='Data Sheet'!C69/'Data Sheet'!C$76 -> 0.072238254 | E43: ='Data Sheet'!D69/'Data Sheet'!D$76 -> 0.029723031 | F43: ='Data Sheet'!E69/'Data Sheet'!E$76 -> 0.011024571 | G43: ='Data Sheet'!F69/'Data Sheet'!F$76 -> 0.0097892265 | H43: ='Data Sheet'!G69/'Data Sheet'!G$76 -> 0.018963261 | I43: ='Data Sheet'!H69/'Data Sheet'!H$76 -> 0.013276034 | J43: ='Data Sheet'!I69/'Data Sheet'!I$76 -> 0.01172881 | ... L43: ='Data Sheet'!K69/'Data Sheet'!K$76 -> 0.051692008

Sheet Forecasting
B2: ='Data Sheet'!B1&" - "&'Data Sheet'!A17&" Forecasting" -> OIL & NATURAL GAS CORPN LTD - Sales Forecasting | G2: ='Data Sheet'!B1&" - "&'Historical FS'!B19&" Forecasting" -> OIL & NATURAL GAS CORPN LTD - EBITDA Forecasting | L2: ='Data Sheet'!B1&" - "&'Historical FS'!B39&" Forecasting" -> OIL & NATURAL GAS CORPN LTD - EPS Forecasting
B3: Year Weight | C3: Year | D3: Sales | E3: Sales Growth | G3: Year Weight | H3: Year | I3: EBITDA | J3: EBITDA Growth | L3: Year Weight | M3: Year | N3: EPS | O3: EPS Growth
B4: 1 | C4: 42094 | D4: {=TRANSPOSE('Data Sheet'!B17:K17)} -> 160922.64 | G4: 1 | H4: 42094 | I4: {=TRANSPOSE('Historical FS'!C19:L19)} -> 42312.32 | L4: 1 | M4: 42094 | N4: {=TRANSPOSE('Historical FS'!C39:L39)} -> 9.131152
B5: 2 | C5: 42460 | D5: 124035.71 | E5: =D5/D4-1 -> -0.22922151 | G5: 2 | H5: 42460 | I5: 39134.63 | J5: =I5/I4-1 -> -0.075100822 | L5: 2 | M5: 42460 | N5: 9.3774663 | O5: =N5/N4-1 -> 0.026975156
B6: 3 | C6: 42825 | D6: 282506.11 | E6: =D6/D5-1 -> 1.2776192 | G6: 3 | H6: 42825 | I6: 52803.67 | J6: =I6/I5-1 -> 0.34928246 | L6: 3 | M6: 42825 | N6: 12.814372 | O6: =N6/N5-1 -> 0.36650687
B7: 4 | C7: 43190 | D7: 322705.76 | E7: =D7/D6-1 -> 0.14229657 | G7: 4 | H7: 43190 | I7: 56889.06 | J7: =I7/I6-1 -> 0.077369433 | L7: 4 | M7: 43190 | N7: 12.186041 | O7: =N7/N6-1 -> -0.04903332
B8: 5 | C8: 43555 | D8: 421623.93 | E8: =D8/D7-1 -> 0.30652744 | G8: 5 | H8: 43555 | I8: 74818.99 | J8: =I8/I7-1 -> 0.3151736 | L8: 5 | M8: 43555 | N8: 19.37228 | O8: =N8/N7-1 -> 0.58971077
B9: 6 | C9: 43921 | D9: 396727.91 | E9: =D9/D8-1 -> -0.059047929 | G9: 6 | H9: 43921 | I9: 52104.98 | J9: =I9/I8-1 -> -0.30358616 | L9: 6 | M9: 43921 | N9: 8.3261687 | O9: =N9/N8-1 -> -0.57020193
B10: 7 | C10: 44286 | D10: 303848.91 | E10: =D10/D9-1 -> -0.23411259 | G10: 7 | H10: 44286 | I10: 49473.44 | J10: =I10/I9-1 -> -0.050504577 | L10: 7 | M10: 44286 | N10: 8.0202698 | O10: =N10/N9-1 -> -0.036739456
B11: 8 | C11: 44651 | D11: 491246.24 | E11: =D11/D10-1 -> 0.61674511 | G11: 8 | H11: 44651 | I11: 79873.59 | J11: =I11/I10-1 -> 0.61447415 | L11: 8 | M11: 44651 | N11: 33.780872 | O11: =N11/N10-1 -> 3.2119371
B12: 9 | C12: 45016 | D12: 632291.18 | E12: =D12/D11-1 -> 0.28711658 | G12: 9 | H12: 45016 | I12: 75526.99 | J12: =I12/I11-1 -> -0.054418488 | L12: 9 | M12: 45016 | N12: 26.078408 | O12: =N12/N11-1 -> -0.22801257
B13: 10 | C13: 45382 | D13: 591396.26 | E13: =D13/D12-1 -> -0.064677353 | G13: 10 | H13: 45382 | I13: 102835.44 | J13: =I13/I12-1 -> 0.36157207 | L13: 10 | M13: 45382 | N13: 35.070141 | O13: =N13/N12-1 -> 0.34479609
B14: 11 | C14: 45747 | D14: =FORECAST(B14,$D$4:$D$13,$B$4:$B$13) -> 652539.96 | E14: =D14/D13-1 -> 0.10338872 | G14: 11 | H14: 45747 | I14: =FORECAST(G14,$I$4:$I$13,$G$4:$G$13) -> 92238.755 | J14: =I14/I13-1 -> -0.10304507 | L14: 11 | M14: 45747 | N14: =FORECAST(L14,$N$4:$N$13,$L$4:$L$13) -> 31.803936 | O14: =N14/N13-1 -> -0.093133505
B15: 12 | C15: 46112 | D15: =FORECAST(B15,$D$4:$D$13,$B$4:$B$13) -> 703414.42 | E15: =D15/D14-1 -> 0.077963737 | G15: 12 | H15: 46112 | I15: =FORECAST(G15,$I$4:$I$13,$G$4:$G$13) -> 97631.745 | J15: =I15/I14-1 -> 0.058467722 | L15: 12 | M15: 46112 | N15: =FORECAST(L15,$N$4:$N$13,$L$4:$L$13) -> 34.419976 | O15: =N15/N14-1 -> 0.082255222
B16: 13 | C16: 46477 | D16: =FORECAST(B16,$D$4:$D$13,$B$4:$B$13) -> 754288.87 | E16: =D16/D15-1 -> 0.072325009 | G16: 13 | H16: 46477 | I16: =FORECAST(G16,$I$4:$I$13,$G$4:$G$13) -> 103024.74 | J16: =I16/I15-1 -> 0.055238077 | L16: 13 | M16: 46477 | N16: =FORECAST(L16,$N$4:$N$13,$L$4:$L$13) -> 37.036016 | O16: =N16/N15-1 -> 0.076003534
B17: 14 | C17: 46843 | D17: =FORECAST(B17,$D$4:$D$13,$B$4:$B$13) -> 805163.33 | E17: =D17/D16-1 -> 0.067446911 | G17: 14 | H17: 46843 | I17: =FORECAST(G17,$I$4:$I$13,$G$4:$G$13) -> 108417.72 | J17: =I17/I16-1 -> 0.052346554 | L17: 14 | M17: 46843 | N17: =FORECAST(L17,$N$4:$N$13,$L$4:$L$13) -> 39.652056 | O17: =N17/N16-1 -> 0.070635023
B18: 15 | C18: 47208 | D18: =FORECAST(B18,$D$4:$D$13,$B$4:$B$13) -> 856037.78 | E18: =D18/D17-1 -> 0.06318526 | G18: 15 | H18: 47208 | I18: =FORECAST(G18,$I$4:$I$13,$G$4:$G$13) -> 113810.71 | J18: =I18/I17-1 -> 0.049742695 | L18: 15 | M18: 47208 | N18: =FORECAST(L18,$N$4:$N$13,$L$4:$L$13) -> 42.268096 | O18: =N18/N17-1 -> 0.065974885
B19: 16 | C19: 47573 | D19: =FORECAST(B19,$D$4:$D$13,$B$4:$B$13) -> 906912.23 | E19: =D19/D18-1 -> 0.059430151 | G19: 16 | H19: 47573 | I19: =FORECAST(G19,$I$4:$I$13,$G$4:$G$13) -> 119203.7 | J19: =I19/I18-1 -> 0.047385608 | L19: 16 | M19: 47573 | N19: =FORECAST(L19,$N$4:$N$13,$L$4:$L$13) -> 44.884135 | O19: =N19/N18-1 -> 0.061891594

Sheet WACC
B2: Weighted Average Cost of Capital
B4: All figures are in INR unless stated otherwise
B5: PeerCompos
H6: Debt/ | I6: Debt/ | J6: Levered | K6: Unlevered
B7: Name of the Company | D7: Country | E7: Total Debt | F7: Total Equity | G7: Tax Rate 1 | H7: Equity | I7: Capital | J7: Beta 2 | K7: Beta 3
B8: ONGC | D8: India | E8: 187817.31 | F8: 307084.57 | G8: 0.3 | H8: 0.55 | I8: =E8/(SUM(E8:F8)) -> 0.37950414 | J8: =BETA!J8 -> 1.1431569 | K8: =J8/(1+(1-G8)*H8) -> 0.82538401
B9: Oil Indial | D9: India | E9: 30645.24 | F9: 70196.32 | G9: 0.3 | H9: 0.62 | I9: =E9/(SUM(E9:F9)) -> 0.30389494 | J9: 1.41 | K9: =J9/(1+(1-G9)*H9) -> 0.9832636
B10: Deep industries | D10: India | E10: 205.37 | F10: 2705.28 | G10: 0.3 | H10: 0.11 | I10: =E10/(SUM(E10:F10)) -> 0.070558123 | J10: 2.38 | K10: =J10/(1+(1-G10)*H10) -> 2.2098422
B11: Hind. Oil Explore | D11: India | E11: 145.13 | F11: 2401.55 | G11: 0.3 | H11: 0.12 | I11: =E11/(SUM(E11:F11)) -> 0.056987922 | J11: 1.13 | K11: =J11/(1+(1-G11)*H11) -> 1.0424354
B12: Asian Energy | D12: India | E12: 24.07 | F12: 1408.61 | G12: 0.3 | H12: 0.06 | I12: =E12/(SUM(E12:F12)) -> 0.016800681 | J12: 1.53 | K12: =J12/(1+(1-G12)*H12) -> 1.4683301
F14: Average | G14: =AVERAGE(G8:G12) -> 0.3 | H14: =AVERAGE(H8:H12) -> 0.292 | I14: =AVERAGE(I8:I12) -> 0.16554916 | J14: =AVERAGE(J8:J12) -> 1.5186314 | K14: =AVERAGE(K8:K12) -> 1.3058511
F15: Media | G15: =MEDIAN(G8:G12) -> 0.3 | H15: =MEDIAN(H8:H12) -> 0.12 | I15: =MEDIAN(I8:I12) -> 0.070558123 | J15: =MEDIAN(J8:J12) -> 1.41 | K15: =MEDIAN(K8:K12) -> 1.0424354
B17: Cost of Debt | G17: Cost of Equity
B19: Pre-Tax Cost of Debt | E19: =10194/E8 -> 0.054276147 | F19: =E19/0.7 -> 0.077537353 | G19: Risk Free Rate | K19: 0.0622
B20: Tax Rate | E20: 0.3 | G20: Equity Risk Premium | K20: =Rm!G7-WACC!K19 -> 0.105048
B21: Post Tax cost of Debt | E21: =E19*(1-E20) -> 0.037993303 | G21: Levered Beta 4 | K21: =K30 -> 1.1872037
G22: Cost of Equity | K22: =K19+K20*K21 -> 0.18691338
B25: Capital Structure | G25: Capital Structure
D27: Current | E27: Target | G27: Comps Median Unlevered Beta | K27: =K15 -> 1.0424354
B28: Total Debt | C28: =E8 -> 187817.31 | D28: =C28/C30 -> 0.37950414 | E28: =I14 -> 0.16554916 | G28: Target Debt / Equity | K28: =E32 -> 0.19839295
B29: Market Capitalization | C29: =F8 -> 307084.57 | D29: =C29/C30 -> 0.62049586 | E29: =1-E28 -> 0.83445084 | G29: Tax Rate | K29: =E20 -> 0.3
B30: Total Capital | C30: =SUM(C28:C29) -> 494901.88 | D30: =C30/C30 -> 1 | E30: =E29+E28 -> 1 | G30: Levered Beta | K30: =K27*(1+(1-K29)*K28) -> 1.1872037
B32: Debt / Equity | D32: =D28/D29 -> 0.61161429 | E32: =E28/E29 -> 0.19839295 | G32: Weighted Average Cost of Capital
B34: Notes: | J34: Total Cost | K34: Total Weight
B35: 1. Tax Rate considered as Marginal Tax Rate for the country | G35: Debt | J35: =E21 -> 0.037993303 | K35: =E28 -> 0.16554916
B36: 2. Levered beta is based on 1 year dialy data | G36: Equity | J36: =K22 -> 0.18691338 | K36: =E29 -> 0.83445084
B37: 3. Unlevered Beta = Levered Beta/(1+(1-Tax Rate)*Debt/Equity) | G37: Weighted Average Cost of Capital | K37: =SUMPRODUCT(J35:J36,K35:K36) -> 0.16225978
B38: 4. Unlevered Beta = UnLevered Beta/(1+(1-Tax Rate)*Debt/Equity)

Sheet BETA
B4: Regression Beta - One Year Dialy
B6: ONGC Daily Returns | F6: NIFTY Return | I6: Beta Drifting | L6: Beta 1 | M6: =SLOPE(D9:D218,G9:G218) -> 1.1431569
L7: Beta 2 | M7: =_xlfn.COVARIANCE.S(D9:D218,G9:G218)/_xlfn.VAR.S(G9:G218) -> 1.1431569
B8: Date | C8: Closing Price | D8: Return | F8: Closing Price | G8: Return | I8: Levered Raw Beta | J8: =M6 -> 1.1431569 | L8: Beta 3 | M8: =M28 -> 1.1431569
B9: 45743 | C9: 242.17 | F9: 23591.95 | I9: Raw Beta Weight | J9: 0.75
B10: 45744 | C10: 246.38 | D10: =C10/C9-1 -> 0.017384482 | F10: 23519.35 | G10: =F10/F9-1 -> -0.0030773209
B11: 45748 | C11: 248.07 | D11: =C11/C10-1 -> 0.006859323 | F11: 23165.7 | G11: =F11/F10-1 -> -0.015036555 | I11: Market Beta | J11: 1 | L11: SUMMARY OUTPUT
B12: 45749 | C12: 250.64 | D12: =C12/C11-1 -> 0.010359979 | F12: 23332.35 | G12: =F12/F11-1 -> 0.0071938254 | I12: Market Beta Weight | J12: 0.25
B13: 45750 | C13: 243.31 | D13: =C13/C12-1 -> -0.029245132 | F13: 23250.1 | G13: =F13/F12-1 -> -0.0035251486 | L13: Regression Statistics
B14: 45751 | C14: 226.01 | D14: =C14/C13-1 -> -0.071102708 | F14: 22904.45 | G14: =F14/F13-1 -> -0.014866603 | I14: Adjusted Beta | J14: =(J8*J9)+(J12*J11) -> 1.1073676 | L14: Multiple R | M14: 0.65677463
B15: 45754 | C15: 219.84 | D15: =C15/C14-1 -> -0.027299677 | F15: 22161.6 | G15: =F15/F14-1 -> -0.032432562 | L15: R Square | M15: 0.43135291
B16: 45755 | C16: 226.66 | D16: =C16/C15-1 -> 0.031022562 | F16: 22535.85 | G16: =F16/F15-1 -> 0.016887319 | L16: Adjusted R Square | M16: 0.414628
B17: 45756 | C17: 221.94 | D17: =C17/C16-1 -> -0.020824142 | F17: 22399.15 | G17: =F17/F16-1 -> -0.0060658906 | L17: Standard Error | M17: 0.017179608
B18: 45758 | C18: 230.37 | D18: =C18/C17-1 -> 0.037983239 | F18: 22828.55 | G18: =F18/F17-1 -> 0.01917037 | L18: Observations | M18: 36
B19: 45762 | C19: 232.69 | D19: =C19/C18-1 -> 0.010070756 | F19: 23328.55 | G19: =F19/F18-1 -> 0.021902399
B20: 45763 | C20: 241.22 | D20: =C20/C19-1 -> 0.036658215 | F20: 23437.2 | G20: =F20/F19-1 -> 0.0046573833 | L20: ANOVA
B21: 45764 | C21: 243.49 | D21: =C21/C20-1 -> 0.0094104966 | F21: 23851.65 | G21: =F21/F20-1 -> 0.017683426 | M21: df | N21: SS | O21: MS | P21: F | Q21: Significance F
B22: 45768 | C22: 249.78 | D22: =C22/C21-1 -> 0.025832683 | F22: 24125.55 | G22: =F22/F21-1 -> 0.011483482 | L22: Regression | M22: 1 | N22: 0.0076119393 | O22: 0.0076119393 | P22: 25.791038 | Q22: 1.3589364e-05
B23: 45769 | C23: 247.78 | D23: =C23/C22-1 -> -0.0080070462 | F23: 24167.25 | G23: =F23/F22-1 -> 0.001728458 | L23: Residual | M23: 34 | N23: 0.010034723 | O23: 0.00029513892
B24: 45770 | C24: 252.17 | D24: =C24/C23-1 -> 0.01771733 | F24: 24328.95 | G24: =F24/F23-1 -> 0.006690873 | L24: Total | M24: 35 | N24: 0.017646663
B25: 45771 | C25: 249.37 | D25: =C25/C24-1 -> -0.011103621 | F25: 24246.7 | G25: =F25/F24-1 -> -0.003380746
B26: 45772 | C26: 246.33 | D26: =C26/C25-1 -> -0.012190721 | F26: 24039.35 | G26: =F26/F25-1 -> -0.0085516792 | M26: Coefficients | N26: Standard Error | O26: t Stat | P26: P-value | Q26: Lower 95% | R26: Upper 95% | S26: Lower 95.0% | T26: Upper 95.0% | U26: Lower 95.0% | V26: Upper 95.0%
B27: 45775 | C27: 250.6 | D27: =C27/C26-1 -> 0.01733447 | F27: 24328.5 | G27: =F27/F26-1 -> 0.012028195 | L27: Intercept | M27: -0.0012630961 | N27: 0.0028838609 | O27: -0.43798788 | P27: 0.66416516 | Q27: -0.0071238065 | R27: 0.0045976143 | S27: -0.0071238065 | T27: 0.0045976143 | U27: -0.0030257378 | V27: 0.0013673757
B28: 45776 | C28: 245.68 | D28: =C28/C27-1 -> -0.019632881 | F28: 24335.95 | G28: =F28/F27-1 -> 0.00030622521 | L28: X Variable 1 | M28: 1.1431569 | N28: 0.22509788 | O28: 5.0784878 | P28: 1.3589364e-05 | Q28: 0.68570291 | R28: 1.6006108 | S28: 0.68570291 | T28: 1.6006108 | U28: 1.3248892 | V28: 1.771357
B29: 45777 | C29: 244.45 | D29: =C29/C28-1 -> -0.0050065125 | F29: 24334.2 | G29: =F29/F28-1 -> -7.1910075e-05
B30: 45779 | C30: 243.42 | D30: =C30/C29-1 -> -0.0042135406 | F30: 24346.7 | G30: =F30/F29-1 -> 0.00051368033
B31: 45782 | C31: 239.2 | D31: =C31/C30-1 -> -0.017336291 | F31: 24461.15 | G31: =F31/F30-1 -> 0.0047008424
B32: 45783 | C32: 237 | D32: =C32/C31-1 -> -0.0091973244 | F32: 24379.6 | G32: =F32/F31-1 -> -0.003333858
B33: 45784 | C33: 238.67 | D33: =C33/C32-1 -> 0.0070464135 | F33: 24414.4 | G33: =F33/F32-1 -> 0.0014274229
B34: 45785 | C34: 233.22 | D34: =C34/C33-1 -> -0.022834877 | F34: 24273.8 | G34: =F34/F33-1 -> -0.0057588964
B35: 45786 | C35: 234.96 | D35: =C35/C34-1 -> 0.0074607667 | F35: 24008 | G35: =F35/F34-1 -> -0.010950078
B36: 45789 | C36: 244.02 | D36: =C36/C35-1 -> 0.038559755 | F36: 24924.7 | G36: =F36/F35-1 -> 0.038183106
B37: 45790 | C37: 241.16 | D37: =C37/C36-1 -> -0.011720351 | F37: 24578.35 | G37: =F37/F36-1 -> -0.013895854
B38: 45791 | C38: 246.01 | D38: =C38/C37-1 -> 0.02011113 | F38: 24666.9 | G38: =F38/F37-1 -> 0.0036027642
B39: 45792 | C39: 247.61 | D39: =C39/C38-1 -> 0.0065038007 | F39: 25062.1 | G39: =F39/F38-1 -> 0.01602147
B40: 45793 | C40: 247.27 | D40: =C40/C39-1 -> -0.0013731271 | F40: 25019.8 | G40: =F40/F39-1 -> -0.0016878075
... B45: 45800 | C45: 244.24 | D45: =C45/C44-1 -> 0.010634336 | F45: 24853.15 | G45: =F45/F44-1 -> 0.0098924408

Sheet Intristic Growth
B2: ="Intrinsic Growth of - "&'Profit & Loss'!A1 -> Intrinsic Growth of - OIL & NATURAL GAS CORPN LTD
B4: Calculation of ROIC
B6: Particulars | D6: ='Historical FS'!H3 -> 43921 | E6: ='Historical FS'!I3 -> 44286 | F6: ='Historical FS'!J3 -> 44651 | G6: ='Historical FS'!K3 -> 45016 | H6: ='Historical FS'!L3 -> 45382
B8: Current Assets
B9: ='Raw FS'!B36 -> Inventories | D9: ='Raw FS'!H36 -> 34065 | E9: ='Raw FS'!I36 -> 45736 | F9: ='Raw FS'!J36 -> 55360 | G9: ='Raw FS'!K36 -> 45238 | H9: ='Raw FS'!L36 -> 53255
B10: ='Raw FS'!B37 -> Trade receivables | D10: ='Raw FS'!H37 -> 9173 | E10: ='Raw FS'!I37 -> 16016 | F10: ='Raw FS'!J37 -> 19187 | G10: ='Raw FS'!K37 -> 18752 | H10: ='Raw FS'!L37 -> 19763
B11: ='Raw FS'!B39 -> Loans n Advances | D11: ='Raw FS'!H39 -> -1268 | E11: ='Raw FS'!I39 -> -817 | F11: ='Raw FS'!J39 -> -911 | G11: ='Raw FS'!K39 -> -1060 | H11: ='Raw FS'!L39 -> -1237
B12: ='Raw FS'!B40 -> Other asset items | D12: ='Raw FS'!H40 -> 72274 | E12: ='Raw FS'!I40 -> 69245 | F12: ='Raw FS'!J40 -> 75019 | G12: ='Raw FS'!K40 -> 77407 | H12: ='Raw FS'!L40 -> 84620
B13: Total Current Assets | D13: =SUM(D9:D12) -> 114244 | E13: =SUM(E9:E12) -> 130180 | F13: =SUM(F9:F12) -> 148655 | G13: =SUM(G9:G12) -> 140337 | H13: =SUM(H9:H12) -> 156401
B15: Current Liabilities
B16: ='Raw FS'!B13 -> Trade Payables | D16: ='Raw FS'!H13 -> 23064 | E16: ='Raw FS'!I13 -> 27251 | F16: ='Raw FS'!J13 -> 40186 | G16: ='Raw FS'!K13 -> 33643 | H16: ='Raw FS'!L13 -> 37490
B17: ='Raw FS'!B14 -> Advance from Customers | D17: ='Raw FS'!H14 -> 1359 | E17: ='Raw FS'!I14 -> 1268 | F17: ='Raw FS'!J14 -> 1953 | G17: ='Raw FS'!K14 -> 1325 | H17: ='Raw FS'!L14 -> 1424
B18: ='Raw FS'!B15 -> Other liability items | D18: ='Raw FS'!H15 -> 130958 | E18: ='Raw FS'!I15 -> 137445 | F18: ='Raw FS'!J15 -> 135807 | G18: ='Raw FS'!K15 -> 134637 | H18: ='Raw FS'!L15 -> 152588
B19: Total Current Liabilities | D19: =SUM(D16:D18) -> 155381 | E19: =SUM(E16:E18) -> 165964 | F19: =SUM(F16:F18) -> 177946 | G19: =SUM(G16:G18) -> 169605 | H19: =SUM(H16:H18) -> 191502
A21: # | B21: Net Working Capital | D21: =D13-D19 -> -41137 | E21: =E13-E19 -> -35784 | F21: =F13-F19 -> -29291 | G21: =G13-G19 -> -29268 | H21: =H13-H19 -> -35101
B23: Non Current Assets
B24: ='Raw FS'!B19 -> Land | D24: ='Raw FS'!H19 -> 6798 | E24: ='Raw FS'!I19 -> 7550 | F24: ='Raw FS'!J19 -> 8582 | G24: ='Raw FS'!K19 -> 8970 | H24: ='Raw FS'!L19 -> 9819
B25: ='Raw FS'!B20 -> Building | D25: ='Raw FS'!H20 -> 14498 | E25: ='Raw FS'!I20 -> 15686 | F25: ='Raw FS'!J20 -> 17552 | G25: ='Raw FS'!K20 -> 18545 | H25: ='Raw FS'!L20 -> 20729
B26: ='Raw FS'!B21 -> Plant Machinery | D26: ='Raw FS'!H21 -> 97348 | E26: ='Raw FS'!I21 -> 103871 | F26: ='Raw FS'!J21 -> 116943 | G26: ='Raw FS'!K21 -> 130419 | H26: ='Raw FS'!L21 -> 166783
B27: ='Raw FS'!B22 -> Equipments | D27: ='Raw FS'!H22 -> 5156 | E27: ='Raw FS'!I22 -> 5727 | F27: ='Raw FS'!J22 -> 6399 | G27: ='Raw FS'!K22 -> 6454 | H27: ='Raw FS'!L22 -> 7594
B28: ='Raw FS'!B23 -> Furniture n fittings | D28: ='Raw FS'!H23 -> 1671 | E28: ='Raw FS'!I23 -> 1705 | F28: ='Raw FS'!J23 -> 1741 | G28: ='Raw FS'!K23 -> 1838 | H28: ='Raw FS'!L23 -> 2105
B29: ='Raw FS'!B24 -> Railway sidings | D29: ='Raw FS'!H24 -> 633 | E29: ='Raw FS'!I24 -> 681 | F29: ='Raw FS'!J24 -> 762 | G29: ='Raw FS'!K24 -> 793 | H29: ='Raw FS'!L24 -> 791
B30: ='Raw FS'!B25 -> Vehicles | D30: ='Raw FS'!H25 -> 3936 | E30: ='Raw FS'!I25 -> 6174 | F30: ='Raw FS'!J25 -> 6935 | G30: ='Raw FS'!K25 -> 7366 | H30: ='Raw FS'!L25 -> 8737
B31: ='Raw FS'!B26 -> Intangible Assets | D31: ='Raw FS'!H26 -> 14597 | E31: ='Raw FS'!I26 -> 23923 | F31: ='Raw FS'!J26 -> 24744 | G31: ='Raw FS'!K26 -> 26702 | H31: ='Raw FS'!L26 -> 27495
B32: ='Raw FS'!B27 -> Other fixed assets | D32: ='Raw FS'!H27 -> 140957 | E32: ='Raw FS'!I27 -> 140299 | F32: ='Raw FS'!J27 -> 144507 | G32: ='Raw FS'!K27 -> 132213 | H32: ='Raw FS'!L27 -> 146442
B33: Gross Block | D33: ='Raw FS'!H28 -> 285595 | E33: ='Raw FS'!I28 -> 305615 | F33: ='Raw FS'!J28 -> 328166 | G33: ='Raw FS'!K28 -> 333300 | H33: ='Raw FS'!L28 -> 390494
B34: Accumulated Depreciation | D34: ='Raw FS'!H29 -> 41702 | E34: ='Raw FS'!I29 -> 61869 | F34: ='Raw FS'!J29 -> 73763 | G34: ='Raw FS'!K29 -> 82436 | H34: ='Raw FS'!L29 -> 91996
A35: # | B35: Net Non Current Assets | D35: =D33-D34 -> 243893 | E35: =E33-E34 -> 243746 | F35: =F33-F34 -> 254403 | G35: =G33-G34 -> 250864 | H35: =H33-H34 -> 298498
A37: # | B37: Invested Capital | D37: =D35+D21 -> 202756 | E37: =E35+E21 -> 207962 | F37: =F35+F21 -> 225112 | G37: =G35+G21 -> 221596 | H37: =H35+H21 -> 263397
B38: EBIT | D38: =('Historical FS'!H28+'Historical FS'!H22) -> 25470.1 | E38: =('Historical FS'!I28+'Historical FS'!I22) -> 23934.97 | F38: =('Historical FS'!J28+'Historical FS'!J22) -> 52990.43 | G38: =('Historical FS'!K28+'Historical FS'!K22) -> 50969.93 | H38: =('Historical FS'!L28+'Historical FS'!L22) -> 74072.69
B40: ROIC | D40: =D38/D37 -> 0.12561946 | E40: =E38/E37 -> 0.115093 | F40: =F38/F37 -> 0.23539585 | G40: =G38/G37 -> 0.23001286 | H40: =H38/H37 -> 0.2812207
B43: Calculation of Reinvestment Rate
B45: Particulars | D45: ='Historical FS'!H3 -> 43921 | E45: ='Historical FS'!I3 -> 44286 | F45: ='Historical FS'!J3 -> 44651 | G45: ='Historical FS'!K3 -> 45016 | H45: ='Historical FS'!L3 -> 45382
B47: Net Capex | D47: =-SUM('Raw FS'!H57:H58) -> 41857 | E47: =-SUM('Raw FS'!I57:I58) -> 32038 | F47: =-SUM('Raw FS'!J57:J58) -> 33090 | G47: =-SUM('Raw FS'!K57:K58) -> 38380 | H47: =-SUM('Raw FS'!L57:L58) -> 37665
B48: Change in Working Capital | E48: =E21-D21 -> 5353 | F48: =F21-E21 -> 6493 | G48: =G21-F21 -> 23 | H48: =H21-G21 -> -5833
B50: EBIT | D50: =D38 -> 25470.1 | E50: =E38 -> 23934.97 | F50: =F38 -> 52990.43 | G50: =G38 -> 50969.93 | H50: =H38 -> 74072.69
B51: Marginal Tax Rate | D51: 0.25 | E51: 0.25 | F51: 0.25 | G51: 0.25 | H51: 0.25
B52: EBIT(1-T) | D52: =D50*(1-D51) -> 19102.575 | E52: =E50*(1-E51) -> 17951.227 | F52: =F50*(1-F51) -> 39742.822 | G52: =G50*(1-G51) -> 38227.448 | H52: =H50*(1-H51) -> 55554.518
B54: Reinvestment | E54: =SUM(E47:E48) -> 37391 | F54: =SUM(F47:F48) -> 39583 | G54: =SUM(G47:G48) -> 38403 | H54: =SUM(H47:H48) -> 31832
B55: Reinvestment Rate | E55: =E54/E52 -> 2.0829216 | F55: =F54/F52 -> 0.99597858 | G55: =G54/G52 -> 1.0045923 | H55: =H54/H52 -> 0.57298671
F57: 4 Year Average | H57: =AVERAGE(E55:H55) -> 1.1641198
F58: 4 Year Median | H58: =MEDIAN(E55:H55) -> 1.0002854
B60: Calculation of Reinvestment Rate
B62: Particulars | D62: ='Historical FS'!H3 -> 43921 | E62: ='Historical FS'!I3 -> 44286 | F62: ='Historical FS'!J3 -> 44651 | G62: ='Historical FS'!K3 -> 45016 | H62: ='Historical FS'!L3 -> 45382
B64: Reinvestment Rate | E64: =E55 -> 2.0829216 | F64: =F55 -> 0.99597858 | G64: =G55 -> 1.0045923 | H64: =H55 -> 0.57298671
B65: ROIC | E65: =E40 -> 0.115093 | F65: =F40 -> 0.23539585 | G65: =G40 -> 0.23001286 | H65: =H40 -> 0.2812207
B67: Intristic Growth | E67: =E65*E64 -> 0.23972969 | F67: =F65*F64 -> 0.23444922 | G67: =G65*G64 -> 0.23106915 | H67: =H65*H64 -> 0.16113573
F69: 4 Year Average | H69: =AVERAGE(E67:H67) -> 0.21659595
F70: 4 Year Median | H70: =MEDIAN(E67:H67) -> 0.23275919

Sheet FCFF
B2: ="Free Cash Flow to the Firm - "&'Profit & Loss'!A1 -> Free Cash Flow to the Firm - OIL & NATURAL GAS CORPN LTD
B4: Calculation of PV of FCFF
B6: Particulars | E6: ='Data Sheet'!K56 -> 45382 | F6: =E6+365 -> 45747 | G6: =F6+365 -> 46112 | H6: =G6+365 -> 46477 | I6: =H6+365 -> 46842 | J6: =I6+365 -> 47207
B8: EBIT | E8: ='Data Sheet'!K32-'Data Sheet'!K26 -> 79174.78 | F8: =E8*(1+$D$17) -> 97603.437 | G8: =F8*(1+$D$17) -> 120321.53 | H8: =G8*(1+$D$17) -> 148327.48 | I8: =H8*(1+$D$17) -> 182852.06 | J8: =I8*(1+$D$17) -> 225412.56
B9: Tax Rate | E9: 0.25 | F9: =E9 -> 0.25 | G9: =F9 -> 0.25 | H9: =G9 -> 0.25 | I9: =H9 -> 0.25 | J9: =I9 -> 0.25
B10: EBIT(1-T) | E10: =E8*(1-E9) -> 59381.085 | F10: =F8*(1-F9) -> 73202.578 | G10: =G8*(1-G9) -> 90241.151 | H10: =H8*(1-H9) -> 111245.61 | I10: =I8*(1-I9) -> 137139.04 | J10: =J8*(1-J9) -> 169059.42
B11: Less: Reinvestmen Rate | E11: ='Intristic Growth'!H57 -> 1.1641198 | F11: =E11+(($J$11-$E$11)/5) -> 1.0574358 | G11: =F11+(($J$11-$E$11)/4) -> 0.92408089 | H11: =G11+(($J$11-$E$11)/4) -> 0.79072594 | I11: =H11+(($J$11-$E$11)/4) -> 0.65737099 | J11: 0.6307
B12: Free Cash Flow to Firm(FCFF) | E12: =E10*(1-E11) -> -9745.6123 | F12: =F10*(1-F11) -> -4204.452 | G12: =G10*(1-G11) -> 6851.0275 | H12: =H10*(1-H11) -> 23280.82 | I12: =I10*(1-I11) -> 46987.815 | J12: =J10*(1-J11) -> 62433.643
B13: Mid Year Convention | F13: 0.5 | G13: =F13+1 -> 1.5 | H13: =G13+1 -> 2.5 | I13: =H13+1 -> 3.5 | J13: =I13+1 -> 4.5
B14: Discounting Factor | F14: =1/(1+$D$19)^F13 -> 0.92757363 | G14: =1/(1+$D$19)^G13 -> 0.79807772 | H14: =1/(1+$D$19)^H13 -> 0.68666036 | I14: =1/(1+$D$19)^I13 -> 0.59079766 | J14: =1/(1+$D$19)^J13 -> 0.50831808
B15: PV of FCFF | F15: =F12*F14 -> -3899.9388 | G15: =G12*G14 -> 5467.6523 | H15: =H12*H14 -> 15986.016 | I15: =I12*I14 -> 27760.291 | J15: =J12*J14 -> 31736.149
B17: Expected Growth | D17: ='Intristic Growth'!H70 -> 0.23275919
B18: Terminal Growth | D18: 0.065
B19: WACC | D19: =WACC!K37 -> 0.16225978
B21: Calculation of Terminal Value | F21: EV Senstivity Analysis
F22: =D33 -> 479303.07 | G22: 0.14 | H22: 0.16225978 | I22: 0.19 | J22: 0.22
B23: FCFF (n+1) | D23: =J12*(1+D17) -> 76965.647 | F23: 0.03 | G23: 432714.08 | H23: 372854.6 | I23: 321569.1 | J23: 282960.85
B24: WACC | D24: =D19 -> 0.16225978 | F24: 0.05 | G24: 511750.5 | H24: 425554.58 | I24: 356500.38 | J24: 307185.64
B25: Terminal Growth Rate | D25: =D18 -> 0.065 | F25: 0.065 | G25: 598690.56 | H25: 479303.07 | I25: 390034.41 | J25: 329456.81
B26: Terminal Value | D26: =D23/(D24-D25) -> 791340.93 | F26: 0.07 | G26: 635950.59 | H26: 501103.08 | I26: 403075.42 | J26: 337870.37
F27: 0.08 | G27: 729100.66 | H27: 552653.54 | I27: 432714.08 | J27: 356500.38
B29: Calculation of Equity Value per Share | F29: Equity Share Price Senstivity Analysis
F30: =D39 -> 314.96718 | G30: 0.14 | H30: 0.16225978 | I30: 0.19 | J30: 0.22
B31: PV of FCFF | D31: =SUM(F15:J15) -> 77050.17 | F31: 0.03 | G31: 277.93384 | H31: 230.35187 | I31: 189.58531 | J31: 158.89583
B32: PV ofTerminal Value | D32: =D26*J14 -> 402252.9 | F32: 0.05 | G32: 340.75946 | H32: 272.2428 | I32: 217.35199 | J32: 178.15198
B33: Enterprise Value | D33: =D32+D31 -> 479303.07 | F33: 0.065 | G33: 409.86764 | H33: 314.96718 | I33: 244.00801 | J33: 195.85521
F34: 0.07 | G34: 439.48543 | H34: 332.29589 | I34: 254.37423 | J34: 202.5431
B35: Add: Cash | D35: ='Data Sheet'!K69 -> 36689.64 | F35: 0.08 | G35: 513.52991 | H35: 373.27306 | I35: 277.93384 | J35: 217.35199
B36: Less: Debt | D36: =SUM('Raw FS'!L7:L8) -> 119755
B37: Value of Equity | D37: =D33+D35-D36 -> 396237.71
B38: No of Shares | D38: ='Data Sheet'!B6 -> 1258.0286
B39: Equity Value per Share | D39: =D37/D38 -> 314.96718
B41: Share Price | D41: ='Data Sheet'!B8 -> 247.35
B42: Discount/Premium | D42: =D41/D39 -> 0.78531993

Sheet Relative Valuation
B2: ="Intrinsic Growth of - "&'Profit & Loss'!A1 -> Intrinsic Growth of - OIL & NATURAL GAS CORPN LTD
B4: Figures in crores | D4: Market Data | J4: Financials | N4: Valuation
B5: Company | C5: Ticker | D5: Share Price | E5: Shares Outstanding | F5: Equity Value | G5: Net Debt | H5: Enterprice value | J5: Revenue | K5: EBITDA | L5: Net Income | N5: EV/Revenue | O5: EV/EBITDA | P5: P/E
B7: ='Comps Data'!C3 -> O N G C | D7: ='Comps Data'!D3 -> 244.55 | E7: ='Comps Data'!E3 -> 1258.03 | F7: =E7*D7 -> 307651.24 | G7: ='Comps Data'!I3 -> 160639.55 | H7: =F7+G7 -> 468290.79 | J7: ='Comps Data'!K3 -> 663262.31 | K7: ='Comps Data'!L3 -> 102289.87 | L7: ='Comps Data'!M3 -> 38328.59 | N7: =$H7/J7 -> 0.70604161 | O7: =$H7/K7 -> 4.5780759 | P7: =F7/L7 -> 8.0266776
B8: ='Comps Data'!C4 -> Oil India | D8: ='Comps Data'!D4 -> 431.1 | E8: ='Comps Data'!E4 -> 162.66 | F8: =E8*D8 -> 70122.726 | G8: ='Comps Data'!I4 -> 23448.07 | H8: =F8+G8 -> 93570.796 | J8: ='Comps Data'!K4 -> 32512.48 | K8: ='Comps Data'!L4 -> 12823.92 | L8: ='Comps Data'!M4 -> 7039.63 | N8: =$H8/J8 -> 2.8779963 | O8: =$H8/K8 -> 7.2965829 | P8: =F8/L8 -> 9.961138
B9: ='Comps Data'!C5 -> Deep Industries | D9: ='Comps Data'!D5 -> 422.5 | E9: ='Comps Data'!E5 -> 6.4 | F9: =E9*D9 -> 2704 | G9: ='Comps Data'!I5 -> 154.11 | H9: =F9+G9 -> 2858.11 | J9: ='Comps Data'!K5 -> 576.13 | K9: ='Comps Data'!L5 -> 263.8 | L9: ='Comps Data'!M5 -> -78.76 | N9: =$H9/J9 -> 4.9608769 | O9: =$H9/K9 -> 10.834382 | P9: =F9/L9 -> -34.332148
B10: ='Comps Data'!C6 -> Hind.Oil Explor. | D10: ='Comps Data'!D6 -> 182.3 | E10: ='Comps Data'!E6 -> 13.22 | F10: =E10*D10 -> 2410.006 | G10: ='Comps Data'!I6 -> 76.63 | H10: =F10+G10 -> 2486.636 | J10: ='Comps Data'!K6 -> 667.09 | K10: ='Comps Data'!L6 -> 266.07 | L10: ='Comps Data'!M6 -> 166.66 | N10: =$H10/J10 -> 3.727587 | O10: =$H10/K10 -> 9.3457962 | P10: =F10/L10 -> 14.460614
B11: ='Comps Data'!C7 -> Asian Energy | D11: ='Comps Data'!D7 -> 313.25 | E11: ='Comps Data'!E7 -> 4.48 | F11: =E11*D11 -> 1403.36 | G11: ='Comps Data'!I7 -> -53.63 | H11: =F11+G11 -> 1349.73 | J11: ='Comps Data'!K7 -> 465.04 | K11: ='Comps Data'!L7 -> 77.71 | L11: ='Comps Data'!M7 -> 42.16 | N11: =$H11/J11 -> 2.9023955 | O11: =$H11/K11 -> 17.368807 | P11: =F11/L11 -> 33.286528
B12: ='Comps Data'!C8 -> Selan Expl. Tech | D12: ='Comps Data'!D8 -> 546.4 | E12: ='Comps Data'!E8 -> 1.52 | F12: =E12*D12 -> 830.528 | G12: ='Comps Data'!I8 -> -19.56 | H12: =F12+G12 -> 810.968 | J12: ='Comps Data'!K8 -> 258.08 | K12: ='Comps Data'!L8 -> 103.41 | L12: ='Comps Data'!M8 -> 73.98 | N12: =$H12/J12 -> 3.1423125 | O12: =$H12/K12 -> 7.842259 | P12: =F12/L12 -> 11.226386
B13: ='Comps Data'!C9 -> Guj.Nat.Resour. | D13: ='Comps Data'!D9 -> 46.94 | E13: ='Comps Data'!E9 -> 12.84 | F13: =E13*D13 -> 602.7096 | G13: ='Comps Data'!I9 -> 49.12 | H13: =F13+G13 -> 651.8296 | J13: ='Comps Data'!K9 -> 25.6 | K13: ='Comps Data'!L9 -> 7.45 | L13: ='Comps Data'!M9 -> -1.73 | N13: =$H13/J13 -> 25.462094 | O13: =$H13/K13 -> 87.493906 | P13: =F13/L13 -> -348.38705
B14: ='Comps Data'!C10 -> Aban Offshore | D14: ='Comps Data'!D10 -> 44.18 | E14: ='Comps Data'!E10 -> 5.84 | F14: =E14*D14 -> 258.0112 | G14: ='Comps Data'!I10 -> 15326.63 | H14: =F14+G14 -> 15584.641 | J14: ='Comps Data'!K10 -> 497.41 | K14: ='Comps Data'!L10 -> 289.48 | L14: ='Comps Data'!M10 -> -969.67 | N14: =$H14/J14 -> 31.33158 | O14: =$H14/K14 -> 53.836677 | P14: =F14/L14 -> -0.26608145
B16: High | N16: =MAX(N7:N14) -> 31.33158 | O16: =MAX(O7:O14) -> 87.493906 | P16: =MAX(P7:P14) -> 33.286528
B17: 75th Percentile | N17: =QUARTILE(N7:N14,3) -> 10.086181 | O17: =QUARTILE(O7:O14,3) -> 26.485775 | P17: =QUARTILE(P7:P14,3) -> 12.034943
B18: Average | N18: =AVERAGE(N7:N14) -> 9.3888604 | O18: =AVERAGE(O7:O14) -> 24.824561 | P18: =AVERAGE(P7:P14) -> -38.252992
B19: Median | N19: =MEDIAN(N7:N14) -> 3.4349497 | O19: =MEDIAN(O7:O14) -> 10.090089 | P19: =MEDIAN(P7:P14) -> 8.9939078
B20: 25th Percentile | N20: =QUARTILE(N7:N14,1) -> 2.8962957 | O20: =QUARTILE(O7:O14,1) -> 7.70584 | P20: =QUARTILE(P7:P14,1) -> -8.7825982
B21: Low | N21: =MIN(N7:N14) -> 0.70604161 | O21: =MIN(O7:O14) -> 4.5780759 | P21: =MIN(P7:P14) -> -348.38705
B23: ONGC Comparable Valuation | N23: EV/Revenue | O23: EV/EBITDA | P23: P/E
B25: Implied Enterprice Value | N25: =N19*J$7 -> 2278272.7 | O25: =O19*K$7 -> 1032113.9 | P25: =P26+P27 -> 505363.36
B26: Net Debt | N26: =G7 -> 160639.55 | O26: =N26 -> 160639.55 | P26: =O26 -> 160639.55
B27: Implied Market Value | N27: =N25-N26 -> 2117633.1 | O27: =O25-O26 -> 871474.36 | P27: =P19*L7 -> 344723.81
B28: Shares Outstanding | N28: =$E$7 -> 1258.03 | O28: =$E$7 -> 1258.03 | P28: =$E$7 -> 1258.03
B29: Implied value per Share | N29: =N27/N28 -> 1683.293 | O29: =O27/O28 -> 692.72939 | P29: =P27/P28 -> 274.01875
B31: Source: Screnner.i, The Valuation School | N31: =IF(N29>$D$7,"Undervalued","Overvalued") -> Undervalued | O31: =IF(O29>$D$7,"Undervalued","Overvalued") -> Undervalued | P31: =IF(P29>$D$7,"Undervalued","Overvalued") -> Undervalued

Sheet Football Field Analysis
B2: Football Field Analysis
C5: Open low | D5: Low | E5: Open High | F5: High
B6: Comps | C6: =D6 -> 274.01875 | D6: ='Relative Valuation'!P29 -> 274.01875 | E6: =F6 -> 1683.293 | F6: ='Relative Valuation'!N29 -> 1683.293
B7: DCF Bear | C7: =D7 -> 158.89583 | D7: =FCFF!J31 -> 158.89583 | E7: =F7 -> 217.35199 | F7: =FCFF!J35 -> 217.35199
B8: DCF Base | C8: =D8 -> 230.35187 | D8: =FCFF!H31 -> 230.35187 | E8: =F8 -> 373.27306 | F8: =FCFF!H35 -> 373.27306
B9: DCF Bull | C9: =D9 -> 277.93384 | D9: =FCFF!G31 -> 277.93384 | E9: =F9 -> 513.52991 | F9: =FCFF!G35 -> 513.52991
B10: 52W H/L | C10: =D10 -> 205 | D10: 205 | E10: =F10 -> 345 | F10: 345

Sheet VaR
B3: Date | C3: Adjusted CLOSE | D3: Return | E3: Sorted Return | G3: Calaculation of VaR
B4: 45440 | C4: 277.65 | D4: =(C4-C5)/C5 -> 0.012212906 | E4: 0.20228523
B5: 45441 | C5: 274.3 | D5: =(C5-C6)/C6 -> 0.009012323 | E5: 0.076545286 | G5: Mean | K5: =AVERAGE(E4:E251) -> 0.00084875814
B6: 45442 | C6: 271.85 | D6: =(C6-C7)/C7 -> 0.019310086 | E6: 0.063980661 | G6: Std | K6: =_xlfn.STDEV.S(E4:E251) -> 0.024028043
B7: 45443 | C7: 266.7 | D7: =(C7-C8)/C8 -> 0.0088897295 | E7: 0.043460729 | G7: Min | K7: =MIN(E4:E251) -> -0.069887572
B8: 45446 | C8: 264.35 | D8: =(C8-C9)/C9 -> -0.069517775 | E8: 0.037697482 | G8: Max | K8: =MAX(E4:E251) -> 0.20228523
B9: 45447 | C9: 284.1 | D9: =(C9-C10)/C10 -> 0.20228523 | E9: 0.036102348 | G9: Current Market Price | K9: 243
B10: 45448 | C10: 236.3 | D10: =(C10-C11)/C11 -> -0.045252525 | E10: 0.035292336
B11: 45449 | C11: 247.5 | D11: =(C11-C12)/C12 -> -0.01902497 | E11: 0.034337349
B12: 45450 | C12: 252.3 | D12: =(C12-C13)/C13 -> -0.031105991 | E12: 0.033121445 | G12: Percentile | H12: Confidence | I12: VaR | J12: Stock Price | K12: VaR(INR)
B13: 45453 | C13: 260.4 | D13: =(C13-C14)/C14 -> 0.0048234613 | E13: 0.030967399 | G13: 0.05 | H13: =100%-G13 -> 0.95 | I13: =_xlfn.PERCENTILE.INC(E4:E251,G13) -> -0.036162318 | J13: =$K$9*(1-I13) -> 251.78744 | K13: =$K$9-J13 -> -8.7874432
B14: 45454 | C14: 259.15 | D14: =(C14-C15)/C15 -> -0.052641199 | E14: 0.030126176 | G14: 0.01 | H14: =100%-G14 -> 0.99 | I14: =_xlfn.PERCENTILE.INC(E5:E252,G14) -> -0.051205034 | J14: =$K$9*(1-I14) -> 255.44282 | K14: =$K$9-J14 -> -12.442823
B15: 45455 | C15: 273.55 | D15: =(C15-C16)/C16 -> -0.0070780399 | E15: 0.029128164 | G15: 0.005 | H15: =100%-G15 -> 0.995 | I15: =_xlfn.PERCENTILE.INC(E6:E253,G15) -> -0.065720546 | J15: =$K$9*(1-I15) -> 258.97009 | K15: =$K$9-J15 -> -15.970093
B16: 45456 | C16: 275.5 | D16: =(C16-C17)/C17 -> -0.0037967818 | E16: 0.029006496 | G16: 0.1 | H16: =100%-G16 -> 0.9 | I16: =_xlfn.PERCENTILE.INC(E7:E254,G16) -> -0.027292918 | J16: =$K$9*(1-I16) -> 249.63218 | K16: =$K$9-J16 -> -6.632179
B17: 45457 | C17: 276.55 | D17: =(C17-C18)/C18 -> 0.0041757444 | E17: 0.028506628
B18: 45461 | C18: 275.4 | D18: =(C18-C19)/C19 -> -0.0014503263 | E18: 0.028065866
B19: 45462 | C19: 275.8 | D19: =(C19-C20)/C20 -> 0.015650893 | E19: 0.026603423
B20: 45463 | C20: 271.55 | D20: =(C20-C21)/C21 -> -0.0011035498 | E20: 0.025527192
B21: 45464 | C21: 271.85 | D21: =(C21-C22)/C22 -> 0.0081587243 | E21: 0.025496082
B22: 45467 | C22: 269.65 | D22: =(C22-C23)/C23 -> -0.00092626899 | E22: 0.02480916
B23: 45468 | C23: 269.9 | D23: =(C23-C24)/C24 -> 0.010861423 | E23: 0.0243121
B24: 45469 | C24: 267 | D24: =(C24-C25)/C25 -> -0.0028011204 | E24: 0.024222704
B25: 45470 | C25: 267.75 | D25: =(C25-C26)/C26 -> 0.00093457944 | E25: 0.024158579
B26: 45471 | C26: 267.5 | D26: =(C26-C27)/C27 -> -0.024434719 | E26: 0.023682526
B27: 45474 | C27: 274.2 | D27: =(C27-C28)/C28 -> 0.0045795933 | E27: 0.023617248
B28: 45475 | C28: 272.95 | D28: =(C28-C29)/C29 -> -0.0069128616 | E28: 0.023368493
... B251: 45804 | C251: 245.94 | D251: =(C251-C252)/C252 -> #DIV/0! | E251: -0.069887572

Sheet Monte Carlo Simulation
B3: Date | C3: Adjusted CLOSE | D3: Return | E3: Sorted Return | F3: Replication | G3: Simulated Returns | I3: Calaculation of VaR
B4: 45440 | C4: 277.65 | D4: =(C4-C5)/C5 -> 0.012212906 | E4: 0.20228523 | F4: 1 | G4: =_xlfn.NORM.INV(RAND(),$M$7,$M$8) -> -0.029919122
B5: 45441 | C5: 274.3 | D5: =(C5-C6)/C6 -> 0.009012323 | E5: 0.076545286 | F5: 2 | G5: =_xlfn.NORM.INV(RAND(),$M$7,$M$8) -> -0.01894456
B6: 45442 | C6: 271.85 | D6: =(C6-C7)/C7 -> 0.019310086 | E6: 0.063980661 | F6: 3 | G6: =_xlfn.NORM.INV(RAND(),$M$7,$M$8) -> -0.0032091248 | I6: Historical Approch
B7: 45443 | C7: 266.7 | D7: =(C7-C8)/C8 -> 0.0088897295 | E7: 0.043460729 | F7: 4 | G7: =_xlfn.NORM.INV(RAND(),$M$7,$M$8) -> -0.017281319 | I7: Mean | M7: =AVERAGE(E4:E251) -> 0.00084875814
B8: 45446 | C8: 264.35 | D8: =(C8-C9)/C9 -> -0.069517775 | E8: 0.037697482 | F8: 5 | G8: =_xlfn.NORM.INV(RAND(),$M$7,$M$8) -> -0.015204029 | I8: Std | M8: =_xlfn.STDEV.S(E4:E251) -> 0.024028043
B9: 45447 | C9: 284.1 | D9: =(C9-C10)/C10 -> 0.20228523 | E9: 0.036102348 | F9: 6 | G9: =_xlfn.NORM.INV(RAND(),$M$7,$M$8) -> -0.043901926 | I9: Min | M9: =MIN(E4:E251) -> -0.069887572
B10: 45448 | C10: 236.3 | D10: =(C10-C11)/C11 -> -0.045252525 | E10: 0.035292336 | F10: 7 | G10: =_xlfn.NORM.INV(RAND(),$M$7,$M$8) -> 0.012577016 | I10: Max | M10: =MAX(E4:E251) -> 0.20228523
B11: 45449 | C11: 247.5 | D11: =(C11-C12)/C12 -> -0.01902497 | E11: 0.034337349 | F11: 8 | G11: =_xlfn.NORM.INV(RAND(),$M$7,$M$8) -> 0.0082705311 | I11: Current Market Price | M11: 243
B12: 45450 | C12: 252.3 | D12: =(C12-C13)/C13 -> -0.031105991 | E12: 0.033121445 | F12: 9 | G12: =_xlfn.NORM.INV(RAND(),$M$7,$M$8) -> 0.0032275652
B13: 45453 | C13: 260.4 | D13: =(C13-C14)/C14 -> 0.0048234613 | E13: 0.030967399 | F13: 10 | G13: =_xlfn.NORM.INV(RAND(),$M$7,$M$8) -> 0.03148893 | I13: Monte Carlo Simulation
B14: 45454 | C14: 259.15 | D14: =(C14-C15)/C15 -> -0.052641199 | E14: 0.030126176 | F14: 11 | G14: =_xlfn.NORM.INV(RAND(),$M$7,$M$8) -> 0.015533546 | I14: Mean | M14: =G4:G10003 -> 0.015533546
B15: 45455 | C15: 273.55 | D15: =(C15-C16)/C16 -> -0.0070780399 | E15: 0.029128164 | F15: 12 | G15: =_xlfn.NORM.INV(RAND(),$M$7,$M$8) -> 0.058673772 | I15: Std | M15: =_xlfn.STDEV.S(G4:G10003) -> 0.023875982
B16: 45456 | C16: 275.5 | D16: =(C16-C17)/C17 -> -0.0037967818 | E16: 0.029006496 | F16: 13 | G16: =_xlfn.NORM.INV(RAND(),$M$7,$M$8) -> -0.01736265 | I16: Min | M16: =MIN(G4:G10003) -> -0.084481689
B17: 45457 | C17: 276.55 | D17: =(C17-C18)/C18 -> 0.0041757444 | E17: 0.028506628 | F17: 14 | G17: =_xlfn.NORM.INV(RAND(),$M$7,$M$8) -> -0.013515717 | I17: Max | M17: =MAX(G4:G10003) -> 0.094639143
B18: 45461 | C18: 275.4 | D18: =(C18-C19)/C19 -> -0.0014503263 | E18: 0.028065866 | F18: 15 | G18: =_xlfn.NORM.INV(RAND(),$M$7,$M$8) -> -0.020985872 | I18: Current Market Price | M18: 243
B19: 45462 | C19: 275.8 | D19: =(C19-C20)/C20 -> 0.015650893 | E19: 0.026603423 | F19: 16 | G19: =_xlfn.NORM.INV(RAND(),$M$7,$M$8) -> 0.0028485682
B20: 45463 | C20: 271.55 | D20: =(C20-C21)/C21 -> -0.0011035498 | E20: 0.025527192 | F20: 17 | G20: =_xlfn.NORM.INV(RAND(),$M$7,$M$8) -> -0.014458782 | I20: Percentile | J20: Confidence | K20: VaR | L20: Stock Price | M20: VaR(INR)
B21: 45464 | C21: 271.85 | D21: =(C21-C22)/C22 -> 0.0081587243 | E21: 0.025496082 | F21: 18 | G21: =_xlfn.NORM.INV(RAND(),$M$7,$M$8) -> 0.019924931 | I21: 0.05 | J21: =100%-I21 -> 0.95 | K21: =_xlfn.PERCENTILE.INC($G$4:$G$10003,I21) -> -0.037661992 | L21: =$M$11*(1-K21) -> 252.15186 | M21: =$M$11-L21 -> -9.1518641
B22: 45467 | C22: 269.65 | D22: =(C22-C23)/C23 -> -0.00092626899 | E22: 0.02480916 | F22: 19 | G22: =_xlfn.NORM.INV(RAND(),$M$7,$M$8) -> -0.011650491 | I22: 0.01 | J22: =100%-I22 -> 0.99 | K22: =_xlfn.PERCENTILE.INC($G$4:$G$10003,I22) -> -0.053688978 | L22: =$M$11*(1-K22) -> 256.04642 | M22: =$M$11-L22 -> -13.046422
B23: 45468 | C23: 269.9 | D23: =(C23-C24)/C24 -> 0.010861423 | E23: 0.0243121 | F23: 20 | G23: =_xlfn.NORM.INV(RAND(),$M$7,$M$8) -> -0.033158305 | I23: 0.005 | J23: =100%-I23 -> 0.995 | K23: =_xlfn.PERCENTILE.INC($G$4:$G$10003,I23) -> -0.059757911 | L23: =$M$11*(1-K23) -> 257.52117 | M23: =$M$11-L23 -> -14.521172
B24: 45469 | C24: 267 | D24: =(C24-C25)/C25 -> -0.0028011204 | E24: 0.024222704 | F24: 21 | G24: =_xlfn.NORM.INV(RAND(),$M$7,$M$8) -> -0.019118865 | I24: 0.1 | J24: =100%-I24 -> 0.9 | K24: =_xlfn.PERCENTILE.INC($G$4:$G$10003,I24) -> -0.029595783 | L24: =$M$11*(1-K24) -> 250.19178 | M24: =$M$11-L24 -> -7.1917753
B25: 45470 | C25: 267.75 | D25: =(C25-C26)/C26 -> 0.00093457944 | E25: 0.024158579 | F25: 22 | G25: =_xlfn.NORM.INV(RAND(),$M$7,$M$8) -> 0.054567867
B26: 45471 | C26: 267.5 | D26: =(C26-C27)/C27 -> -0.024434719 | E26: 0.023682526 | F26: 23 | G26: =_xlfn.NORM.INV(RAND(),$M$7,$M$8) -> -0.0017692923
B27: 45474 | C27: 274.2 | D27: =(C27-C28)/C28 -> 0.0045795933 | E27: 0.023617248 | F27: 24 | G27: =_xlfn.NORM.INV(RAND(),$M$7,$M$8) -> -0.024679008
B28: 45475 | C28: 272.95 | D28: =(C28-C29)/C29 -> -0.0069128616 | E28: 0.023368493 | F28: 25 | G28: =_xlfn.NORM.INV(RAND(),$M$7,$M$8) -> -0.010758197
B29: 45476 | C29: 274.85 | D29: =(C29-C30)/C30 -> 0.00054605024 | E29: 0.022848712 | F29: 26 | G29: =_xlfn.NORM.INV(RAND(),$M$7,$M$8) -> 0.021312951
B30: 45477 | C30: 274.7 | D30: =(C30-C31)/C31 -> -0.0084822234 | E30: 0.021992993 | F30: 27 | G30: =_xlfn.NORM.INV(RAND(),$M$7,$M$8) -> -0.0013730038
B31: 45478 | C31: 277.05 | D31: =(C31-C32)/C32 -> -0.038688411 | E31: 0.021471794 | F31: 28 | G31: =_xlfn.NORM.INV(RAND(),$M$7,$M$8) -> 0.0075367579
B32: 45481 | C32: 288.2 | D32: =(C32-C33)/C33 -> -0.036603711 | E32: 0.021418021 | F32: 29 | G32: =_xlfn.NORM.INV(RAND(),$M$7,$M$8) -> -0.037661932
B33: 45482 | C33: 299.15 | D33: =(C33-C34)/C34 -> 0.0057152463 | E33: 0.021267009 | F33: 30 | G33: =_xlfn.NORM.INV(RAND(),$M$7,$M$8) -> 0.01506851
B34: 45483 | C34: 297.45 | D34: =(C34-C35)/C35 -> -0.0023478115 | E34: 0.021168232 | F34: 31 | G34: =_xlfn.NORM.INV(RAND(),$M$7,$M$8) -> 0.050630661
B35: 45484 | C35: 298.15 | D35: =(C35-C36)/C36 -> -0.021657096 | E35: 0.021116928 | F35: 32 | G35: =_xlfn.NORM.INV(RAND(),$M$7,$M$8) -> 0.019199263
B36: 45485 | C36: 304.75 | D36: =(C36-C37)/C37 -> -0.0076522305 | E36: 0.020169278 | F36: 33 | G36: =_xlfn.NORM.INV(RAND(),$M$7,$M$8) -> 0.01678106
... B251: 45804 | C251: 245.94 | D251: =(C251-C252)/C252 -> #DIV/0! | E251: -0.069887572 | F251: 248 | G251: =_xlfn.NORM.INV(RAND(),$M$7,$M$8) -> -0.048207427
F252: 249 | G252: =_xlfn.NORM.INV(RAND(),$M$7,$M$8) -> 0.0059580549
F253: 250 | G253: =_xlfn.NORM.INV(RAND(),$M$7,$M$8) -> -0.013391698
F254: 251 | G254: =_xlfn.NORM.INV(RAND(),$M$7,$M$8) -> 0.01942222
F255: 252 | G255: =_xlfn.NORM.INV(RAND(),$M$7,$M$8) -> -0.010473185
F256: 253 | G256: =_xlfn.NORM.INV(RAND(),$M$7,$M$8) -> -0.0094541907
F257: 254 | G257: =_xlfn.NORM.INV(RAND(),$M$7,$M$8) -> 0.015640229
F258: 255 | G258: =_xlfn.NORM.INV(RAND(),$M$7,$M$8) -> -0.0447154
F259: 256 | G259: =_xlfn.NORM.INV(RAND(),$M$7,$M$8) -> 0.010461451
F260: 257 | G260: =_xlfn.NORM.INV(RAND(),$M$7,$M$8) -> -0.0090448387
F261: 258 | G261: =_xlfn.NORM.INV(RAND(),$M$7,$M$8) -> 0.030075284
F262: 259 | G262: =_xlfn.NORM.INV(RAND(),$M$7,$M$8) -> 0.010591489
F263: 260 | G263: =_xlfn.NORM.INV(RAND(),$M$7,$M$8) -> 0.0058409828
... F10003: 10000 | G10003: =_xlfn.NORM.INV(RAND(),$M$7,$M$8) -> 0.04038174

Sheet Data Sheet
A1: COMPANY NAME | B1: OIL & NATURAL GAS CORPN LTD | E1: =IF(B2<>B3, "A NEW VERSION OF THE WORKSHEET IS AVAILABLE", "")
A2: LATEST VERSION | B2: 2.1 | E2: PLEASE DO NOT MAKE ANY CHANGES TO THIS SHEET
A3: CURRENT VERSION | B3: 2.1
D4: =TRANSPOSE('Data Sheet'!B17:K17) -> 282506.11
A5: META
A6: Number of shares | B6: =IF(B9>0, B9/B8, 0) -> 1258.0286
A7: Face Value | B7: 5
A8: Current Price | B8: 247.35
A9: Market Capitalization | B9: 311173.37
A15: PROFIT & LOSS
A16: Report Date | B16: 42094 | C16: 42460 | D16: 42825 | E16: 43190 | F16: 43555 | G16: 43921 | H16: 44286 | I16: 44651 | J16: 45016 | K16: 45382
A17: Sales | B17: 160922.64 | C17: 124035.71 | D17: 282506.11 | E17: 322705.76 | F17: 421623.93 | G17: 396727.91 | H17: 303848.91 | I17: 491246.24 | J17: 632291.18 | K17: 591396.26
A18: Raw Material Cost | B18: 61912.64 | C18: 36666.93 | D18: 175376.73 | E18: 202298.51 | F18: 275523.61 | G18: 269975.37 | H18: 205913.12 | I18: 225616.93 | J18: 266120.04 | K18: 230469.53
A19: Change in Inventory | B19: -1722.92 | C19: -756.02 | D19: 4784.69 | E19: 8.17 | F19: 3095.62 | G19: -1145.56 | H19: 10047.09 | I19: 2303.07 | J19: -2566.08 | K19: 4433.93
A20: Power and Fuel | B20: 876.3 | C20: 1182.38 | D20: 1957.93 | E20: 2177.5 | F20: 2139.73 | G20: 2078.92 | H20: 1980.44 | I20: 2239.16 | J20: 2174.44 | K20: 3018.32
A21: Other Mfr. Exp | B21: 8171.9 | C21: 9085.95 | D21: 16260.06 | E21: 18372.26 | F21: 19178.34 | G21: 20949.65 | H21: 19726.55 | I21: 136419.7 | J21: 222102.21 | K21: 209079.88
A22: Employee Cost | B22: 9361.34 | C22: 9230.17 | D22: 15128.16 | E22: 14970.72 | F22: 15850.5 | G22: 15531.26 | H22: 14135.12 | I22: 15235.74 | J22: 14898.79 | K22: 15281.06
A23: Selling and admin | B23: 41281.42 | C23: 35735.31 | D23: 36378.9 | E23: 34331.58 | F23: 39621.44 | G23: 29357.66 | H23: 23004.08 | I23: 36347.61 | J23: 44365.47 | K23: 38145.51
A24: Other Expenses | B24: -4716.2 | C24: -7755.68 | D24: -10614.65 | E24: -6325.7 | F24: -2413.06 | G24: 5584.51 | H24: -336.75 | I24: -2183.42 | J24: 4537.16 | K24: -2999.55
A25: Other Income | B25: 5954.76 | C25: 1067.26 | D25: 12724.18 | E25: 10429.39 | F25: 9567.1 | G25: 981.69 | H25: 11270.51 | I25: 6796.72 | J25: -29.82 | K25: 12981.54
A26: Depreciation | B26: 18032.97 | C26: 16384.06 | D26: 20219.2 | E26: 23111.91 | F26: 23703.7 | G26: 26634.88 | H26: 25538.47 | I26: 26883.16 | J26: 24557.06 | K26: 28762.75
A27: Interest | B27: 2863.75 | C27: 3765.58 | D27: 3591.11 | E27: 4999.04 | F27: 5836.73 | G27: 7489.34 | H27: 5079.03 | I27: 5696.04 | J27: 7889.36 | K27: 10194.17
... A31: Dividend Amount | B31: 8127.74 | C31: 7272.19 | D31: 9689.11 | E31: 8469.95 | F31: 8806.21 | G31: 6290.15 | H31: 4528.9 | I31: 13209.29 | J31: 14152.82 | K31: 15410.84
A32: EBITDA | B32: =B30+B26+B27+B29 -> 48927.65 | C32: =C30+C26+C27+C29 -> 39975.55 | D32: =D30+D26+D27+D29 -> 60777.98 | E32: =E30+E26+E27+E29 -> 63356.4 | F32: =F30+F26+F27+F29 -> 80994.12 | G32: =G30+G26+G27+G29 -> 52434.01 | H32: =H30+H26+H27+H29 -> 55688.1 | I32: =I30+I26+I27+I29 -> 82898.35 | ... K32: =K30+K26+K27+K29 -> 107937.53
A40: Quarters
A41: Report Date | B41: 44834 | C41: 44926 | D41: 45016 | E41: 45107 | F41: 45199 | G41: 45291 | H41: 45382 | I41: 45473 | J41: 45565 | K41: 45657
A42: Sales | B42: 168656.12 | C42: 169212.63 | D42: 164066.72 | E42: 163823.59 | F42: 147613.68 | G42: 167356.63 | H42: 166770.63 | I42: 168024.8 | J42: 158329.1 | K42: 166096.68
A43: Expenses | B43: 155310.59 | C43: 147345.52 | D43: 143527.29 | E43: 133028.63 | F43: 119533.64 | G43: 146996.46 | H43: 143545.42 | I43: 146398.25 | J43: 137834.41 | K43: 141818.62
A44: Other Income | B44: 2314.59 | C44: 2807.3 | D44: -4786.26 | E44: 3069.28 | F44: 3672.87 | G44: 4299.03 | H44: 2548.87 | I44: 3615.38 | J44: 4163.42 | K44: 2411.09
A45: Depreciation | B45: 4442.76 | C45: 6784.01 | D45: 6743.59 | E45: 7078.28 | F45: 7078.57 | G45: 7494.27 | H45: 7862.89 | I45: 8456.43 | J45: 8209.01 | K45: 9497.22
A46: Interest | B46: 1992.94 | C46: 2188.43 | D46: 2068.11 | E46: 2363.94 | F46: 3243.32 | G46: 3203.18 | H46: 2682.77 | I46: 3615.9 | J46: 3748.99 | K46: 3669.74
A47: Profit before tax | B47: 9224.42 | C47: 15701.97 | D47: 6941.47 | E47: 24422.02 | F47: 21431.02 | G47: 13961.75 | H47: 15228.42 | I47: 13169.6 | J47: 12700.11 | K47: 13522.19
A48: Tax | B48: 2394.26 | C48: 4036.73 | D48: 463.24 | E48: 6528.54 | F48: 5259.72 | G48: 3450.52 | H48: 3701.89 | I48: 3359.42 | J48: 2821.67 | K48: 3738.55
A49: Net profit | B49: 8299.37 | C49: 11488.99 | D49: 4492.25 | E49: 14644.43 | F49: 13703.38 | G49: 10703.17 | H49: 10107.36 | I49: 10008.6 | J49: 10272.5 | K49: 8621.69
A50: Operating Profit | B50: 13345.53 | C50: 21867.11 | D50: 20539.43 | E50: 30794.96 | F50: 28080.04 | G50: 20360.17 | H50: 23225.21 | I50: 21626.55 | J50: 20494.69 | K50: 24278.06
A55: BALANCE SHEET
A56: Report Date | B56: 42094 | C56: 42460 | D56: 42825 | E56: 43190 | F56: 43555 | G56: 43921 | H56: 44286 | I56: 44651 | J56: 45016 | K56: 45382
A57: Equity Share Capital | B57: 4277.76 | C57: 4277.76 | D57: 6416.63 | E57: 6416.63 | F57: 6290.15 | G57: 6290.15 | H57: 6290.14 | I57: 6290.14 | J57: 6290.14 | K57: 6290.14
A58: Reserves | B58: 176176.64 | C58: 193535.88 | D58: 187968.59 | E58: 197602.3 | F58: 210644.5 | G58: 198814.45 | H58: 214690.85 | I58: 253212.77 | J58: 274357.16 | K58: 330780.09
A59: Borrowings | B59: 53944.47 | C59: 45500.17 | D59: 80029.27 | E59: 106549.94 | F59: 107741.69 | G59: 129472.52 | H59: 133186.92 | I59: 121985.86 | J59: 142254.81 | K59: 153180.53
A60: Other Liabilities | B60: 103447.69 | C60: 98458.57 | D60: 170110.83 | E60: 148663.53 | F60: 167666.95 | G60: 173786.92 | H60: 187579.74 | I60: 201770.75 | J60: 190212.41 | K60: 219523.17
A61: Total | B61: 337846.56 | C61: 341772.38 | D61: 444525.32 | E61: 459232.4 | F61: 492343.29 | G61: 508364.04 | H61: 541747.65 | I61: 583259.52 | J61: 613114.52 | K61: 709773.93
A62: Net Block | B62: 179932.96 | C62: 166276.73 | D62: 211125.43 | E62: 226057.68 | F62: 230390.7 | G62: 243891.96 | H62: 243746.36 | I62: 254402.17 | J62: 250819.44 | K62: 298454.36
A63: Capital Work in Progress | B63: 63393.37 | C63: 57668.48 | D63: 59042.48 | E63: 61511.87 | F63: 69056.44 | G63: 83832.4 | H63: 100308.82 | I63: 106719.23 | J63: 113944.61 | K63: 116021.68
A64: Investments | B64: 4749.14 | C64: 33386.85 | D64: 70745.67 | E64: 67334.61 | F64: 66908.92 | G64: 56755.18 | H64: 60320.36 | I64: 66642.14 | J64: 78872.61 | K64: 102207.2
A65: Other Assets | B65: 89771.09 | C65: 84440.32 | D65: 103611.74 | E65: 104328.24 | F65: 125987.23 | G65: 123884.5 | H65: 137372.11 | I65: 155495.98 | J65: 169477.86 | K65: 193090.69
A66: Total | B66: 337846.56 | C66: 341772.38 | D66: 444525.32 | E66: 459232.4 | F66: 492343.29 | G66: 508364.04 | H66: 541747.65 | I66: 583259.52 | J66: 613114.52 | K66: 709773.93
A67: Receivables | B67: 18815.82 | C67: 8331.71 | D67: 12547.12 | E67: 13899.17 | F67: 15396.46 | G67: 9173.41 | H67: 16015.83 | I67: 19187.28 | J67: 18751.58 | K67: 19762.95
... A70: No. of Equity Shares | B70: 8555520120 | C70: 8555520120 | D70: 12833265180 | E70: 12833265180 | F70: 12580309206 | G70: 12580309206 | H70: 12580279206 | I70: 12580279206 | J70: 12580279206 | K70: 12580279206
A71: New Bonus Shares | D71: 4277745060
A72: Face value | B72: 5 | C72: 5 | D72: 5 | E72: 5 | F72: 5 | G72: 5 | H72: 5 | I72: 5 | J72: 5 | K72: 5
A74: Other Assets | B74: =B65-SUM(B67:B69) -> 43503.49 | C74: =C65-SUM(C67:C69) -> 40657.6 | D74: =D65-SUM(D67:D69) -> 47296.6 | E74: =E65-SUM(E67:E69) -> 54112.66 | F74: =F65-SUM(F67:F69) -> 69821.7 | G74: =G65-SUM(G67:G69) -> 71005.73 | H74: =H65-SUM(H67:H69) -> 68428.17 | I74: =I65-SUM(I67:I69) -> 74107.49 | ... K74: =K65-SUM(K67:K69) -> 83382.86
A76: Total Assets | B76: =B61 -> 337846.56 | C76: =C61 -> 341772.38 | D76: =D61 -> 444525.32 | E76: =E61 -> 459232.4 | F76: =F61 -> 492343.29 | G76: =G61 -> 508364.04 | H76: =H61 -> 541747.65 | I76: =I61 -> 583259.52 | ... K76: =K61 -> 709773.93
A80: CASH FLOW:
A81: Report Date | B81: 42094 | C81: 42460 | D81: 42825 | E81: 43190 | F81: 43555 | G81: 43921 | H81: 44286 | I81: 44651 | J81: 45016 | K81: 45382
A82: Cash from Operating Activity | B82: 33950.42 | C82: 46292.49 | D82: 45780.48 | E82: 56792.1 | F82: 61457.6 | G82: 70592.98 | H82: 47185.19 | I82: 78248.25 | J82: 86062.1 | K82: 99262.69
A83: Cash from Investing Activity | B83: -30058.33 | C83: -38255.87 | D83: -43814.55 | E83: -66798.14 | F83: -37131.63 | G83: -53159.05 | H83: -39141.15 | I83: -41197.15 | J83: -74689.86 | K83: -57203.42
A84: Cash from Financing Activity | B84: -10640.78 | C84: -8972 | D84: -1867.05 | E84: 9909.36 | F84: -23324.5 | G84: -16726.36 | H84: -8239.48 | I84: -35790.02 | J84: -12876.23 | K84: -45650.29
A85: Net Cash Flow | B85: -6748.68 | C85: -935.38 | D85: 98.87 | E85: -96.69 | F85: 1001.47 | G85: 707.57 | H85: -195.44 | I85: 1261.09 | J85: -1503.98 | K85: -3591.02
A90: PRICE: | B90: 204.23 | C90: 142.73 | D90: 185 | E90: 177.8 | F90: 159.75 | G90: 68.3 | H90: 102.15 | I90: 163.9 | J90: 151.05 | K90: 268.05
A92: DERIVED:
A93: Adjusted Equity Shares in Cr | B93: 1283.32 | C93: 1283.32 | D93: 1283.32 | E93: 1283.32 | F93: 1258.03 | G93: 1258.03 | H93: 1258.03 | I93: 1258.03 | J93: 1258.03 | K93: 1258.03

Sheet Dupont Analysis
B2: ='Data Sheet'!B1 -> OIL & NATURAL GAS CORPN LTD
B3: (NSE: ONGC | BSE Code: 500312)
B4: INR 243
B5: 52 weeks (High INR - 345 & Low - 205)
B7: About the Company
B8: The Oil and Natural Gas Corporation Limited (ONGC) is an Indian central public sector undertaking which is the largest government-owned oil and gas explorer and producer in the country. It accounts for around 70 percent of India's domestic production of crude oil and around 84 percent of natural gas. Headquartered in Delhi, ONGC is under the ownership of the Government of India and administration of Ministry of Petroleum and Natural Gas. It was founded on 14 August 1956 by the Government of India. In November 2010, the Government of India conferred the Maharatna status to ONGC.
B15: Financial Summary
B39: Return on Equity (ROE)
C40: ='Historical FS'!F3 -> 43190 | D40: ='Historical FS'!G3 -> 43555 | E40: ='Historical FS'!H3 -> 43921 | F40: ='Historical FS'!I3 -> 44286 | G40: ='Historical FS'!J3 -> 44651 | H40: ='Historical FS'!K3 -> 45016 | I40: ='Historical FS'!L3 -> 45382
B41: Net Profit | C41: ='Data Sheet'!E30 -> 22105.93 | D41: ='Data Sheet'!F30 -> 30546.04 | E41: ='Data Sheet'!G30 -> 10803.6 | F41: ='Data Sheet'!H30 -> 16304.4 | G41: ='Data Sheet'!I30 -> 45522.11 | H41: ='Data Sheet'!J30 -> 35440.48 | I41: ='Data Sheet'!K30 -> 49221.38
B42: Average Shareholder Equity | C42: =(('Data Sheet'!E57+'Data Sheet'!E58)+('Data Sheet'!D57+'Data Sheet'!D58))/2 -> 199202.08 | D42: =(('Data Sheet'!F57+'Data Sheet'!F58)+('Data Sheet'!E57+'Data Sheet'!E58))/2 -> 210476.79 | E42: =(('Data Sheet'!G57+'Data Sheet'!G58)+('Data Sheet'!F57+'Data Sheet'!F58))/2 -> 211019.62 | F42: =(('Data Sheet'!H57+'Data Sheet'!H58)+('Data Sheet'!G57+'Data Sheet'!G58))/2 -> 213042.8 | G42: =(('Data Sheet'!I57+'Data Sheet'!I58)+('Data Sheet'!H57+'Data Sheet'!H58))/2 -> 240241.95 | H42: =(('Data Sheet'!J57+'Data Sheet'!J58)+('Data Sheet'!I57+'Data Sheet'!I58))/2 -> 270075.1 | I42: =(('Data Sheet'!K57+'Data Sheet'!K58)+('Data Sheet'!J57+'Data Sheet'!J58))/2 -> 308858.77
B43: Return on Equity (ROE) | C43: =C41/C42 -> 0.11097239 | D43: =D41/D42 -> 0.14512783 | E43: =E41/E42 -> 0.051197134 | F43: =F41/F42 -> 0.076531103 | G43: =G41/G42 -> 0.18948443 | H43: =H41/H42 -> 0.13122453 | I43: =I41/I42 -> 0.15936533
B45: ROE - Dupont Equation
C46: =C40 -> 43190 | D46: =D40 -> 43555 | E46: =E40 -> 43921 | F46: =F40 -> 44286 | G46: =G40 -> 44651 | H46: =H40 -> 45016 | I46: =I40 -> 45382
B47: Net Profit | C47: =C41 -> 22105.93 | D47: =D41 -> 30546.04 | E47: =E41 -> 10803.6 | F47: =F41 -> 16304.4 | G47: =G41 -> 45522.11 | H47: =H41 -> 35440.48 | I47: =I41 -> 49221.38
B48: Revenue | C48: ='Data Sheet'!E17 -> 322705.76 | D48: ='Data Sheet'!F17 -> 421623.93 | E48: ='Data Sheet'!G17 -> 396727.91 | F48: ='Data Sheet'!H17 -> 303848.91 | G48: ='Data Sheet'!I17 -> 491246.24 | H48: ='Data Sheet'!J17 -> 632291.18 | I48: ='Data Sheet'!K17 -> 591396.26
B49: Net Profit Margin(A) | C49: =C47/C48 -> 0.068501814 | D49: =D47/D48 -> 0.072448544 | E49: =E47/E48 -> 0.027231762 | F49: =F47/F48 -> 0.053659564 | G49: =G47/G48 -> 0.092666582 | H49: =H47/H48 -> 0.056050885 | I49: =I47/I48 -> 0.083229103
B51: Revenue | C51: =C48 -> 322705.76 | D51: =D48 -> 421623.93 | E51: =E48 -> 396727.91 | F51: =F48 -> 303848.91 | G51: =G48 -> 491246.24 | H51: =H48 -> 632291.18 | I51: =I48 -> 591396.26
B52: Average Total Assets | C52: =('Data Sheet'!D66+'Data Sheet'!E66)/2 -> 451878.86 | D52: =('Data Sheet'!E66+'Data Sheet'!F66)/2 -> 475787.84 | E52: =('Data Sheet'!F66+'Data Sheet'!G66)/2 -> 500353.66 | F52: =('Data Sheet'!G66+'Data Sheet'!H66)/2 -> 525055.84 | G52: =('Data Sheet'!H66+'Data Sheet'!I66)/2 -> 562503.58 | H52: =('Data Sheet'!I66+'Data Sheet'!J66)/2 -> 598187.02 | I52: =('Data Sheet'!J66+'Data Sheet'!K66)/2 -> 661444.23
B53: Asset Turnover Ratio(B) | C53: =C51/C52 -> 0.71414219 | D53: =D51/D52 -> 0.88615952 | E53: =E51/E52 -> 0.79289498 | F53: =F51/F52 -> 0.57869827 | G53: =G51/G52 -> 0.87332108 | H53: =H51/H52 -> 1.0570125 | I53: =I51/I52 -> 0.89409846
B55: Average Total Assets | C55: =C52 -> 451878.86 | D55: =D52 -> 475787.84 | E55: =E52 -> 500353.66 | F55: =F52 -> 525055.84 | G55: =G52 -> 562503.58 | H55: =H52 -> 598187.02 | I55: =I52 -> 661444.23
B56: Average Shareholder Equity | C56: =C42 -> 199202.08 | D56: =D42 -> 210476.79 | E56: =E42 -> 211019.62 | F56: =F42 -> 213042.8 | G56: =G42 -> 240241.95 | H56: =H42 -> 270075.1 | I56: =I42 -> 308858.77
B57: Equity Multiplier (C) | C57: =C55/C56 -> 2.2684445 | D57: =D55/D56 -> 2.260524 | E57: =E55/E56 -> 2.3711238 | F57: =F55/F56 -> 2.4645557 | G57: =G55/G56 -> 2.3414045 | H57: =H55/H56 -> 2.2148914 | I57: =I55/I56 -> 2.141575
B59: Return on Equity (A*B*C) | C59: =C57*C53*C49 -> 0.11097239 | D59: =D57*D53*D49 -> 0.14512783 | E59: =E57*E53*E49 -> 0.051197134 | F59: =F57*F53*F49 -> 0.076531103 | G59: =G57*G53*G49 -> 0.18948443 | H59: =H57*H53*H49 -> 0.13122453 | I59: =I57*I53*I49 -> 0.15936533
B61: Return on Asset (ROA)
C62: =C46 -> 43190 | D62: =D46 -> 43555 | E62: =E46 -> 43921 | F62: =F46 -> 44286 | G62: =G46 -> 44651 | H62: =H46 -> 45016 | I62: =I46 -> 45382
B63: Net Profit | C63: =C41 -> 22105.93 | D63: =D41 -> 30546.04 | E63: =E41 -> 10803.6 | F63: =F41 -> 16304.4 | G63: =G41 -> 45522.11 | H63: =H41 -> 35440.48 | I63: =I41 -> 49221.38
B64: Average Total Asset | C64: =C52 -> 451878.86 | D64: =D52 -> 475787.84 | E64: =E52 -> 500353.66 | F64: =F52 -> 525055.84 | G64: =G52 -> 562503.58 | H64: =H52 -> 598187.02 | I64: =I52 -> 661444.23
B65: Net Profit Margin(A) | C65: =C63/C64 -> 0.048920036 | D65: =D63/D64 -> 0.064200968 | E65: =E63/E64 -> 0.021591927 | F65: =F63/F64 -> 0.031052697 | G65: =G63/G64 -> 0.08092768 | H65: =H63/H64 -> 0.059246488 | I65: =I63/I64 -> 0.074415012
B67: ROA - Dupont Equation
C68: =C62 -> 43190 | D68: =D62 -> 43555 | E68: =E62 -> 43921 | F68: =F62 -> 44286 | G68: =G62 -> 44651 | H68: =H62 -> 45016 | I68: =I62 -> 45382
B69: Net Profit | C69: =C63 -> 22105.93 | D69: =D63 -> 30546.04 | E69: =E63 -> 10803.6 | F69: =F63 -> 16304.4 | G69: =G63 -> 45522.11 | H69: =H63 -> 35440.48 | I69: =I63 -> 49221.38
B70: Revenue | C70: =C48 -> 322705.76 | D70: =D48 -> 421623.93 | E70: =E48 -> 396727.91 | F70: =F48 -> 303848.91 | G70: =G48 -> 491246.24 | H70: =H48 -> 632291.18 | I70: =I48 -> 591396.26
B71: Net Profit Margin(A) | C71: =C69/C70 -> 0.068501814 | D71: =D69/D70 -> 0.072448544 | E71: =E69/E70 -> 0.027231762 | F71: =F69/F70 -> 0.053659564 | G71: =G69/G70 -> 0.092666582 | H71: =H69/H70 -> 0.056050885 | I71: =I69/I70 -> 0.083229103
B73: Revenue | C73: =C70 -> 322705.76 | D73: =D70 -> 421623.93 | E73: =E70 -> 396727.91 | F73: =F70 -> 303848.91 | G73: =G70 -> 491246.24 | H73: =H70 -> 632291.18 | I73: =I70 -> 591396.26
B74: Average Total Assets | C74: =C64 -> 451878.86 | D74: =D64 -> 475787.84 | E74: =E64 -> 500353.66 | F74: =F64 -> 525055.84 | G74: =G64 -> 562503.58 | H74: =H64 -> 598187.02 | I74: =I64 -> 661444.23
B75: Asset Turnover Ratio(B) | C75: =C73/C74 -> 0.71414219 | D75: =D73/D74 -> 0.88615952 | E75: =E73/E74 -> 0.79289498 | F75: =F73/F74 -> 0.57869827 | G75: =G73/G74 -> 0.87332108 | H75: =H73/H74 -> 1.0570125 | I75: =I73/I74 -> 0.89409846
B77: Return on Asset (A*B) | C77: =C75*C71 -> 0.048920036 | D77: =D75*D71 -> 0.064200968 | E77: =E75*E71 -> 0.021591927 | F77: =F75*F71 -> 0.031052697 | G77: =G75*G71 -> 0.08092768 | H77: =H75*H71 -> 0.059246488 | I77: =I75*I71 -> 0.074415012

Sheet Rm
B3: Returns on Markets
B4: Year | C4: Annual
B5: 2000 | C5: -0.1465 | E5: Average Return | G5: =AVERAGE(C5:C29) -> 0.153348
B6: 2001 | C6: -0.1618 | E6: Dividend Yeid | G6: 0.0139
B7: 2002 | C7: 0.0325 | E7: Total Market Return | G7: =G6+G5 -> 0.167248
B8: 2003 | C8: 0.719
B9: 2004 | C9: 0.1068
B10: 2005 | C10: 0.3634
B11: 2006 | C11: 0.3983
B12: 2007 | C12: 0.5477
B13: 2008 | C13: -0.5179
B14: 2009 | C14: 0.7576
B15: 2010 | C15: 0.1795
B16: 2011 | C16: -0.2462
B17: 2012 | C17: 0.277
B18: 2013 | C18: 0.0676
B19: 2014 | C19: 0.3139
... B29: 2024 | C29: 0.0875

Sheet Comps Data
B2: S.No. | C2: Name | D2: CMP Rs. | E2: No. Eq. Shares Cr. | F2: Market Value | G2: Debt Rs.Cr. | H2: Cash End Rs.Cr. | I2: Net Debt' | J2: EV | K2: Sales Rs.Cr. | L2: EBITDA | M2: NP 12M Rs.Cr. | P2: EV Rs.Cr. | Q2: Mar Cap Rs.Cr.
B3: 1 | C3: O N G C | D3: 244.55 | E3: 1258.03 | F3: =E3*D3 -> 307651.24 | G3: 187817.31 | H3: 27177.76 | I3: =G3-H3 -> 160639.55 | J3: =F3+G3-H3 -> 468290.79 | K3: 663262.31 | L3: =L13+M13 -> 102289.87 | M3: 38328.59 | P3: 468465.51 | Q3: 307825.96
B4: 2 | C4: Oil India | D4: 431.1 | E4: 162.66 | F4: =E4*D4 -> 70122.726 | G4: 30645.24 | H4: 7197.17 | I4: =G4-H4 -> 23448.07 | J4: =F4+G4-H4 -> 93570.796 | K4: 32512.48 | L4: =L14+M14 -> 12823.92 | M4: 7039.63 | P4: 93571.14 | Q4: 70123.07
B5: 3 | C5: Deep Industries | D5: 422.5 | E5: 6.4 | F5: =E5*D5 -> 2704 | G5: 205.37 | H5: 51.26 | I5: =G5-H5 -> 154.11 | J5: =F5+G5-H5 -> 2858.11 | K5: 576.13 | L5: =L15+M15 -> 263.8 | M5: -78.76 | P5: 2857.16 | Q5: 2703.05
B6: 4 | C6: Hind.Oil Explor. | D6: 182.3 | E6: 13.22 | F6: =E6*D6 -> 2410.006 | G6: 145.13 | H6: 68.5 | I6: =G6-H6 -> 76.63 | J6: =F6+G6-H6 -> 2486.636 | K6: 667.09 | L6: =L16+M16 -> 266.07 | M6: 166.66 | P6: 2419.58 | Q6: 2410.66
B7: 5 | C7: Asian Energy | D7: 313.25 | E7: 4.48 | F7: =E7*D7 -> 1403.36 | G7: 24.07 | H7: 77.7 | I7: =G7-H7 -> -53.63 | J7: =F7+G7-H7 -> 1349.73 | K7: 465.04 | L7: =L17+M17 -> 77.71 | M7: 42.16 | P7: 1345.62 | Q7: 1399.25
B8: 6 | C8: Selan Expl. Tech | D8: 546.4 | E8: 1.52 | F8: =E8*D8 -> 830.528 | G8: 4.01 | H8: 23.57 | I8: =G8-H8 -> -19.56 | J8: =F8+G8-H8 -> 810.968 | K8: 258.08 | L8: =L18+M18 -> 103.41 | M8: 73.98 | P8: 810.44 | Q8: 830
B9: 7 | C9: Guj.Nat.Resour. | D9: 46.94 | E9: 12.84 | F9: =E9*D9 -> 602.7096 | G9: 54.57 | H9: 5.45 | I9: =G9-H9 -> 49.12 | J9: =F9+G9-H9 -> 651.8296 | K9: 25.6 | L9: =L19+M19 -> 7.45 | M9: -1.73 | P9: 652.26 | Q9: 602.72
B10: 8 | C10: Aban Offshore | D10: 44.18 | E10: 5.84 | F10: =E10*D10 -> 258.0112 | G10: 15370.14 | H10: 43.51 | I10: =G10-H10 -> 15326.63 | J10: =F10+G10-H10 -> 15584.641 | K10: 497.41 | L10: =L20+M20 -> 289.48 | M10: -969.67 | P10: 15518.13 | Q10: 257.86
B12: S.No. | C12: Name | D12: CMP Rs. | E12: No. Eq. Shares Cr. | F12: Debt Rs.Cr. | G12: Cash End Rs.Cr. | H12: EV Rs.Cr. | J12: Sales Rs.Cr. | K12: NP 12M Rs.Cr. | L12: EBIT 12M Rs.Cr. | M12: Dep 12M Rs.Cr. | N12: Mar Cap Rs.Cr.
B13: 1 | C13: O N G C | D13: 244.55 | E13: 1258.03 | F13: 187817.31 | G13: 27177.76 | H13: 468465.51 | J13: 663262.31 | K13: 38328.59 | L13: 67083.9 | M13: 35205.97 | N13: 307825.96
B14: 2 | C14: Oil India | D14: 431.1 | E14: 162.66 | F14: 30645.24 | G14: 7197.17 | H14: 93571.14 | J14: 32512.48 | K14: 7039.63 | L14: 10505.69 | M14: 2318.23 | N14: 70123.07
B15: 3 | C15: Deep Industries | D15: 422.5 | E15: 6.4 | F15: 205.37 | G15: 51.26 | H15: 2857.16 | J15: 576.13 | K15: -78.76 | L15: 222.63 | M15: 41.17 | N15: 2703.05
B16: 4 | C16: Hind.Oil Explor. | D16: 182.3 | E16: 13.22 | F16: 145.13 | G16: 68.5 | H16: 2419.58 | J16: 667.09 | K16: 166.66 | L16: 189.89 | M16: 76.18 | N16: 2410.66
B17: 5 | C17: Asian Energy | D17: 313.25 | E17: 4.48 | F17: 24.07 | G17: 77.7 | H17: 1345.62 | J17: 465.04 | K17: 42.16 | L17: 60 | M17: 17.71 | N17: 1399.25
B18: 6 | C18: Selan Expl. Tech | D18: 546.4 | E18: 1.52 | F18: 4.01 | G18: 23.57 | H18: 810.44 | J18: 258.08 | K18: 73.98 | L18: 98.93 | M18: 4.48 | N18: 830
B19: 7 | C19: Guj.Nat.Resour. | D19: 46.94 | E19: 12.84 | F19: 54.57 | G19: 5.45 | H19: 652.26 | J19: 25.6 | K19: -1.73 | L19: 0.61 | M19: 6.84 | N19: 602.72
B20: 8 | C20: Aban Offshore | D20: 44.18 | E20: 5.84 | F20: 15370.14 | G20: 43.51 | H20: 15518.13 | J20: 497.41 | K20: -969.67 | L20: 165.67 | M20: 123.81 | N20: 257.86

Sheet Forecasting(REGRESSION)
B1: ONGC
B2: Year Weight | C2: Year | D2: Sales | E2: Sales Growth
B3: 1 | C3: 2014 | D3: 174121
B4: 2 | C4: 2015 | D4: 160923 | E4: =D4/D3 -1 -> -0.075797865
B5: 3 | C5: 2016 | D5: 124036 | E5: =D5/D4 -1 -> -0.22922143
B6: 4 | C6: 2017 | D6: 282506 | E6: =D6/D5 -1 -> 1.277613
B7: 5 | C7: 2018 | D7: 322706 | E7: =D7/D6 -1 -> 0.14229786
B8: 6 | C8: 2019 | D8: 421624 | E8: =D8/D7 -1 -> 0.30652668
B9: 7 | C9: 2020 | D9: 396728 | E9: =D9/D8 -1 -> -0.059047872 | G9: SUMMARY OUTPUT
B10: 8 | C10: 2021 | D10: 303849 | E10: =D10/D9 -1 -> -0.23411254
B11: 9 | C11: 2022 | D11: 491246 | E11: =D11/D10 -1 -> 0.61674384 | G11: Regression Statistics
B12: 10 | C12: 2023 | D12: 632291 | E12: =D12/D11 -1 -> 0.28711684 | G12: Multiple R | H12: 0.91869155
B13: 11 | C13: 2024 | D13: 591396 | E13: =D13/D12 -1 -> -0.064677498 | G13: R Square | H13: 0.84399416
B14: 12 | C14: 2025 | D14: =$H$25+B14*$H$26 -> 637776.09 | E14: =D14/D13 -1 -> 0.078424763 | G14: Adjusted R Square | H14: 0.82666017
B15: 13 | C15: 2026 | D15: =$H$25+B15*$H$26 -> 684959.59 | E15: =D15/D14 -1 -> 0.073981293 | G15: Standard Error | H15: 70919.547
B16: 14 | C16: 2027 | D16: =$H$25+B16*$H$26 -> 732143.09 | E16: =D16/D15 -1 -> 0.068885086 | G16: Observations | H16: 11
B17: 15 | C17: 2028 | D17: =$H$25+B17*$H$26 -> 779326.59 | E17: =D17/D16 -1 -> 0.064445736
B18: 16 | C18: 2029 | D18: =$H$25+B18*$H$26 -> 826510.09 | E18: =D18/D17 -1 -> 0.060543937 | G18: ANOVA
D19: =FORECAST(B14,$D$3:$D$13,$B$3:$B$13) -> 637776.09 | H19: df | I19: SS | J19: MS | K19: F | L19: Significance F
D20: =FORECAST(B15,$D$3:$D$13,$B$3:$B$13) -> 684959.59 | G20: Regression | H20: 1 | I20: 2.4489109e+11 | J20: 2.4489109e+11 | K20: 48.690147 | L20: 6.4816003e-05
D21: =FORECAST(B16,$D$3:$D$13,$B$3:$B$13) -> 732143.09 | G21: Residual | H21: 9 | I21: 4.5266239e+10 | J21: 5.0295821e+09
D22: =FORECAST(B17,$D$3:$D$13,$B$3:$B$13) -> 779326.59 | G22: Total | H22: 10 | I22: 2.9015733e+11
D23: =FORECAST(B18,$D$3:$D$13,$B$3:$B$13) -> 826510.09
H24: Coefficients | I24: Standard Error | J24: t Stat | K24: P-value | L24: Lower 95% | M24: Upper 95% | N24: Lower 95.0% | O24: Upper 95.0%
B25: Arthematic Growth | D25: =AVERAGE(E4:E13) -> 0.1967441 | G25: Intercept | H25: 71574.091 | I25: 45861.529 | J25: 1.5606565 | K25: 0.15303751 | L25: -32171.895 | M25: 175320.08 | N25: -32171.895 | O25: 175320.08
B26: Geometric Growth | D26: =_xlfn.RRI(B13,D3,D13) -> 0.1175712 | G26: Year Weight | H26: 47183.5 | I26: 6761.9135 | J26: 6.9778325 | K26: 6.4816003e-05 | L26: 31886.989 | M26: 62480.011 | N26: 31886.989 | O26: 62480.011
B27: Standard Deviation | D27: =_xlfn.STDEV.S(E4:E13) -> 0.46463786

Sheet Raw FS
B2: Particulars | C2: 42064 | D2: 42430 | E2: 42795 | F2: 43160 | G2: 43525 | H2: 43891 | I2: 44256 | J2: 44621 | K2: 44986 | L2: 45352
B4: Equity Capital | C4: 4278 | D4: 4278 | E4: 6417 | F4: 6417 | G4: 6290 | H4: 6290 | I4: 6290 | J4: 6290 | K4: 6290 | L4: 6290
B5: Reserves | C5: 176177 | D5: 193536 | E5: 187969 | F5: 197602 | G5: 210644 | H5: 198814 | I5: 214691 | J5: 253213 | K5: 274357 | L5: 330780
B6: Borrowings -
B7: Long term Borrowings | C7: 47575 | D7: 40229 | E7: 52772 | F7: 55025 | G7: 52168 | H7: 72932 | I7: 79162 | J7: 88043 | K7: 98360 | L7: 77952
B8: Short term Borrowings | C8: 5345 | D8: 4318 | E8: 21627 | F8: 46221 | G8: 49332 | H8: 31506 | I8: 39899 | J8: 19733 | K8: 30826 | L8: 41803
B9: Lease Liabilities | C9: 0 | D9: 0 | E9: 0 | F9: 0 | G9: 707 | H9: 13170 | I9: 14126 | J9: 14210 | K9: 13069 | L9: 33425
B10: Other Borrowings | C10: 1024 | D10: 953 | E10: 5629 | F10: 5304 | G10: 5534 | H10: 11865 | I10: 0 | J10: 0 | K10: 0 | L10: 0
B11: Other Liabilities -
B12: Non controlling int | C12: 2473 | D12: 2652 | E12: 13292 | F12: 15606 | G12: 18106 | H12: 18406 | I12: 21616 | J12: 23825 | K12: 20608 | L12: 28020
B13: Trade Payables | C13: 30466 | D13: 29778 | E13: 24014 | F13: 26485 | G13: 30557 | H13: 23064 | I13: 27251 | J13: 40186 | K13: 33643 | L13: 37490
B14: Advance from Customers | C14: 127 | D14: 69 | E14: 805 | F14: 917 | G14: 972 | H14: 1359 | I14: 1268 | J14: 1953 | K14: 1325 | L14: 1424
B15: Other liability items | C15: 70381 | D15: 65960 | E15: 132000 | F15: 105656 | G15: 118032 | H15: 130958 | I15: 137445 | J15: 135807 | K15: 134637 | L15: 152588
B16: Total Liabilities | C16: 337847 | D16: 341772 | E16: 444525 | F16: 459232 | G16: 492343 | H16: 508364 | I16: 541748 | J16: 583260 | K16: 613115 | L16: 709774
B18: Fixed Assets -
B19: Land | C19: 2441 | D19: 1161 | E19: 1979 | F19: 2203 | G19: 2338 | H19: 6798 | I19: 7550 | J19: 8582 | K19: 8970 | L19: 9819
B20: Building | C20: 4487 | D20: 2495 | E20: 10661 | F20: 11734 | G20: 13459 | H20: 14498 | I20: 15686 | J20: 17552 | K20: 18545 | L20: 20729
B21: Plant Machinery | C21: 159917 | D21: 33485 | E21: 65957 | F21: 70048 | G21: 77113 | H21: 97348 | I21: 103871 | J21: 116943 | K21: 130419 | L21: 166783
B22: Equipments | C22: 925 | D22: 944 | E22: 2981 | F22: 3463 | G22: 4351 | H22: 5156 | I22: 5727 | J22: 6399 | K22: 6454 | L22: 7594
B23: Furniture n fittings | C23: 1765 | D23: 857 | E23: 1061 | F23: 1416 | G23: 1628 | H23: 1671 | I23: 1705 | J23: 1741 | K23: 1838 | L23: 2105
B24: Railway sidings | C24: 0 | D24: 0 | E24: 0 | F24: 0 | G24: 0 | H24: 633 | I24: 681 | J24: 762 | K24: 793 | L24: 791
B25: Vehicles | C25: 1175 | D25: 574 | E25: 831 | F25: 1075 | G25: 1381 | H25: 3936 | I25: 6174 | J25: 6935 | K25: 7366 | L25: 8737
B26: Intangible Assets | C26: 26935 | D26: 20987 | E26: 20718 | F26: 20776 | G26: 14332 | H26: 14597 | I26: 23923 | J26: 24744 | K26: 26702 | L26: 27495
B27: Other fixed assets | C27: 91775 | D27: 120078 | E27: 130194 | F27: 143761 | G27: 145200 | H27: 140957 | I27: 140299 | J27: 144507 | K27: 132213 | L27: 146442
B28: Gross Block | C28: 289420 | D28: 180582 | E28: 234384 | F28: 254476 | G28: 259802 | H28: 285595 | I28: 305615 | J28: 328166 | K28: 333300 | L28: 390494
B29: Accumulated Depreciation | C29: 107319 | D29: 14304 | E29: 23258 | F29: 28418 | G29: 29411 | H29: 41702 | I29: 61869 | J29: 73763 | K29: 82436 | L29: 91996
B30: Net Block | C30: =C28-C29 -> 182101 | D30: =D28-D29 -> 166278 | E30: =E28-E29 -> 211126 | F30: =F28-F29 -> 226058 | G30: =G28-G29 -> 230391 | H30: =H28-H29 -> 243893 | I30: =I28-I29 -> 243746 | J30: =J28-J29 -> 254403 | ... L30: =L28-L29 -> 298498
B32: CWIP | C32: 63393 | D32: 57668 | E32: 59042 | F32: 61512 | G32: 69056 | H32: 83832 | I32: 100309 | J32: 106719 | K32: 113945 | L32: 116022
B33: Investments | C33: 4749 | D33: 33387 | E33: 70746 | F33: 67335 | G33: 66909 | H33: 56755 | I33: 60320 | J33: 66642 | K33: 78873 | L33: 102207
B35: Other Assets
B36: Inventories | C36: 11355 | D36: 10762 | E36: 30555 | F36: 31254 | G36: 35949 | H36: 34065 | I36: 45736 | J36: 55360 | K36: 45238 | L36: 53255
B37: Trade receivables | C37: 18816 | D37: 8332 | E37: 12547 | F37: 13899 | G37: 15396 | H37: 9173 | I37: 16016 | J37: 19187 | K37: 18752 | L37: 19763
B38: Cash Equivalents | C38: 16097 | D38: 24689 | E38: 13213 | F38: 5063 | G38: 4820 | H38: 9640 | I38: 7192 | J38: 6841 | K38: 29140 | L38: 36690
B39: Loans n Advances | C39: 820 | D39: -683 | E39: -546 | F39: -618 | G39: -815 | H39: -1268 | I39: -817 | J39: -911 | K39: -1060 | L39: -1237
B40: Other asset items | C40: 42683 | D40: 41340 | E40: 47843 | F40: 54730 | G40: 70636 | H40: 72274 | I40: 69245 | J40: 75019 | K40: 77407 | L40: 84620
B41: Total Assets | C41: 337847 | D41: 341772 | E41: 444525 | F41: 459232 | G41: 492343 | H41: 508364 | I41: 541748 | J41: 583260 | K41: 613115 | L41: 709774
B46: Cash from Operating Activity - | C46: 33950 | D46: 46292 | E46: 45780 | F46: 56792 | G46: 61458 | H46: 70593 | I46: 47185 | J46: 78248 | K46: 86062 | L46: 99263
B47: Profit from operations | C47: 54535 | D47: 46768 | E47: 58077 | F47: 67335 | G47: 86600 | H47: 67907 | I47: 58661 | J47: 88028 | K47: 92907 | L47: 113693
B48: Receivables | C48: -6040 | D48: 7835 | E48: -2128 | F48: -1744 | G48: -2252 | H48: 6145 | I48: -6666 | J48: -3067 | K48: 615 | L48: -1085
B49: Inventory | C49: 4462 | D49: 491 | E49: -6594 | F49: -751 | G49: -4682 | H49: 957 | I49: -11681 | J49: -9672 | K49: 9235 | L49: -8135
B50: Payables | C50: -3972 | D50: 579 | E50: -6214 | F50: 5875 | G50: 9441 | H50: 6161 | I50: 13406 | J50: 18358 | K50: -4639 | L50: 9639
B51: Loans Advances | C51: -3007 | D51: 145 | E51: 123 | F51: -1866 | G51: -6374 | H51: 2622 | I51: 5236 | J51: -451 | K51: 526 | L51: -1186
... B75: Net Cash Flow | C75: -6749 | D75: -935 | E75: 99 | F75: -97 | G75: 1001 | H75: 708 | I75: -195 | J75: 1261 | K75: -1504 | L75: -3591

Sheet Cash Flow Data
C2: 41334 | D2: 41699 | E2: 42064 | F2: 42430 | G2: 42795 | H2: 43160 | I2: 43525 | J2: 43891 | K2: 44256 | L2: 44621 | M2: 44986 | N2: 45352
B3: Cash from Operating Activity - | C3: 39874 | D3: 53270 | E3: 33950 | F3: 46292 | G3: 45780 | H3: 56792 | I3: 61458 | J3: 70593 | K3: 47185 | L3: 78248 | M3: 86062 | N3: 99263
B4: Profit from operations | C4: 58306 | D4: 59570 | E4: 54535 | F4: 46768 | G4: 58077 | H4: 67335 | I4: 86600 | J4: 67907 | K4: 58661 | L4: 88028 | M4: 92907 | N4: 113693
B5: Receivables | C5: -4431 | D5: 571 | E5: -6040 | F5: 7835 | G5: -2128 | H5: -1744 | I5: -2252 | J5: 6145 | K5: -6666 | L5: -3067 | M5: 615 | N5: -1085
B6: Inventory | C6: 292 | D6: -2202 | E6: 4462 | F6: 491 | G6: -6594 | H6: -751 | I6: -4682 | J6: 957 | K6: -11681 | L6: -9672 | M6: 9235 | N6: -8135
B7: Payables | C7: 189 | D7: 20772 | E7: -3972 | F7: 579 | G7: -6214 | H7: 5875 | I7: 9441 | J7: 6161 | K7: 13406 | L7: 18358 | M7: -4639 | N7: 9639 | S7: =SUM(E4:E12) -> 22316
B8: Loans Advances | C8: -881 | D8: -137 | E8: -3007 | F8: 145 | G8: 123 | H8: -1866 | I8: -6374 | J8: 2622 | K8: 5236 | L8: -451 | M8: 526 | N8: -1186
B9: Other WC items | C9: -1176 | D9: -14801 | E9: -3078 | F9: -1863 | G9: 12140 | H9: -1261 | I9: -5951 | J9: -3182 | K9: -4235 | L9: -1452 | M9: 2971 | N9: 902
B10: Working capital changes | C10: -6007 | D10: 4203 | E10: -11635 | F10: 7186 | G10: -2673 | H10: 254 | I10: -9817 | J10: 12702 | K10: -3940 | L10: 3716 | M10: 8709 | N10: 136
B11: Direct taxes | C11: -12416 | D11: -10567 | E11: -9029 | F11: -7662 | G11: -9624 | H11: -10798 | I11: -15326 | J11: -10017 | K11: -7537 | L11: -13496 | M11: -15554 | N11: -14566
B12: Other operating items | C12: -9 | D12: 64 | E12: 80 | F12: 0 | G12: 0 | H12: 0 | I12: 0 | J12: 0 | K12: 0 | L12: 0 | M12: 0 | N12: 0
B13: Cash from Investing Activity - | C13: -41220 | D13: -63633 | E13: -30058 | F13: -38256 | G13: -43815 | H13: -66798 | I13: -37132 | J13: -53159 | K13: -39141 | L13: -41197 | M13: -74690 | N13: -57203
B14: Fixed assets purchased | C14: -17961 | D14: -14938 | E14: -16906 | F14: -15120 | G14: -20524 | H14: -27815 | I14: -25963 | J14: -42258 | K14: -32319 | L14: -33457 | M14: -38719 | N14: -37916
B15: Fixed assets sold | C15: 17 | D15: 3 | E15: 9 | F15: 26 | G15: 189 | H15: 83 | I15: 203 | J15: 401 | K15: 281 | L15: 367 | M15: 339 | N15: 251
B16: Investments purchased | C16: -83 | D16: 0 | E16: 0 | F16: -3003 | G16: -631 | H16: -240 | I16: -236 | J16: -235 | K16: -327 | L16: -836 | M16: -291 | N16: -8
B17: Investments sold | C17: 879 | D17: 65 | E17: 33 | F17: 0 | G17: 140 | H17: 5010 | I17: 0 | J17: 0 | K17: 0 | L17: 0 | M17: 0 | N17: 32
B18: Subsidy received | C18: 0 | D18: 0 | E18: 0 | F18: 0 | G18: 0 | H18: 0 | I18: 0 | J18: 0 | K18: 0 | L18: 0 | M18: 165 | N18: 5
B19: Interest received | C19: 3594 | D19: 3145 | E19: 2993 | F19: 2892 | G19: 2807 | H19: 2465 | I19: 1932 | J19: 1797 | K19: 1606 | L19: 1509 | M19: 2386 | N19: 4416
... B32: Net Cash Flow | C32: -8273 | D32: 4862 | E32: -6749 | F32: -935 | G32: 99 | H32: -97 | I32: 1001 | J32: 708 | K32: -195 | L32: 1261 | M32: -1504 | N32: -3591
